Workbook

Sheet Cronograma
A1: CRONOGRAMA PSP6 · ENGENHARIA DE PRODUTO
G3: Concluído | K3: Em andamento | O3: Previsto | S3: ◆ Entrega/marco
G4: Feriado | K4: Prova | O4: Evento | S4: 2ª avaliação
A6: 1 · GANTT DAS ATIVIDADES DO PROJETO
A7: Fase | B7: Atividade | C7: Início | D7: Fim | E7: Situação | F7: Agosto | J7: Setembro | N7: Outubro | R7: Novembro | W7: Dezembro
F8: 10/08 | G8: 17/08 | H8: 24/08 | I8: 31/08 | J8: 07/09 | K8: 14/09 | L8: 21/09 | M8: 28/09 | N8: 05/10 | O8: 12/10 | P8: 19/10 | Q8: 26/10 | R8: 02/11 | S8: 09/11 | T8: 16/11 | U8: 23/11 | V8: 30/11 | W8: 07/12 | X8: 09/12
A9: Pré-desenvolvimento | B9: Ambientação: palestras, vídeos e formação do grupo | C9: 46244 | D9: 46244 | E9: Concluído
B10: Local/atividade, usuários e clientes (Lauff et al., p. 31) | C10: 46251 | D10: 46251 | E10: Concluído
B11: Levantamento de informações: entrevistas, visita técnica e pesquisa bibliográfica (Lauff et al., p. 87) | C11: 46251 | D11: 46265 | E11: Concluído
B12: 1ª Entrega de PSP6 — apresentação da sustentação do problema | C12: 46265 | D12: 46265 | E12: Concluído | I12: ◆
A13: Projeto informacional | B13: Ciclo de vida, necessidades dos clientes e matriz de atributos | C13: 46265 | D13: 46272 | E13: Concluído
B14: Requisitos dos clientes e requisitos valorizados (Kano, Mudge e Pareto) | C14: 46272 | D14: 46279 | E14: Concluído
B15: Benchmarking, QFD e especificações-meta | C15: 46279 | D15: 46286 | E15: Concluído
B16: Consolidação do relatório em normas ABNT | C16: 46279 | D16: 46293 | E16: Concluído
B17: 2ª Entrega de PSP6 — relatório consolidado | C17: 46293 | D17: 46293 | E17: Concluído | M17: ◆
A18: Avaliações | B18: Primeira prova de produto | C18: 46300 | D18: 46300 | E18: Concluído | N18: ◆
A19: Projeto conceitual | B19: Modelagem funcional: função global, FAST e funções parciais (3 modelos) | C19: 46300 | D19: 46321 | E19: Modelagem revisada; 23 vínculos e 17 funções
B20: Seleção da modelagem pela matriz de Pugh | C20: 46321 | D20: 46321 | E20: Comparação funcional feita; M1 priorizada
B21: Princípios de solução: matriz morfológica e TRIZ | C21: 46321 | D21: 46335 | E21: Em andamento
B22: Módulos do produto: MIM e arquitetura modular | C22: 46335 | D22: 46342 | E22: MIM herdada; reavaliar sob M1
B23: Concepções e matriz de Pugh das concepções | C23: 46342 | D23: 46349 | E23: Previsto
B24: Otimização: lista de materiais, viabilidade técnica e análise de valor | C24: 46349 | D24: 46356 | E24: Previsto
A25: Fechamento | B25: Preparação da apresentação final | C25: 46349 | D25: 46358 | E25: Previsto
B26: Apresentação final de PSP6 | C26: 46358 | D26: 46358 | E26: Previsto | V26: ◆
A27: Avaliações | B27: Segunda avaliação | C27: 46363 | D27: 46363 | E27: Previsto | W27: ◆
B28: Revisão de nota | C28: 46365 | D28: 46365 | E28: Previsto
A30: 2 · CRONOGRAMA OFICIAL DA DISCIPLINA
A31: Planejamento | B31: Entregas | C31: Data | D31: Observação | F31: Referências / Eng. Produto
A32: Aula 01 | C32: 46244 | F32: Palestras, vídeos
A33: Aula 02 | B33: Local/Atividade — Usuários/Clientes | C33: 46251 | F33: Lauff et al., Design Innovation Handbook (responder as perguntas da página 31)
A34: Aula 03 | B34: Levantamento das informações (sustentação do problema) | C34: 46258 | F34: Entrevistas, visitas técnicas, levantamento bibliográfico. Lauff et al., Design Innovation Handbook (responder as perguntas da página 87)
A35: Aula 04 | B35: Só apresentação | C35: 46265 | D35: 1ª Entrega de PSP6
A36: — | C36: 46272 | D36: Feriado
A37: Aula 05 | B37: Requisitos dos clientes e requisitos valorizados | C37: 46279 | F37: Aulas 6 e 7
A38: Aula 06 | B38: Especificações-meta | C38: 46286 | F38: Aulas 8 e 9 (QFD)
A39: Aula 07 | B39: Entrega do relatório consolidado | C39: 46293 | D39: 2ª Entrega de PSP6 | F39: Normas ABNT
A40: — | C40: 46300 | D40: Primeira prova de produto
A41: — | C41: 46307 | D41: Feriado
A42: — | C42: 46314 | D42: ENEGEP 2026
A43: Aula 08 | B43: Modelagem funcional (3 modelos) e seleção da modelagem | C43: 46321 | F43: Aulas 11, 12 e 13 (síntese funcional)
A44: — | C44: 46328 | D44: Feriado
A45: Aula 09 | B45: Princípios de solução | C45: 46335 | F45: Matriz morfológica, TRIZ (aulas 14 e 15)
A46: Aula 10 | B46: Módulos do produto | C46: 46342 | F46: MIM (aulas 15 e 16)
A47: Aula 11 | B47: Concepção | C47: 46349 | F47: Aulas 17, 18 e 19
A48: Aula 12 | B48: Otimização | C48: 46356 | F48: Aulas 19, 20, 21 e 24
A49: PSP6 | B49: Apresentação final de PSP6 | C49: 46358 | D49: Entrega final
A50: — | C50: 46363 | D50: Segunda avaliação
A51: — | C51: 46365 | D51: Revisão de nota
A53: Fonte: cronograma da turma de segunda-feira divulgado pela disciplina. As barras do Gantt marcam as semanas de trabalho do grupo; o losango (◆) marca entregas e avaliações. A coluna destacada em bege é a semana corrente.

Sheet Revisão
A1: Revisão do escopo do produto
A2: Síntese do recorte | D2: Tipo de projeto | E2: Plataforma
A3: Pergunta | B3: Resposta sustentada | D3: Estratégia de produção | E3: ATO
A4: Onde ocorre o elo crítico? | B4: Hipótese de foco: transporte do distribuidor à obra, descarga e manuseios. Relatos iniciais não medem a participação causal de cada etapa. | D4: Arquitetura | E4: Modular (premissa em avaliação)
A5: Quem absorve diretamente? | B5: No relato do distribuidor, reposição e nova logística são absorvidas por ele. Confirmar em registros; não generalizar a todos os distribuidores.
A6: Por que o problema persiste? | B6: Existe tensão entre maior proteção e preço competitivo. As alternativas de alta proteção podem elevar custo e volume logístico.
A8: Cadeia observada
A9: Etapa | B9: Fabricação/distribuição | C9: Transporte externo | D9: Recebimento/abertura | E9: Movimentação interna | F9: Instalação | G9: Situação atual
A10: Papel | B10: Preparar e expedir | C10: Levar até a obra | D10: Descarregar e conferir | E10: Levar até o ponto de uso | F10: Instalar a louça | G10: Mapeada
A11: Evidência disponível | B11: Escala setorial | C11: Distribuidor associa avarias ao trecho | D11: Peças podem chegar trincadas | E11: Quedas no transporte manual sem acesso para carrinho | F11: A avaria pode se tornar visível nesta etapa | G11: Qualitativa
A12: Risco | B12: Dano latente | C12: Impacto/vibração/manuseio | D12: Fragmentos na abertura | E12: Queda e esforço manual | F12: Retrabalho e risco ao trabalhador | G12: A validar
A13: Decisão futura | B13: Embalagem e unitização | C13: Proteção e movimentação | D13: Conferência segura | E13: Acesso e auxílio de transporte | F13: Critério de aceitação | G13: Projeto informacional
A15: Enunciados de projeto
A16: Problema definido | B16: A quebra no transporte entre distribuidor e obra pode permanecer oculta até o recebimento ou a instalação. O evento gera reposição, nova entrega, atraso, desperdício e exposição do trabalhador a peças avariadas ou fragmentos cortantes.
A17: Opportunity statement | B17: Como podemos reduzir as avarias de louças sanitárias no transporte entre o distribuidor e a obra, diminuindo custos de reposição, atrasos e riscos aos trabalhadores, sem inviabilizar comercialmente o produto ou a operação?
B20: 14/10/2026 — revisão do projeto conceitual
B21: Corrigidos: evidência versus estimativa na V0; fronteiras e inspeção; histórico Pugh (12/0/40) e revisão pendente; conceitos TRIZ; combinações morfológicas; linha de base por RP e custo completo. MIM, módulos e concepções preparados como propostas, sem resultados de ensaio.
A24: Feedback 2 — revisão do escopo antes da definição do ciclo de vida | B24: Feedback 2 — revisão do escopo antes da definição do ciclo de vida | C24: Feedback 2 — revisão do escopo antes da definição do ciclo de vida | D24: Feedback 2 — revisão do escopo antes da definição do ciclo de vida | E24: Feedback 2 — revisão do escopo antes da definição do ciclo de vida | F24: Feedback 2 — revisão do escopo antes da definição do ciclo de vida | G24: Feedback 2 — revisão do escopo antes da definição do ciclo de vida
A25: Atividade | B25: Objetivo | C25: Entrada | D25: Entrega | E25: Aplicação | F25: Natureza | G25: Situação
A26: Revisar escopo | B26: Reavaliar problema, atores, fronteiras, restrições e premissas | C26: Pré-desenvolvimento e devolutiva | D26: Recorte revisto e limites | E26: Proteção e movimentação distribuidor–obra; retorno | F26: Decisão de planejamento | G26: Revisão documental aplicada
A27: Definir ciclo de vida | B27: Descrever a trajetória da solução dentro do escopo revisto | C27: Recorte de projeto revisto | D27: Ciclo macro, 13 fases operacionais, atores e estados | E27: Obtenção, uso, manutenção, retorno e fim de vida | F27: Modelo para levantar necessidades | G27: Descrito no relatório e na Lista de Necessidades
A29: Alcance: uma obra residencial observada e duas entrevistas (operário e distribuidor). A solução é uma hipótese para esse contexto; ampliar campo, mix e condições de uso antes de afirmar abrangência. A taxa de avaria e o custo real ainda não foram medidos. | B29: Alcance: uma obra residencial observada e duas entrevistas (operário e distribuidor). A solução é uma hipótese para esse contexto; ampliar campo, mix e condições de uso antes de afirmar abrangência. A taxa de avaria e o custo real ainda não foram medidos. | C29: Alcance: uma obra residencial observada e duas entrevistas (operário e distribuidor). A solução é uma hipótese para esse contexto; ampliar campo, mix e condições de uso antes de afirmar abrangência. A taxa de avaria e o custo real ainda não foram medidos. | D29: Alcance: uma obra residencial observada e duas entrevistas (operário e distribuidor). A solução é uma hipótese para esse contexto; ampliar campo, mix e condições de uso antes de afirmar abrangência. A taxa de avaria e o custo real ainda não foram medidos. | E29: Alcance: uma obra residencial observada e duas entrevistas (operário e distribuidor). A solução é uma hipótese para esse contexto; ampliar campo, mix e condições de uso antes de afirmar abrangência. A taxa de avaria e o custo real ainda não foram medidos. | F29: Alcance: uma obra residencial observada e duas entrevistas (operário e distribuidor). A solução é uma hipótese para esse contexto; ampliar campo, mix e condições de uso antes de afirmar abrangência. A taxa de avaria e o custo real ainda não foram medidos. | G29: Alcance: uma obra residencial observada e duas entrevistas (operário e distribuidor). A solução é uma hipótese para esse contexto; ampliar campo, mix e condições de uso antes de afirmar abrangência. A taxa de avaria e o custo real ainda não foram medidos.
A31: Lições: detectar dano não prova sua origem; louça é o objeto protegido; a solução física é o produto do projeto; retorno exige manutenção e custo. Comentários da banca: fechar essas lições, separar escopo/ciclo, explicar Kano–Mudge e validar metas estimadas. | B31: Lições: detectar dano não prova sua origem; louça é o objeto protegido; a solução física é o produto do projeto; retorno exige manutenção e custo. Comentários da banca: fechar essas lições, separar escopo/ciclo, explicar Kano–Mudge e validar metas estimadas. | C31: Lições: detectar dano não prova sua origem; louça é o objeto protegido; a solução física é o produto do projeto; retorno exige manutenção e custo. Comentários da banca: fechar essas lições, separar escopo/ciclo, explicar Kano–Mudge e validar metas estimadas. | D31: Lições: detectar dano não prova sua origem; louça é o objeto protegido; a solução física é o produto do projeto; retorno exige manutenção e custo. Comentários da banca: fechar essas lições, separar escopo/ciclo, explicar Kano–Mudge e validar metas estimadas. | E31: Lições: detectar dano não prova sua origem; louça é o objeto protegido; a solução física é o produto do projeto; retorno exige manutenção e custo. Comentários da banca: fechar essas lições, separar escopo/ciclo, explicar Kano–Mudge e validar metas estimadas. | F31: Lições: detectar dano não prova sua origem; louça é o objeto protegido; a solução física é o produto do projeto; retorno exige manutenção e custo. Comentários da banca: fechar essas lições, separar escopo/ciclo, explicar Kano–Mudge e validar metas estimadas. | G31: Lições: detectar dano não prova sua origem; louça é o objeto protegido; a solução física é o produto do projeto; retorno exige manutenção e custo. Comentários da banca: fechar essas lições, separar escopo/ciclo, explicar Kano–Mudge e validar metas estimadas.
A33: 14/10/2026 — Feedback 2 registrado em logs-ajustes. Correções documentais aplicadas; ampliação do campo e ensaios pendentes. Sem alteração automática das categorias Kano, dos pesos Mudge/QFD ou da seleção pendente de M3. | B33: 14/10/2026 — Feedback 2 registrado em logs-ajustes. Correções documentais aplicadas; ampliação do campo e ensaios pendentes. Sem alteração automática das categorias Kano, dos pesos Mudge/QFD ou da seleção pendente de M3. | C33: 14/10/2026 — Feedback 2 registrado em logs-ajustes. Correções documentais aplicadas; ampliação do campo e ensaios pendentes. Sem alteração automática das categorias Kano, dos pesos Mudge/QFD ou da seleção pendente de M3. | D33: 14/10/2026 — Feedback 2 registrado em logs-ajustes. Correções documentais aplicadas; ampliação do campo e ensaios pendentes. Sem alteração automática das categorias Kano, dos pesos Mudge/QFD ou da seleção pendente de M3. | E33: 14/10/2026 — Feedback 2 registrado em logs-ajustes. Correções documentais aplicadas; ampliação do campo e ensaios pendentes. Sem alteração automática das categorias Kano, dos pesos Mudge/QFD ou da seleção pendente de M3. | F33: 14/10/2026 — Feedback 2 registrado em logs-ajustes. Correções documentais aplicadas; ampliação do campo e ensaios pendentes. Sem alteração automática das categorias Kano, dos pesos Mudge/QFD ou da seleção pendente de M3. | G33: 14/10/2026 — Feedback 2 registrado em logs-ajustes. Correções documentais aplicadas; ampliação do campo e ensaios pendentes. Sem alteração automática das categorias Kano, dos pesos Mudge/QFD ou da seleção pendente de M3.
B36: 14/10/2026 — MIM conceitual pontuada para a referência C1 | C36: 14/10/2026 — MIM conceitual pontuada para a referência C1 | D36: 14/10/2026 — MIM conceitual pontuada para a referência C1 | E36: 14/10/2026 — MIM conceitual pontuada para a referência C1 | F36: 14/10/2026 — MIM conceitual pontuada para a referência C1 | G36: 14/10/2026 — MIM conceitual pontuada para a referência C1
B37: Registrados 156 julgamentos (12 direcionadores × 13 portadores), escala 0/1/3/5 da base, somas/posições, OP-01 fora por padrão, justificativas e quatro núcleos propostos. Interfaces e troca de MD2/MD3/MD4 ainda precisam de dimensionamento e ensaio; C1 não foi selecionada. | C37: Registrados 156 julgamentos (12 direcionadores × 13 portadores), escala 0/1/3/5 da base, somas/posições, OP-01 fora por padrão, justificativas e quatro núcleos propostos. Interfaces e troca de MD2/MD3/MD4 ainda precisam de dimensionamento e ensaio; C1 não foi selecionada. | D37: Registrados 156 julgamentos (12 direcionadores × 13 portadores), escala 0/1/3/5 da base, somas/posições, OP-01 fora por padrão, justificativas e quatro núcleos propostos. Interfaces e troca de MD2/MD3/MD4 ainda precisam de dimensionamento e ensaio; C1 não foi selecionada. | E37: Registrados 156 julgamentos (12 direcionadores × 13 portadores), escala 0/1/3/5 da base, somas/posições, OP-01 fora por padrão, justificativas e quatro núcleos propostos. Interfaces e troca de MD2/MD3/MD4 ainda precisam de dimensionamento e ensaio; C1 não foi selecionada. | F37: Registrados 156 julgamentos (12 direcionadores × 13 portadores), escala 0/1/3/5 da base, somas/posições, OP-01 fora por padrão, justificativas e quatro núcleos propostos. Interfaces e troca de MD2/MD3/MD4 ainda precisam de dimensionamento e ensaio; C1 não foi selecionada. | G37: Registrados 156 julgamentos (12 direcionadores × 13 portadores), escala 0/1/3/5 da base, somas/posições, OP-01 fora por padrão, justificativas e quatro núcleos propostos. Interfaces e troca de MD2/MD3/MD4 ainda precisam de dimensionamento e ensaio; C1 não foi selecionada.
B40: 15/10/2026 — separação entre requisitos, funções, atributos e restrições | C40: 15/10/2026 — separação entre requisitos, funções, atributos e restrições | D40: 15/10/2026 — separação entre requisitos, funções, atributos e restrições | E40: 15/10/2026 — separação entre requisitos, funções, atributos e restrições | F40: 15/10/2026 — separação entre requisitos, funções, atributos e restrições | G40: 15/10/2026 — separação entre requisitos, funções, atributos e restrições
B41: Mantidos 23 RP e 23 metas. V01–V23 registram vínculos; catálogo reúne 17 funções sem duplicar uniformidade/vida nem converter custo em efeito físico. FAST, estruturas, morfológica, MIM e relatório alinhados. Julgamentos da MIM e seleções pendentes preservados. | C41: Mantidos 23 RP e 23 metas. V01–V23 registram vínculos; catálogo reúne 17 funções sem duplicar uniformidade/vida nem converter custo em efeito físico. FAST, estruturas, morfológica, MIM e relatório alinhados. Julgamentos da MIM e seleções pendentes preservados. | D41: Mantidos 23 RP e 23 metas. V01–V23 registram vínculos; catálogo reúne 17 funções sem duplicar uniformidade/vida nem converter custo em efeito físico. FAST, estruturas, morfológica, MIM e relatório alinhados. Julgamentos da MIM e seleções pendentes preservados. | E41: Mantidos 23 RP e 23 metas. V01–V23 registram vínculos; catálogo reúne 17 funções sem duplicar uniformidade/vida nem converter custo em efeito físico. FAST, estruturas, morfológica, MIM e relatório alinhados. Julgamentos da MIM e seleções pendentes preservados. | F41: Mantidos 23 RP e 23 metas. V01–V23 registram vínculos; catálogo reúne 17 funções sem duplicar uniformidade/vida nem converter custo em efeito físico. FAST, estruturas, morfológica, MIM e relatório alinhados. Julgamentos da MIM e seleções pendentes preservados. | G41: Mantidos 23 RP e 23 metas. V01–V23 registram vínculos; catálogo reúne 17 funções sem duplicar uniformidade/vida nem converter custo em efeito físico. FAST, estruturas, morfológica, MIM e relatório alinhados. Julgamentos da MIM e seleções pendentes preservados.
B44: 15/10/2026 — primeira Pugh funcional e escolha da fronteira M1 | C44: 15/10/2026 — primeira Pugh funcional e escolha da fronteira M1 | D44: 15/10/2026 — primeira Pugh funcional e escolha da fronteira M1 | E44: 15/10/2026 — primeira Pugh funcional e escolha da fronteira M1 | F44: 15/10/2026 — primeira Pugh funcional e escolha da fronteira M1 | G44: 15/10/2026 — primeira Pugh funcional e escolha da fronteira M1
B45: Pugh qualitativo: empate 0/0/0, com vantagem potencial de acesso e operação extra de preparo em M1. A equipe priorizou M1. Morfológica e C1/C2/C3 ajustadas para peça descoberta; escores da MIM preservados como histórico e reavaliação reaberta. Metas e segunda seleção continuam aplicáveis. | C45: Pugh qualitativo: empate 0/0/0, com vantagem potencial de acesso e operação extra de preparo em M1. A equipe priorizou M1. Morfológica e C1/C2/C3 ajustadas para peça descoberta; escores da MIM preservados como histórico e reavaliação reaberta. Metas e segunda seleção continuam aplicáveis. | D45: Pugh qualitativo: empate 0/0/0, com vantagem potencial de acesso e operação extra de preparo em M1. A equipe priorizou M1. Morfológica e C1/C2/C3 ajustadas para peça descoberta; escores da MIM preservados como histórico e reavaliação reaberta. Metas e segunda seleção continuam aplicáveis. | E45: Pugh qualitativo: empate 0/0/0, com vantagem potencial de acesso e operação extra de preparo em M1. A equipe priorizou M1. Morfológica e C1/C2/C3 ajustadas para peça descoberta; escores da MIM preservados como histórico e reavaliação reaberta. Metas e segunda seleção continuam aplicáveis. | F45: Pugh qualitativo: empate 0/0/0, com vantagem potencial de acesso e operação extra de preparo em M1. A equipe priorizou M1. Morfológica e C1/C2/C3 ajustadas para peça descoberta; escores da MIM preservados como histórico e reavaliação reaberta. Metas e segunda seleção continuam aplicáveis. | G45: Pugh qualitativo: empate 0/0/0, com vantagem potencial de acesso e operação extra de preparo em M1. A equipe priorizou M1. Morfológica e C1/C2/C3 ajustadas para peça descoberta; escores da MIM preservados como histórico e reavaliação reaberta. Metas e segunda seleção continuam aplicáveis.
B47: 21/10/2026 — MF-A/MF-B/MF-C, FAST e primeira Pugh revisadas
B48: 23 RP e 17 funções preservados. Nova comparação da organização do amortecimento, com indicação conceitual MF-B e sensibilidade explícita. Imagens mantidas junto aos quadros editáveis. Morfológica, concepções, MIM e arquitetura sinalizam a reavaliação necessária, sem transferir resultados históricos.
B50: 21/10/2026 — primeira Pugh ampliada para os 23 requisitos
B51: Substituída a seleção por dois critérios por análise ampla, com vínculos às 17 funções, equivalências justificadas e AV explícitos. Retirados +1/−1 automáticos de MF-B/MF-C. Resultado em aberto, com dependências posteriores alinhadas; metas, pesos, imagens e MIM numérica preservados.
B53: 21/10/2026 — avaliação conceitual da primeira Pugh com princípios de apoio
B54: Hipóteses H1–H5 registradas. Avaliados mais seis critérios: RP3/RP7/RP13/RP15/RP19/RP20. MF-B tem saldo parcial +2 e MF-C −1, com nove AV cada. A seleção permanece aberta. Preservados requisitos, metas, pesos, funções, figuras e julgamentos numéricos da MIM.
B56: 21/10/2026 — recorte qualitativo de mix e transporte informado pela equipe
B57: Estudar louças médias, incluindo cubas e bacias/vasos, compatíveis com os veículos/métodos de envio. Levantar dimensões, massas, apoios e arranjo de carga por família. Metas, notas e nove AV da Pugh preservados; empilhamento continua a dimensionar.
B59: 21/10/2026 — referências de catálogo e cenário físico preliminar
B60: Definidas faixas de cubas/bacias individuais, carga, envelope, paletização e caso de dois níveis/24 h. RP7/RP8/RP14 revistos; compressão 7,5 kN mantida provisória. QFD,17 funções e notas da Pugh preservados; nove AV por alternativa.
B62: 21/10/2026 — seleção funcional MF-B na primeira Pugh
B63: MF-B escolhida para desenvolvimento pelos potenciais de ajuste (RP7/H3) e manutenção (RP15/H4), parcial +2. Nove AV e escores preservados; condições e sensibilidade registradas. Atualizados apenas os encaminhamentos das etapas posteriores, sem escolher C1/C2/C3 ou recalcular a MIM.

Sheet Dados 
A1: 1 | B1: Amortecer impactos do transporte
A2: 2 | B2: Imobilizar a louça
A3: 3 | B3: Permitir conferência sem abrir
A4: 4 | B4: Ser ajustável a diferentes louças
A5: 5 | B5: Ser compatível com o veículo
A6: 6 | B6: Ser de fácil movimentação
A7: 7 | B7: Ter pontos de pega definidos
A8: 8 | B8: Ter retirada segura da louça
A9: 9 | B9: Ser de uso intuitivo
A10: 10 | B10: Ser compacto
A11: 11 | B11: Ser empilhável
A12: 12 | B12: Ter desempenho uniforme
... A23: 23 | B23: Ser estável quando apoiado
B27: Referência preliminar de peças e transporte — revisão de 21/10/2026
B28: Uma peça cerâmica por dispositivo, no fluxo distribuidor–obra. Famílias iniciais: cubas e corpos de bacias/vasos sem caixa acoplada. Kits montados, monoblocos e peças fora dos limites exigem outra configuração e nova avaliação.
B29: Catálogo = dado publicado. Premissa = limite escolhido para desenvolver e comparar as três modelagens. Cálculo = resultado dessas entradas. Nenhuma linha representa ensaio do protótipo. Campos vazios/inválidos bloqueiam os cálculos; controle na linha130.
B31: Modelo / código | C31: Família | D31: A (mm) | E31: B (mm) | F31: H (mm) | G31: Massa (kg) | H31: Fonte | I31: Observação
B32: Celite Basic Q5 1730490027300 | C32: Cuba | D32: 350 | E32: 350 | F32: 135 | H32: S1 | I32: Massa não informada na ficha consultada; pesar.
B33: Celite Design D5 1380850077300 | C33: Cuba | D33: 450 | E33: 400 | F33: 95 | G33: 9.5 | H33: S2 | I33: A/B normalizados a partir de 400 × 450 mm.
B34: Deca Liquid L.13050.LQ.17 | C34: Cuba | D34: 500 | E34: 350 | F34: 140 | G34: 9.746 | H34: S3 | I34: Peso líquido; modelo cerâmico, sem confundir com cuba inox LI.
B35: Celite Like 1643550010300 | C35: Bacia | D35: 610 | E35: 360 | F35: 370 | G35: 18 | H35: S4 | I35: Corpo da bacia; peso declarado como Peso KG.
B36: Celite Elite 1743530010300 | C36: Bacia | D36: 565 | E36: 360 | F36: 400 | G36: 27 | H36: S5 | I36: Caixa, assento e instalação vendidos separadamente.
B37: Deca LK P.23.17 | C37: Bacia | D37: 515 | E37: 355 | F37: 400 | G37: 32.341 | H37: S6 | I37: Peso líquido; AxLxC da fonte = 400 × 355 × 515 mm.
B38: Deca Flex KP.381.BR.17 | C38: Kit montado | D38: 600 | E38: 360 | F38: 760 | G38: 39.449 | H38: S7 | I38: Fora do recorte compacto: a caixa aumenta a altura. Não representa o corpo isolado.
B39: A é o maior lado horizontal e B o lado perpendicular, preservando H e a posição vertical de transporte. Não representam a área de contato. Confirmar apoio admissível, curvatura, áreas frágeis, massa e centro de gravidade por modelo.
B41: Faixa nominal de desenvolvimento — premissa, não cobertura comercial comprovada
B42: Família | C42: A mín. (mm) | D42: A máx. (mm) | E42: B mín. (mm) | F42: B máx. (mm) | G42: H mín. (mm) | H42: H máx. (mm) | I42: Massa máx. (kg) | J42: Natureza
B43: Cubas | C43: 350 | D43: 600 | E43: 300 | F43: 420 | G43: 80 | H43: 200 | I43: 15 | J43: Premissa a verificar
B44: Bacias | C44: 500 | D44: 630 | E44: 340 | F44: 400 | G44: 350 | H44: 420 | I44: 40 | J44: Premissa a verificar
B45: Amostras de catálogo delimitam referências, sem demonstrar representatividade do mix. As extensões até 600/630 mm e os tetos de 15/40 kg são margens de desenvolvimento escolhidas pela equipe; dependem do estoque e do volume vendido.
B46: Aceitar um SKU exige também contato protegido e imobilização sem dano, inspeção da cerâmica, retenção e atendimento ao envelope. Caber na caixa delimitadora é necessário, mas não basta. Peças fora da faixa não entram por suposição.
B48: Entradas para dimensionamento e comparação comum de MF-A, MF-B e MF-C
B49: Reserva dimensional em cada dimensão nominal | E49: 10 | F49: mm | G49: Premissa ±10 mm; Celite informa aproximadamente 10 mm. Para outros fabricantes, confirmar a tolerância aplicável.
B50: Massa máxima da cuba | E50: =I43 -> 15 | F50: kg | G50: Limite de desenvolvimento da família.
B51: Massa máxima da bacia | E51: =I44 -> 40 | F51: kg | G51: Limite de desenvolvimento da família.
B52: Massa cerâmica do caso carregado | E52: 40 | F52: kg | G52: Caso comum conservador; não é limite de levantamento manual.
B53: Orçamento de massa do dispositivo | E53: 8 | F53: kg | G53: Premissa para estrutura, contatos, barreira e interfaces; pesar BOM/protótipo.
B54: Massa máxima do conjunto | E54: =IF(AND(COUNT(E52:E53)=2,MIN(E52:E53)>0),E52+E53,"Pendente") -> 48 | F54: kg | G54: Cerâmica + dispositivo. A interface de carrinho deve ser verificada com esta carga.
B55: Curso mínimo de ajuste no eixo A | E55: 300 | F55: mm | G55: Sem troca de componentes no ajuste. A faixa com reserva vai de 340 a 640 mm.
B56: Curso mínimo de ajuste no eixo B | E56: 150 | F56: mm | G56: Sem troca de componentes no ajuste. A faixa com reserva vai de 290 a 430 mm.
B57: Altura externa carregada — cuba | E57: 275 | F57: mm | G57: Orçamento de envelope, incluindo apoios, proteção e partes salientes.
B58: Altura externa carregada — bacia | E58: 480 | F58: mm | G58: Orçamento de envelope; carga empilhada deve passar pela estrutura, fora da cerâmica.
B59: Folga nominal entre dispositivos no palete | E59: 10 | F59: mm | G59: Premissa de arranjo; não equivale a folga de amortecimento interno nem dimensiona amarração.
B60: Lado A externo máximo | E60: 680 | F60: mm | G60: Orçamento completo carregado, incluindo pegas, pés e fechos, em todas as modelagens.
B61: Lado B externo máximo | E61: 480 | F61: mm | G61: A geometria e a resposta de cada estágio ainda precisam caber neste orçamento.
B62: Unidades por camada de palete | E62: =COUNTA(B87:B89) -> 3 | F62: un. | G62: Contagem das três posições do arranjo em T. Não pressupõe que pegas/amarrações funcionem.
B63: Níveis carregados para estudo | E63: 2 | F63: níveis | G63: Caso de dimensionamento. Não liberar uso empilhado antes dos ensaios e da análise de estabilidade.
B64: Comprimento do palete de referência | E64: 1200 | F64: mm | G64: Base PBR adotada no projeto; conferir o palete real e sua capacidade.
B65: Largura do palete de referência | E65: 1000 | F65: mm | G65: A ocupação calculada é de área, sem inferir segurança da carga.
B66: Altura do palete | E66: 150 | F66: mm | G66: Premissa de transporte; substituir pela medida do palete contratado.
B67: Massa do palete | E67: 35 | F67: kg | G67: Premissa de transporte; substituir pela tara medida. Não é capacidade de carga.
B68: Aceleração da gravidade | E68: 9.81 | F68: m/s² | G68: Constante convencional arredondada.
B69: Compressão provisória RP11 | E69: 7.5 | F69: kN | G69: Meta herdada, ainda sem validação. O peso estático não basta para dimensionar ensaio, duração ou margem.
B70: Ocupação mínima de desenvolvimento RP8 | E70: 0.8 | F70: fração | G70: Revisão preliminar pelo recorte e reserva para proteção. Alvo de otimização de 90% preservado.
B71: Alvo de otimização RP8 | E71: 0.9 | F71: fração | G71: Buscar ganho de densidade sem retirar proteção, inspeção ou contenção.
B72: Teto de volume — cuba | E72: 0.09 | F72: m³/un. | G72: Revisão preliminar; envelope carregado, sem dividir por peças fictícias.
B73: Teto de volume — bacia | E73: 0.16 | F73: m³/un. | G73: Revisão preliminar para o corpo da bacia; não se aplica a kit com caixa montada.
B75: Transporte de referência — Renault Master Furgão L1H1, catálogo brasileiro 2026, p. 13 (S8)
B76: Comprimento útil do compartimento | E76: 2606 | F76: mm | G76: Dado de catálogo da mesma versão L1H1.
B77: Largura livre entre caixas de roda | E77: 1380 | F77: mm | G77: Usar o estrangulamento, não a largura interna máxima de 1765 mm.
B78: Altura útil do compartimento | E78: 1700 | F78: mm | G78: Dado de catálogo L1H1.
B79: Abertura traseira — largura inferior | E79: 1580 | F79: mm | G79: Geometria nominal; verificar percurso e equipamento de carga.
B80: Abertura traseira — altura | E80: 1627 | F80: mm | G80: A abertura traseira limita antes da altura interna.
B81: Carga útil máxima de catálogo | E81: 1450 | F81: kg | G81: Máximo da versão, não saldo disponível: ocupantes, equipamentos e outras cargas devem ser descontados.
B82: Paletes estudados por veículo | E82: 2 | F82: un. | G82: Dois paletes em linha, lado de 1200 mm na direção do comprimento.
B83: Duração de empilhamento para estudo | E83: 24 | F83: h | G83: Premissa de permanência carregada. Medir a operação; ampliar se houver espera maior e estudar fluência.
B85: Arranjo de uma camada — coordenadas (mm) a partir do canto do palete
B86: Unidade | C86: X (mm) | D86: Y (mm) | E86: Lado em X (mm) | F86: Lado em Y (mm) | G86: Orientação | H86: Natureza
B87: U1 | C87: =E59 -> 10 | D87: =E59 -> 10 | E87: =E60 -> 680 | F87: =E61 -> 480 | G87: A em X | H87: Premissa geométrica
B88: U2 | C88: =E59 -> 10 | D88: =E61+2*E59 -> 500 | E88: =E60 -> 680 | F88: =E61 -> 480 | G88: A em X | H88: Premissa geométrica
B89: U3 | C89: =E60+2*E59 -> 700 | D89: =E59 -> 10 | E89: =E61 -> 480 | F89: =E60 -> 680 | G89: B em X | H89: Premissa geométrica
B90: Volume externo carregado — cuba | E90: =IF(E130<>"Preenchidas","Pendente",E60*E61*E57/1000000000) -> 0.08976 | F90: m³/un. | G90: Cálculo de orçamento geométrico. Não demonstra atendimento por qualquer modelagem.
B91: Volume externo carregado — bacia | E91: =IF(E130<>"Preenchidas","Pendente",E60*E61*E58/1000000000) -> 0.156672 | F91: m³/un. | G91: A meta antiga de 0,107 m³ não cobre este orçamento do mix.
B92: Ocupação de área do palete | E92: =IF(E130<>"Preenchidas","Pendente",E62*E60*E61/(E64*E65)) -> 0.816 | F92: fração | G92: 81,6% da área, com 3 peças/camada como antes. Não demonstra mais peças nem menor frete; alvo de 90% pendente.
B93: Unidades carregadas por palete | E93: =IF(E130<>"Preenchidas","Pendente",E62*E63) -> 6 | F93: un. | G93: Dois níveis são um caso de estudo, não autorização operacional.
B94: Altura total do palete — bacias | E94: =IF(E130<>"Preenchidas","Pendente",E63*E58+E66) -> 1110 | F94: mm | G94: Inclui palete; não inclui equipamentos temporários de movimentação.
B95: Massa total do palete — pior caso | E95: =IF(E130<>"Preenchidas","Pendente",E93*E54+E67) -> 323 | F95: kg | G95: Seis bacias de 40 kg com dispositivos de 8 kg e palete de 35 kg.
B96: Reação estática por coluna na base | E96: =IF(E130<>"Preenchidas","Pendente",E63*E54*E68/1000) -> 0.94176 | F96: kN | G96: Peso dos dois conjuntos da coluna. Não é carga externa aplicada na prensa.
B97: Peso estático superior sobre a unidade inferior | E97: =IF(E130<>"Preenchidas","Pendente",MAX(0,E63-1)*E54*E68/1000) -> 0.47088 | F97: kN | G97: Só a unidade acima. Desconsidera efeitos dinâmicos, amarração e fluência.
B98: Massa estudada no veículo | E98: =IF(E130<>"Preenchidas","Pendente",E82*E95) -> 646 | F98: kg | G98: Não inclui ocupantes, amarração, equipamentos ou outras cargas.
B99: Folga longitudinal para dois paletes | E99: =IF(E130<>"Preenchidas","Pendente",E76-E82*E64) -> 206 | F99: mm | G99: Conferência geométrica. Reservar espaço real para fixação e manobra.
B100: Folga transversal entre caixas de roda | E100: =IF(E130<>"Preenchidas","Pendente",E77-E65) -> 380 | F100: mm | G100: Total transversal; confirmar interferências e distribuição da carga.
B101: Folga vertical na abertura traseira | E101: =IF(E130<>"Preenchidas","Pendente",E80-E94) -> 517 | F101: mm | G101: Não aprova capacidade de rampa/plataforma, estabilidade ou amarração.
B102: Curso necessário em A com reserva | E102: =IF(E130<>"Preenchidas","Pendente",MAX(D43:D44)-MIN(C43:C44)+2*E49) -> 300 | F102: mm | G102: Max 630 +10 menos min 350 −10 = 300 mm.
B103: Curso necessário em B com reserva | E103: =IF(E130<>"Preenchidas","Pendente",MAX(F43:F44)-MIN(E43:E44)+2*E49) -> 140 | F103: mm | G103: Max 420 +10 menos min 300 −10 = 140 mm; adotar curso de 150 mm.
B104: Volume da peça de kit montado S7 | E104: =IF(E130<>"Preenchidas","Pendente",D38*E38*F38/1000000000) -> 0.16416 | F104: m³ | G104: 0,16416 m³ antes do dispositivo. Motiva separar kit montado do corpo individual.
B105: Verificação do arranjo no palete | E105: =IF(E130<>"Preenchidas","Pendente",IF(AND(C87>=0,D87>=0,C87+E87<=E64,D87+F87<=E65,C88>=0,D88>=0,C88+E88<=E64,D88+F88<=E65,C89>=0,D89>=0,C89+E89<=E64,D89+F89<=E65,OR(C87+E87<=C88,C88+E88<=C87,D87+F87<=D88,D88+F88<=D87),OR(C87+E87<=C89,C89+E89<=C87,D87+F87<=D89,D89+F89<=D87),OR(C88+E88<=C89,C89+E89<=C88,D88+F88<=D89,D89+F89<=D88)),"Cabe","Rever")) -> Cabe | F105: geometria | G105: Confere limites e sobreposição das três posições; não aprova proteção nem estabilidade.
B106: Critérios de uso e validações que faltam
B107: F07/F08: provar cursos e acomodação de cada SKU nas três alternativas. F11/F09: dimensionar travamento entre níveis e caminho de compressão fora da cerâmica; verificar carga, 24 h, umidade, fluência, estabilidade e solicitações de transporte.
B108: F01/F02: ensaiar proteção e deslocamento nos representantes e extremos de massa/geometria. RP12: calcular dispersão entre unidades na mesma peça/configuração e condição; repetir por família. Não misturar modelos de 9 e 40 kg em um único CV de uniformidade.
B109: F04/F06: delimitar áreas críticas e apoio por modelo. F03/F05: estudar carrinho/apoio de movimentação com até 48 kg; não deduzir aptidão para carregar à mão. F14/F22 e RP23: verificar desmontagem, recondicionamento, retorno e custo com a base real.
B110: Encaixe geométrico no veículo é apenas uma verificação preliminar. Confirmar palete, piso, portas, altura de carregamento, carga útil disponível/eixos, centro de gravidade, restrição de movimento e equipamento de carga no transporte contratado.
B112: Fontes de catálogo — consulta em 21/10/2026
B113: S1 — Celite Basic Q5; dimensões e tolerância; massa ausente.
B114: https://www.celite.com.br/celite-services/productSheet30/BR/pt/CE1730490027300/
B115: S2 — Celite Design D5; dimensões, massa e tolerância.
B116: https://www.celite.com.br/celite-services/productSheet30/BR/pt/CE1380850077300/
B117: S3 — Deca Liquid cerâmica; AxLxC 140 × 500 × 350 mm; peso líquido 9,746 kg.
B118: https://produtos.deca.com.br/Deca/L.13050.LQ.17/fichaTecnica/ficha_tecnica_1716218459516_L.13050.LQ.17.pdf
... B128: https://cdn.group.renault.com/ren/br/renault-new-cars/editorial/2026/catalogo/jul/afRMA001626A_Master_minibus2026_Catalogo_v3.pdf.asset.pdf/7169a69774.pdf
...

Sheet Lista de Necessidades
A1: Etapa do Ciclo de Vida | B1: ID | C1: Necessidade do Cliente | D1: Categoria | E1: Sim ou não | F1: =COUNTIF(E2:E45,"True")
A2: Projeto | B2: 1 | C2: Ter peças modulares | D2: Interno | E2: True
A3: Projeto | B3: 2 | C3: Ter semelhança entre as peças | D3: Interno | E3: True
A4: Projeto | B4: 3 | C4: Ter poucos tipos de componentes | D4: Interno | E4: True
A5: Projeto | B5: 4 | C5: Ser adaptável às variações de louça | D5: Interno | E5: True
A6: Fabricação | B6: 5 | C6: Ter matéria-prima acessível no mercado local | D6: Interno | E6: True
A7: Fabricação | B7: 6 | C7: Ter geometria simples de fabricar | D7: Interno | E7: True
A8: Fabricação | B8: 7 | C8: Ter geometria repetível entre lotes | D8: Interno | E8: True
A9: Armazenagem de peças | B9: 8 | C9: Ter peças identificáveis visualmente | D9: Interno | E9: True
A10: Armazenagem de peças | B10: 9 | C10: Resistir à degradação por umidade no estoque | D10: Interno | E10: True
A11: Armazenagem de peças | B11: 10 | C11: Ter peças empilháveis | D11: Interno | E11: True
A12: Montagem | B12: 11 | C12: Ter encaixes intuitivos | D12: Interno | E12: True
A13: Montagem | B13: 12 | C13: Ter montagem em poucas etapas | D13: Interno | E13: True
... A45: Descarte | B45: 44 | C45: Ter materiais recicláveis | D45: Externo | E45: True

Sheet Matriz de Atributos
B2: CICLO DE VIDA | C2: FUNCIONAMENTO | D2: ERGONOMIA E SEGURANÇA | E2: EFICIÊNCIA OPERACIONAL | F2: DURABILIDADE E ROBUSTEZ | G2: CONFIABILIDADE | H2: ECONÔMICO | I2: MODULARIDADE | J2: SUSTENTABILIDADE E CONFORMIDADE
B3: Projeto | C3: Ser adaptável às variações de louça (4) | I3: Ter peças modulares (1) Ter semelhança entre as peças (2) Ter poucos tipos de componentes (3)
B4: Fabricação | E4: Ter geometria simples de fabricar (6) | G4: Ter dimensões e tolerâncias repetíveis entre lotes (7) | H4: Ter matéria-prima acessível no mercado local (5)
B5: Armazenagem de peças | E5: Ter peças empilháveis (10) | F5: Ser resistente à umidade e à corrosão no estoque (9) | G5: Ter peças identificáveis visualmente (8)
B6: Montagem | C6: Ter indicação visual de montagem correta (14) | D6: Dispensar ferramenta especial para montar (13) | E6: Ter montagem em poucas etapas (12) | I6: Ter encaixes intuitivos (11)
B7: Armazenagem do produto | E7: Ser compacto quando vazio (15) Ser empilhável e estável (16) | F7: Resistir às intempéries de estocagem (17)
B8: Venda | G8: Ter vida útil declarada em número de ciclos (20) | H8: Ter custo por ciclo inferior ao da avaria evitada (18) | I8: Ter configurações padronizadas (19)
B9: Distribuição | C9: Ser compatível com o veículo, a unitização e a amarração (21) | E9: Ocupar pouco espaço no transporte (22) | F9: Proteger o próprio produto até o distribuidor (23)
B10: Uso no distribuidor | C10: Acomodar as variações de louça do distribuidor (26) | D10: Ser de uso intuitivo, sem treinamento formal (24) Ter pontos de pega definidos (25) | G10: Ter indicação visual de fechamento correto (27)
B11: Função | C11: Amortecer impacto e vibração (28) Imobilizar a louça (29) Evitar atrito entre a louça e o produto (30) Permitir conferir a integridade da louça sem abrir (31)
B12: Movimentação na obra | D12: Ter dimensões compatíveis com portas e corredores (32) Ter peso compatível com o transporte por duas pessoas (33) Permitir retirar a louça sem contato com aresta cortante (34) | E12: Ser estável quando apoiado no canteiro (35)
B13: Manutenção | D13: Ser de fácil limpeza (38) | H13: Ter peça de reposição de baixo custo (37) | I13: Ter peças substituíveis individualmente (36)
B14: Retorno | E14: Ser dobrável ou desmontável para o retorno (39) | F14: Suportar ciclos repetidos de uso (40) | J14: Ter identificação para rastreio do retorno (41)
B15: Descarte | J15: Ter materiais identificados (42) Ser de fácil desmontagem (43) Ter materiais recicláveis (44)
B16: Etapa do Ciclo de Vida | C16: ID | D16: Necessidade do Cliente | E16: Categoria | F16: Sim ou não | G16: =COUNTIF(F17:F60,"True")
B17: Projeto | C17: 1 | D17: Ter peças modulares | E17: Interno | F17: True
B18: Projeto | C18: 2 | D18: Ter semelhança entre as peças | E18: Interno | F18: True
B19: Projeto | C19: 3 | D19: Ter poucos tipos de componentes | E19: Interno | F19: True
B20: Projeto | C20: 4 | D20: Ser adaptável às variações de louça | E20: Interno | F20: True
B21: Fabricação | C21: 5 | D21: Ter matéria-prima acessível no mercado local | E21: Interno | F21: True
B22: Fabricação | C22: 6 | D22: Ter geometria simples de fabricar | E22: Interno | F22: True
B23: Fabricação | C23: 7 | D23: Ter geometria repetível entre lotes | E23: Interno | F23: True
B24: Armazenagem de peças | C24: 8 | D24: Ter peças identificáveis visualmente | E24: Interno | F24: True
B25: Armazenagem de peças | C25: 9 | D25: Resistir à degradação por umidade no estoque | E25: Interno | F25: True
B26: Armazenagem de peças | C26: 10 | D26: Ter peças empilháveis | E26: Interno | F26: True
B27: Montagem | C27: 11 | D27: Ter encaixes intuitivos | E27: Interno | F27: True
B28: Montagem | C28: 12 | D28: Ter montagem em poucas etapas | E28: Interno | F28: True
... B60: Descarte | C60: 44 | D60: Ter materiais recicláveis | E60: Externo | F60: True

Sheet Rastreabilidade
A1: ID | B1: Etapa do ciclo de vida | C1: Necessidade (característica do produto) | D1: Atributo | E1: Letra | F1: Requisito do cliente | G1: Aspecto
A2: N-28 | B2: Função | C2: Amortecer impactos do transporte | D2: Funcionamento | E2: A | F2: Amortecer impactos do transporte | G2: Desempenho funcional
A3: N-29 | B3: Função | C3: Imobilizar a louça | D3: Funcionamento | E3: B | F3: Imobilizar a louça | G3: Desempenho funcional
A4: N-30 | B4: Função | C4: Evitar atrito entre a louça e o produto | D4: Funcionamento | E4: B | F4: Imobilizar a louça | G4: Desempenho funcional
A5: N-31 | B5: Função | C5: Permitir conferir a integridade da louça sem abrir | D5: Funcionamento | E5: C | F5: Permitir conferência sem abrir | G5: Desempenho funcional
A6: N-04 | B6: Projeto | C6: Ser adaptável às variações de louça | D6: Funcionamento | E6: D | F6: Ser ajustável a diferentes louças | G6: Desempenho funcional
A7: N-26 | B7: Uso no distribuidor | C7: Acomodar as variações de louça do distribuidor | D7: Funcionamento | E7: D | F7: Ser ajustável a diferentes louças | G7: Desempenho funcional
A8: N-21 | B8: Distribuição | C8: Ser compatível com o arranjo de carga do veículo | D8: Funcionamento | E8: E | F8: Ser compatível com o veículo | G8: Desempenho funcional
A9: N-32 | B9: Movimentação na obra | C9: Ter dimensões compatíveis com as passagens da obra | D9: Ergonomia e segurança | E9: F | F9: Ser de fácil movimentação | G9: Fatores humanos
A10: N-33 | B10: Movimentação na obra | C10: Ter peso compatível com o transporte por duas pessoas | D10: Ergonomia e segurança | E10: F | F10: Ser de fácil movimentação | G10: Fatores humanos
A11: N-25 | B11: Uso no distribuidor | C11: Ter pontos de pega definidos | D11: Ergonomia e segurança | E11: G | F11: Ter pontos de pega definidos | G11: Fatores humanos
A12: N-34 | B12: Movimentação na obra | C12: Permitir retirar a louça sem contato com aresta cortante | D12: Ergonomia e segurança | E12: H | F12: Ter retirada segura da louça | G12: Fatores humanos
... A45: N-37 | B45: Manutenção | C45: Ter peça de reposição de baixo custo | D45: Econômico | E45: V | F45: Ter baixo custo por ciclo de uso | G45: Recursos e manufatura
A47: 44 necessidades geraram 22 requisitos em 44 ligações. Verificado nos dois sentidos: todo requisito tem necessidade de origem e toda necessidade aparece em algum requisito. O agrupamento é o que a matriz de atributos realiza: necessidades de fases diferentes que caem no mesmo atributo viram um requisito só.

Sheet Diagrama de Kano
B1: ID | C1: Requisito do Cliente | D1: Classe de Kano
B2: A | C2: Amortecer impactos do transporte | D2: Básico
B3: B | C3: Imobilizar a louça | D3: Básico
B4: C | C4: Permitir conferência sem abrir | D4: Atrativo
B5: D | C5: Ser ajustável a diferentes louças | D5: Desempenho
B6: E | C6: Ser compatível com o veículo | D6: Básico
B7: F | C7: Ser de fácil movimentação | D7: Desempenho
B8: G | C8: Ter pontos de pega definidos | D8: Básico
B9: H | C9: Ter retirada segura da louça | D9: Básico
B10: I | C10: Ser de uso intuitivo | D10: Desempenho
B11: J | C11: Ser compacto | D11: Desempenho
B12: K | C12: Ser empilhável | D12: Básico
... B23: V | C23: Ter baixo custo por ciclo de uso | D23: Desempenho
B24: W | C24: Ser estável quando apoiado | D24: Básico | F24: Classificação: Atrativo; Desempenho e Básico
B27: Classificação preliminar da equipe, informada pelo levantamento qualitativo. Não houve questionário funcional/disfuncional Kano nesta rodada. Confirmar ou revisar com clientes ao ampliar o campo. | C27: Classificação preliminar da equipe, informada pelo levantamento qualitativo. Não houve questionário funcional/disfuncional Kano nesta rodada. Confirmar ou revisar com clientes ao ampliar o campo. | D27: Classificação preliminar da equipe, informada pelo levantamento qualitativo. Não houve questionário funcional/disfuncional Kano nesta rodada. Confirmar ou revisar com clientes ao ampliar o campo. | E27: Classificação preliminar da equipe, informada pelo levantamento qualitativo. Não houve questionário funcional/disfuncional Kano nesta rodada. Confirmar ou revisar com clientes ao ampliar o campo. | F27: Classificação preliminar da equipe, informada pelo levantamento qualitativo. Não houve questionário funcional/disfuncional Kano nesta rodada. Confirmar ou revisar com clientes ao ampliar o campo.
B29: Kano descreve a resposta de satisfação; não determina quem vence o Mudge. C (atrativo) tem 45 pontos, N (básico) tem 2 e S (atrativo) tem 0. Baixo peso não exclui requisito ou meta. | C29: Kano descreve a resposta de satisfação; não determina quem vence o Mudge. C (atrativo) tem 45 pontos, N (básico) tem 2 e S (atrativo) tem 0. Baixo peso não exclui requisito ou meta. | D29: Kano descreve a resposta de satisfação; não determina quem vence o Mudge. C (atrativo) tem 45 pontos, N (básico) tem 2 e S (atrativo) tem 0. Baixo peso não exclui requisito ou meta. | E29: Kano descreve a resposta de satisfação; não determina quem vence o Mudge. C (atrativo) tem 45 pontos, N (básico) tem 2 e S (atrativo) tem 0. Baixo peso não exclui requisito ou meta. | F29: Kano descreve a resposta de satisfação; não determina quem vence o Mudge. C (atrativo) tem 45 pontos, N (básico) tem 2 e S (atrativo) tem 0. Baixo peso não exclui requisito ou meta.

Sheet Diagrama de Mudge
G2: Qual requisito é mais importante para o sucesso do produto? Quanto mais importante é este requisito?
B5: REQUISITO DO CLIENTE | C5: ID | G5: A | H5: B | I5: C | J5: D | K5: E | L5: F | M5: G | N5: H | O5: I | P5: J | Q5: K | R5: L | S5: M | T5: N | U5: O | V5: P | W5: Q | X5: R | Y5: S | Z5: T | AA5: U | AB5: V | AC5: W | AD5: Somatório da letra
B6: Amortecer impactos do transporte | C6: A | D6: Básico | F6: A | G6: X | H6: A1 | I6: A5 | J6: A3 | K6: A3 | L6: A3 | M6: A5 | N6: A1 | O6: A3 | P6: A3 | Q6: A3 | R6: A3 | S6: A3 | T6: A5 | U6: A3 | V6: A3 | W6: A5 | X6: A5 | Y6: A5 | Z6: A5 | AA6: A5 | AB6: A3 | AC6: A3 | AD6: =COUNTIF($G$6:$AC$28,F6&"1")+COUNTIF($G$6:$AC$28,F6&"3")*3+COUNTIF($G$6:$AC$28,F6&"5")*5
B7: Imobilizar a louça | C7: B | D7: Básico | F7: B | H7: X | I7: B3 | J7: B3 | K7: B3 | L7: B1 | M7: B3 | N7: B1 | O7: B3 | P7: B3 | Q7: B5 | R7: B3 | S7: B5 | T7: B5 | U7: B3 | V7: B5 | W7: B5 | X7: B5 | Y7: B5 | Z7: B5 | AA7: B5 | AB7: B3 | AC7: B3 | AD7: =COUNTIF($G$6:$AC$28,F7&"1")+COUNTIF($G$6:$AC$28,F7&"3")*3+COUNTIF($G$6:$AC$28,F7&"5")*5
B8: Permitir conferência sem abrir | C8: C | D8: Atrativo | F8: C | I8: X | J8: C1 | K8: C1 | L8: F1 | M8: C1 | N8: C1 | O8: C1 | P8: C3 | Q8: C3 | R8: C3 | S8: C1 | T8: C3 | U8: C3 | V8: C3 | W8: C3 | X8: C5 | Y8: C5 | Z8: C3 | AA8: C3 | AB8: C1 | AC8: C1 | AD8: =COUNTIF($G$6:$AC$28,F8&"1")+COUNTIF($G$6:$AC$28,F8&"3")*3+COUNTIF($G$6:$AC$28,F8&"5")*5
B9: Ser ajustável a diferentes louças | C9: D | D9: Desempenho | F9: D | J9: X | K9: D1 | L9: F3 | M9: D1 | N9: H1 | O9: D1 | P9: D1 | Q9: D1 | R9: D1 | S9: D3 | T9: D3 | U9: D1 | V9: D3 | W9: D3 | X9: D5 | Y9: D5 | Z9: D1 | AA9: D3 | AB9: D1 | AC9: D1 | AD9: =COUNTIF($G$6:$AC$28,F9&"1")+COUNTIF($G$6:$AC$28,F9&"3")*3+COUNTIF($G$6:$AC$28,F9&"5")*5
B10: Ser compatível com o veículo | C10: E | D10: Básico | F10: E | K10: X | L10: F3 | M10: G1 | N10: H1 | O10: E1 | P10: E1 | Q10: E1 | R10: E1 | S10: E1 | T10: E3 | U10: E1 | V10: E1 | W10: E3 | X10: E3 | Y10: E3 | Z10: E3 | AA10: E3 | AB10: E1 | AC10: E1 | AD10: =COUNTIF($G$6:$AC$28,F10&"1")+COUNTIF($G$6:$AC$28,F10&"3")*3+COUNTIF($G$6:$AC$28,F10&"5")*5
B11: Ser de fácil movimentação | C11: F | D11: Desempenho | F11: F | L11: X | M11: F1 | N11: F1 | O11: F3 | P11: F3 | Q11: F3 | R11: F3 | S11: F5 | T11: F5 | U11: F3 | V11: F5 | W11: F5 | X11: F5 | Y11: F5 | Z11: F5 | AA11: F5 | AB11: F3 | AC11: F3 | AD11: =COUNTIF($G$6:$AC$28,F11&"1")+COUNTIF($G$6:$AC$28,F11&"3")*3+COUNTIF($G$6:$AC$28,F11&"5")*5
B12: Ter pontos de pega definidos | C12: G | D12: Básico | F12: G | M12: X | N12: G1 | O12: G1 | P12: G1 | Q12: G1 | R12: G1 | S12: G3 | T12: G3 | U12: G1 | V12: G3 | W12: G3 | X12: G5 | Y12: G5 | Z12: G3 | AA12: G3 | AB12: G1 | AC12: G1 | AD12: =COUNTIF($G$6:$AC$28,F12&"1")+COUNTIF($G$6:$AC$28,F12&"3")*3+COUNTIF($G$6:$AC$28,F12&"5")*5
B13: Ter retirada segura da louça | C13: H | D13: Básico | F13: H | N13: X | O13: H1 | P13: H1 | Q13: H3 | R13: H1 | S13: H1 | T13: H3 | U13: H1 | V13: H3 | W13: H3 | X13: H5 | Y13: H5 | Z13: H3 | AA13: H3 | AB13: H1 | AC13: H1 | AD13: =COUNTIF($G$6:$AC$28,F13&"1")+COUNTIF($G$6:$AC$28,F13&"3")*3+COUNTIF($G$6:$AC$28,F13&"5")*5
B14: Ser de uso intuitivo | C14: I | D14: Desempenho | F14: I | O14: X | P14: I1 | Q14: I1 | R14: I1 | S14: I1 | T14: I3 | U14: I1 | V14: I1 | W14: I3 | X14: I3 | Y14: I3 | Z14: I3 | AA14: I1 | AB14: V1 | AC14: W1 | AD14: =COUNTIF($G$6:$AC$28,F14&"1")+COUNTIF($G$6:$AC$28,F14&"3")*3+COUNTIF($G$6:$AC$28,F14&"5")*5
B15: Ser compacto | C15: J | D15: Desempenho | F15: J | P15: X | Q15: K1 | R15: L1 | S15: J1 | T15: J3 | U15: O1 | V15: J1 | W15: J1 | X15: J3 | Y15: J3 | Z15: J1 | AA15: J1 | AB15: V1 | AC15: W1 | AD15: =COUNTIF($G$6:$AC$28,F15&"1")+COUNTIF($G$6:$AC$28,F15&"3")*3+COUNTIF($G$6:$AC$28,F15&"5")*5
B16: Ser empilhável | C16: K | D16: Básico | F16: K | Q16: X | R16: K1 | S16: K1 | T16: K3 | U16: K1 | V16: K1 | W16: K1 | X16: K3 | Y16: K3 | Z16: K1 | AA16: K1 | AB16: V1 | AC16: W1 | AD16: =COUNTIF($G$6:$AC$28,F16&"1")+COUNTIF($G$6:$AC$28,F16&"3")*3+COUNTIF($G$6:$AC$28,F16&"5")*5
B17: Ter desempenho uniforme | C17: L | D17: Básico | F17: L | R17: X | S17: L1 | T17: L3 | U17: L1 | V17: L1 | W17: L1 | X17: L3 | Y17: L3 | Z17: L1 | AA17: L1 | AB17: V1 | AC17: W1 | AD17: =COUNTIF($G$6:$AC$28,F17&"1")+COUNTIF($G$6:$AC$28,F17&"3")*3+COUNTIF($G$6:$AC$28,F17&"5")*5
B18: Ter indicação visual de uso | C18: M | D18: Atrativo | F18: M | S18: X | T18: M1 | U18: O1 | V18: P1 | W18: M1 | X18: M3 | Y18: M3 | Z18: M1 | AA18: M1 | AB18: V1 | AC18: W1 | AD18: =COUNTIF($G$6:$AC$28,F18&"1")+COUNTIF($G$6:$AC$28,F18&"3")*3+COUNTIF($G$6:$AC$28,F18&"5")*5
B19: Ter identificação visível | C19: N | D19: Básico | F19: N | T19: X | U19: O3 | V19: P1 | W19: Q1 | X19: N1 | Y19: N1 | Z19: T1 | AA19: U1 | AB19: V3 | AC19: W3 | AD19: =COUNTIF($G$6:$AC$28,F19&"1")+COUNTIF($G$6:$AC$28,F19&"3")*3+COUNTIF($G$6:$AC$28,F19&"5")*5
B20: Ser reutilizável | C20: O | D20: Desempenho | F20: O | U20: X | V20: O1 | W20: O1 | X20: O3 | Y20: O3 | Z20: O1 | AA20: O1 | AB20: V1 | AC20: W1 | AD20: =COUNTIF($G$6:$AC$28,F20&"1")+COUNTIF($G$6:$AC$28,F20&"3")*3+COUNTIF($G$6:$AC$28,F20&"5")*5
B21: Ser resistente a intempéries | C21: P | D21: Básico | F21: P | V21: X | W21: P1 | X21: P3 | Y21: P3 | Z21: P1 | AA21: P1 | AB21: V1 | AC21: W1 | AD21: =COUNTIF($G$6:$AC$28,F21&"1")+COUNTIF($G$6:$AC$28,F21&"3")*3+COUNTIF($G$6:$AC$28,F21&"5")*5
B22: Ter manutenção simples | C22: Q | D22: Desempenho | F22: Q | W22: X | X22: Q1 | Y22: Q1 | Z22: T1 | AA22: U1 | AB22: V3 | AC22: W3 | AD22: =COUNTIF($G$6:$AC$28,F22&"1")+COUNTIF($G$6:$AC$28,F22&"3")*3+COUNTIF($G$6:$AC$28,F22&"5")*5
B23: Ser de fácil desmontagem | C23: R | D23: Desempenho | F23: R | X23: X | Y23: R1 | Z23: T1 | AA23: U1 | AB23: V3 | AC23: W3 | AD23: =COUNTIF($G$6:$AC$28,F23&"1")+COUNTIF($G$6:$AC$28,F23&"3")*3+COUNTIF($G$6:$AC$28,F23&"5")*5
B24: Ter materiais recicláveis | C24: S | D24: Atrativo | F24: S | Y24: X | Z24: T1 | AA24: U1 | AB24: V3 | AC24: W3 | AD24: =COUNTIF($G$6:$AC$28,F24&"1")+COUNTIF($G$6:$AC$28,F24&"3")*3+COUNTIF($G$6:$AC$28,F24&"5")*5
B25: Ter peças modulares | C25: T | D25: Desempenho | F25: T | Z25: X | AA25: T1 | AB25: V3 | AC25: W3 | AD25: =COUNTIF($G$6:$AC$28,F25&"1")+COUNTIF($G$6:$AC$28,F25&"3")*3+COUNTIF($G$6:$AC$28,F25&"5")*5
B26: Ter montagem em poucas etapas | C26: U | D26: Desempenho | F26: U | AA26: X | AB26: V3 | AC26: W3 | AD26: =COUNTIF($G$6:$AC$28,F26&"1")+COUNTIF($G$6:$AC$28,F26&"3")*3+COUNTIF($G$6:$AC$28,F26&"5")*5
B27: Ter baixo custo por ciclo de uso | C27: V | D27: Desempenho | F27: V | AB27: X | AC27: W1 | AD27: =COUNTIF($G$6:$AC$28,F27&"1")+COUNTIF($G$6:$AC$28,F27&"3")*3+COUNTIF($G$6:$AC$28,F27&"5")*5
B28: Ser estável quando apoiado | C28: W | D28: Básico | F28: W | AC28: X | AD28: =COUNTIF($G$6:$AC$28,F28&"1")+COUNTIF($G$6:$AC$28,F28&"3")*3+COUNTIF($G$6:$AC$28,F28&"5")*5
AB29: Total | AC29: Total | AD29: =SUM(AD6:AD28)
B31: Um requisito é considerado muito mais importante do que o outro (VALOR 5)
B32: Um requisito é considerado mais importante do que o outro (VALOR 3)
B33: Um requisito é considerado pouco mais importante do que o outro (VALOR 1)
B34: Os requisitos são considerados de igual importância (VALOR 0)
B36: Base da comparação: cada par foi julgado pela pergunta da Aula 12 — qual requisito é mais importante para o sucesso do produto e quanto mais importante. As notas C1, C2 e C3 abaixo servem de âncora comum para que a comparação não fique arbitrária; em 17 dos 253 pares o julgamento do par se afastou dessa âncora, e cada um deles está registrado na tabela de desvios com a razão. Primeiro passe da equipe, a revalidar com o distribuidor.
B38: C1 · Avaria | C38: Reduz diretamente a quebra no trecho distribuidor–obra
B39: C2 · Trabalhador | C39: Reduz esforço, queda e exposição a corte
B40: C3 · Adoção | C40: Determina o distribuidor comprar e usar: custo, ritmo e compatibilidade
B42: Requisito do cliente | C42: ID | D42: C1 | E42: C2 | F42: C3 | G42: Soma
B43: Amortecer impactos do transporte | C43: A | D43: 5 | E43: 2 | F43: 3 | G43: =SUM(D43:F43)
B44: Imobilizar a louça | C44: B | D44: 5 | E44: 3 | F44: 3 | G44: =SUM(D44:F44)
B45: Permitir conferência sem abrir | C45: C | D45: 1 | E45: 4 | F45: 4 | G45: =SUM(D45:F45)
B46: Ser ajustável a diferentes louças | C46: D | D46: 3 | E46: 1 | F46: 4 | G46: =SUM(D46:F46)
B47: Ser compatível com o veículo | C47: E | D47: 3 | E47: 1 | F47: 3 | G47: =SUM(D47:F47)
B48: Ser de fácil movimentação | C48: F | D48: 3 | E48: 5 | F48: 3 | G48: =SUM(D48:F48)
B49: Ter pontos de pega definidos | C49: G | D49: 2 | E49: 4 | F49: 2 | G49: =SUM(D49:F49)
B50: Ter retirada segura da louça | C50: H | D50: 1 | E50: 5 | F50: 2 | G50: =SUM(D50:F50)
B51: Ser de uso intuitivo | C51: I | D51: 1 | E51: 2 | F51: 4 | G51: =SUM(D51:F51)
B52: Ser compacto | C52: J | D52: 1 | E52: 1 | F52: 4 | G52: =SUM(D52:F52)
B53: Ser empilhável | C53: K | D53: 3 | E53: 1 | F53: 2 | G53: =SUM(D53:F53)
B54: Ter desempenho uniforme | C54: L | D54: 2 | E54: 1 | F54: 3 | G54: =SUM(D54:F54)
... B65: Ser estável quando apoiado | C65: W | D65: 2 | E65: 4 | F65: 1 | G65: =SUM(D65:F65)
B67: Pares em que o julgamento se afastou da âncora de critérios
B68: Par | C68: Âncora | D68: Julgado | E68: Razão do julgamento no par
B69: B × C | C69: B1 | D69: B3 | E69: Imobilizar ataca a origem da avaria; conferir sem abrir trata a detecção depois do fato. A distância é maior do que as somas sugerem.
B70: B × K | C70: B3 | D70: B5 | E70: O problema declarado é avaria no transporte; empilhamento é conveniência de armazenagem.
B71: F × G | C71: F3 | D71: F1 | E71: Pega é o meio de obter movimentação fácil. No par, entre o fim e o meio, a diferença é pequena.
B72: F × H | C72: F3 | D72: F1 | E72: Os dois protegem o trabalhador. A movimentação acontece em toda peça; o corte é raro e grave. Vence por pouco.
B73: A × D | C73: A1 | D73: A3 | E73: Amortecer ataca a causa direta da avaria; ajustar-se a modelos é condição de escala comercial.
B74: A × L | C74: A3 | D74: A1 | E74: Uniformidade é a consistência do próprio amortecimento. No par, o fim vence por pouco.
B75: C × M | C75: C3 | D75: C1 | E75: Mesma família: o indicador de impacto é um meio de conferir sem abrir.
B76: C × N | C76: C5 | D76: C3 | E76: Mesma família de informação visível. A diferença é grande, mas não máxima.
B77: D × H | C77: D1 | D77: H1 | E77: Entre servir a mais modelos e não cortar quem abre a embalagem, a integridade do trabalhador vence.
B78: D × T | C78: D3 | D78: D1 | E78: Modularidade é o meio de obter o ajuste. No par, o fim vence por pouco.
B79: H × K | C79: H1 | D79: H3 | E79: Corte na retirada é lesão; empilhamento é conveniência de estoque.
... B85: R × S | C85: empate | D85: R1 | E85: Desmontar é condição para separar o material e reciclar.

Sheet Diagrama de Pareto
A1: Requisito | B1: ID | C1: Pontuação | D1: Frequência | E1: Frequência Acumulada | F1: Grau de Importância | G1: Classe de Pareto
A2: Amortecer impactos do transporte | B2: A | C2: ='Diagrama de Mudge'!AD6 | D2: =C2/$C$25 | E2: =D2 | F2: =IF(C2=0,0,MAX(1,ROUND(C2/MAX($C$2:$C$24)*5,0))) | G2: ="A · vital"
A3: Imobilizar a louça | B3: B | C3: ='Diagrama de Mudge'!AD7 | D3: =C3/$C$25 | E3: =D3+E2 | F3: =IF(C3=0,0,MAX(1,ROUND(C3/MAX($C$2:$C$24)*5,0))) | G3: =IF(E2<0.8,"A · vital","B · trivial")
A4: Ser de fácil movimentação | B4: F | C4: ='Diagrama de Mudge'!AD11 | D4: =C4/$C$25 | E4: =D4+E3 | F4: =IF(C4=0,0,MAX(1,ROUND(C4/MAX($C$2:$C$24)*5,0))) | G4: =IF(E3<0.8,"A · vital","B · trivial")
A5: Permitir conferência sem abrir | B5: C | C5: ='Diagrama de Mudge'!AD8 | D5: =C5/$C$25 | E5: =D5+E4 | F5: =IF(C5=0,0,MAX(1,ROUND(C5/MAX($C$2:$C$24)*5,0))) | G5: =IF(E4<0.8,"A · vital","B · trivial")
A6: Ter pontos de pega definidos | B6: G | C6: ='Diagrama de Mudge'!AD12 | D6: =C6/$C$25 | E6: =D6+E5 | F6: =IF(C6=0,0,MAX(1,ROUND(C6/MAX($C$2:$C$24)*5,0))) | G6: =IF(E5<0.8,"A · vital","B · trivial")
A7: Ter retirada segura da louça | B7: H | C7: ='Diagrama de Mudge'!AD13 | D7: =C7/$C$25 | E7: =D7+E6 | F7: =IF(C7=0,0,MAX(1,ROUND(C7/MAX($C$2:$C$24)*5,0))) | G7: =IF(E6<0.8,"A · vital","B · trivial")
A8: Ser ajustável a diferentes louças | B8: D | C8: ='Diagrama de Mudge'!AD9 | D8: =C8/$C$25 | E8: =D8+E7 | F8: =IF(C8=0,0,MAX(1,ROUND(C8/MAX($C$2:$C$24)*5,0))) | G8: =IF(E7<0.8,"A · vital","B · trivial")
A9: Ser compatível com o veículo | B9: E | C9: ='Diagrama de Mudge'!AD10 | D9: =C9/$C$25 | E9: =D9+E8 | F9: =IF(C9=0,0,MAX(1,ROUND(C9/MAX($C$2:$C$24)*5,0))) | G9: =IF(E8<0.8,"A · vital","B · trivial")
A10: Ser estável quando apoiado | B10: W | C10: ='Diagrama de Mudge'!AD28 | D10: =C10/$C$25 | E10: =D10+E9 | F10: =IF(C10=0,0,MAX(1,ROUND(C10/MAX($C$2:$C$24)*5,0))) | G10: =IF(E9<0.8,"A · vital","B · trivial")
A11: Ter baixo custo por ciclo de uso | B11: V | C11: ='Diagrama de Mudge'!AD27 | D11: =C11/$C$25 | E11: =D11+E10 | F11: =IF(C11=0,0,MAX(1,ROUND(C11/MAX($C$2:$C$24)*5,0))) | G11: =IF(E10<0.8,"A · vital","B · trivial")
A12: Ser de uso intuitivo | B12: I | C12: ='Diagrama de Mudge'!AD14 | D12: =C12/$C$25 | E12: =D12+E11 | F12: =IF(C12=0,0,MAX(1,ROUND(C12/MAX($C$2:$C$24)*5,0))) | G12: =IF(E11<0.8,"A · vital","B · trivial")
A13: Ser empilhável | B13: K | C13: ='Diagrama de Mudge'!AD16 | D13: =C13/$C$25 | E13: =D13+E12 | F13: =IF(C13=0,0,MAX(1,ROUND(C13/MAX($C$2:$C$24)*5,0))) | G13: =IF(E12<0.8,"A · vital","B · trivial")
A14: Ter desempenho uniforme | B14: L | C14: ='Diagrama de Mudge'!AD17 | D14: =C14/$C$25 | E14: =D14+E13 | F14: =IF(C14=0,0,MAX(1,ROUND(C14/MAX($C$2:$C$24)*5,0))) | G14: =IF(E13<0.8,"A · vital","B · trivial")
A15: Ser reutilizável | B15: O | C15: ='Diagrama de Mudge'!AD20 | D15: =C15/$C$25 | E15: =D15+E14 | F15: =IF(C15=0,0,MAX(1,ROUND(C15/MAX($C$2:$C$24)*5,0))) | G15: =IF(E14<0.8,"A · vital","B · trivial")
A16: Ser compacto | B16: J | C16: ='Diagrama de Mudge'!AD15 | D16: =C16/$C$25 | E16: =D16+E15 | F16: =IF(C16=0,0,MAX(1,ROUND(C16/MAX($C$2:$C$24)*5,0))) | G16: =IF(E15<0.8,"A · vital","B · trivial")
A17: Ser resistente a intempéries | B17: P | C17: ='Diagrama de Mudge'!AD21 | D17: =C17/$C$25 | E17: =D17+E16 | F17: =IF(C17=0,0,MAX(1,ROUND(C17/MAX($C$2:$C$24)*5,0))) | G17: =IF(E16<0.8,"A · vital","B · trivial")
A18: Ter indicação visual de uso | B18: M | C18: ='Diagrama de Mudge'!AD18 | D18: =C18/$C$25 | E18: =D18+E17 | F18: =IF(C18=0,0,MAX(1,ROUND(C18/MAX($C$2:$C$24)*5,0))) | G18: =IF(E17<0.8,"A · vital","B · trivial")
A19: Ter peças modulares | B19: T | C19: ='Diagrama de Mudge'!AD25 | D19: =C19/$C$25 | E19: =D19+E18 | F19: =IF(C19=0,0,MAX(1,ROUND(C19/MAX($C$2:$C$24)*5,0))) | G19: =IF(E18<0.8,"A · vital","B · trivial")
A20: Ter montagem em poucas etapas | B20: U | C20: ='Diagrama de Mudge'!AD26 | D20: =C20/$C$25 | E20: =D20+E19 | F20: =IF(C20=0,0,MAX(1,ROUND(C20/MAX($C$2:$C$24)*5,0))) | G20: =IF(E19<0.8,"A · vital","B · trivial")
A21: Ter manutenção simples | B21: Q | C21: ='Diagrama de Mudge'!AD22 | D21: =C21/$C$25 | E21: =D21+E20 | F21: =IF(C21=0,0,MAX(1,ROUND(C21/MAX($C$2:$C$24)*5,0))) | G21: =IF(E20<0.8,"A · vital","B · trivial")
A22: Ter identificação visível | B22: N | C22: ='Diagrama de Mudge'!AD19 | D22: =C22/$C$25 | E22: =D22+E21 | F22: =IF(C22=0,0,MAX(1,ROUND(C22/MAX($C$2:$C$24)*5,0))) | G22: =IF(E21<0.8,"A · vital","B · trivial")
A23: Ser de fácil desmontagem | B23: R | C23: ='Diagrama de Mudge'!AD23 | D23: =C23/$C$25 | E23: =D23+E22 | F23: =IF(C23=0,0,MAX(1,ROUND(C23/MAX($C$2:$C$24)*5,0))) | G23: =IF(E22<0.8,"A · vital","B · trivial")
A24: Ter materiais recicláveis | B24: S | C24: ='Diagrama de Mudge'!AD24 | D24: =C24/$C$25 | E24: =D24+E23 | F24: =IF(C24=0,0,MAX(1,ROUND(C24/MAX($C$2:$C$24)*5,0))) | G24: =IF(E23<0.8,"A · vital","B · trivial")
C25: =SUM(C2:C24) | D25: =SUM(D2:D24)
A28: O grau de importância 0–5 resume a pontuação do Mudge e é usado na triagem Pugh. A quantificação técnica do QFD usa a pontuação bruta de Mudge, conforme a Matriz de Relacionamento.
A30: Kano e Mudge são complementares: a classe de satisfação não determina vitória nos pares. C é atrativo e tem alta importância; N é básico e tem baixo peso. Classe B ou peso zero não elimina requisitos e metas. | B30: Kano e Mudge são complementares: a classe de satisfação não determina vitória nos pares. C é atrativo e tem alta importância; N é básico e tem baixo peso. Classe B ou peso zero não elimina requisitos e metas. | C30: Kano e Mudge são complementares: a classe de satisfação não determina vitória nos pares. C é atrativo e tem alta importância; N é básico e tem baixo peso. Classe B ou peso zero não elimina requisitos e metas. | D30: Kano e Mudge são complementares: a classe de satisfação não determina vitória nos pares. C é atrativo e tem alta importância; N é básico e tem baixo peso. Classe B ou peso zero não elimina requisitos e metas. | E30: Kano e Mudge são complementares: a classe de satisfação não determina vitória nos pares. C é atrativo e tem alta importância; N é básico e tem baixo peso. Classe B ou peso zero não elimina requisitos e metas. | F30: Kano e Mudge são complementares: a classe de satisfação não determina vitória nos pares. C é atrativo e tem alta importância; N é básico e tem baixo peso. Classe B ou peso zero não elimina requisitos e metas. | G30: Kano e Mudge são complementares: a classe de satisfação não determina vitória nos pares. C é atrativo e tem alta importância; N é básico e tem baixo peso. Classe B ou peso zero não elimina requisitos e metas.
A33: Kano–Mudge — interpretação dos resultados no recorte investigado | B33: Kano–Mudge — interpretação dos resultados no recorte investigado | C33: Kano–Mudge — interpretação dos resultados no recorte investigado | D33: Kano–Mudge — interpretação dos resultados no recorte investigado | E33: Kano–Mudge — interpretação dos resultados no recorte investigado | F33: Kano–Mudge — interpretação dos resultados no recorte investigado | G33: Kano–Mudge — interpretação dos resultados no recorte investigado
A34: Requisito | B34: ID | C34: Kano | D34: Pontos Mudge | E34: Posição no Pareto | F34: Diretriz | G34: RP relacionados
A35: =INDEX($A$2:$A$24,MATCH(B35,$B$2:$B$24,0)) -> Amortecer impactos do transporte | B35: A | C35: =INDEX('Diagrama de Kano'!$D$2:$D$24,MATCH(B35,'Diagrama de Kano'!$B$2:$B$24,0)) -> Básico | D35: =INDEX($C$2:$C$24,MATCH(B35,$B$2:$B$24,0)) -> 78 | E35: =MATCH(B35,$B$2:$B$24,0) -> 1 | F35: Priorizar proteção; ensaiar aceleração | G35: RP1
A36: =INDEX($A$2:$A$24,MATCH(B36,$B$2:$B$24,0)) -> Imobilizar a louça | B36: B | C36: =INDEX('Diagrama de Kano'!$D$2:$D$24,MATCH(B36,'Diagrama de Kano'!$B$2:$B$24,0)) -> Básico | D36: =INDEX($C$2:$C$24,MATCH(B36,$B$2:$B$24,0)) -> 77 | E36: =MATCH(B36,$B$2:$B$24,0) -> 2 | F36: Priorizar imobilização; medir deslocamento | G36: RP2
A37: =INDEX($A$2:$A$24,MATCH(B37,$B$2:$B$24,0)) -> Ser de fácil movimentação | B37: F | C37: =INDEX('Diagrama de Kano'!$D$2:$D$24,MATCH(B37,'Diagrama de Kano'!$B$2:$B$24,0)) -> Desempenho | D37: =INDEX($C$2:$C$24,MATCH(B37,$B$2:$B$24,0)) -> 70 | E37: =MATCH(B37,$B$2:$B$24,0) -> 3 | F37: Confrontar proteção com esforço e acesso | G37: RP3, RP5
A38: =INDEX($A$2:$A$24,MATCH(B38,$B$2:$B$24,0)) -> Permitir conferência sem abrir | B38: C | C38: =INDEX('Diagrama de Kano'!$D$2:$D$24,MATCH(B38,'Diagrama de Kano'!$B$2:$B$24,0)) -> Atrativo | D38: =INDEX($C$2:$C$24,MATCH(B38,$B$2:$B$24,0)) -> 45 | E38: =MATCH(B38,$B$2:$B$24,0) -> 4 | F38: Atrativo de alta importância; comprovar inspeção da cerâmica | G38: RP4
A39: =INDEX($A$2:$A$24,MATCH(B39,$B$2:$B$24,0)) -> Ser empilhável | B39: K | C39: =INDEX('Diagrama de Kano'!$D$2:$D$24,MATCH(B39,'Diagrama de Kano'!$B$2:$B$24,0)) -> Básico | D39: =INDEX($C$2:$C$24,MATCH(B39,$B$2:$B$24,0)) -> 17 | E39: =MATCH(B39,$B$2:$B$24,0) -> 12 | F39: Fora dos onze vitais; empilhamento continua exigido | G39: RP11
A40: =INDEX($A$2:$A$24,MATCH(B40,$B$2:$B$24,0)) -> Ter identificação visível | B40: N | C40: =INDEX('Diagrama de Kano'!$D$2:$D$24,MATCH(B40,'Diagrama de Kano'!$B$2:$B$24,0)) -> Básico | D40: =INDEX($C$2:$C$24,MATCH(B40,$B$2:$B$24,0)) -> 2 | E40: =MATCH(B40,$B$2:$B$24,0) -> 21 | F40: Peso baixo; identificação e orientação permanecem | G40: RP16, RP21
A41: =INDEX($A$2:$A$24,MATCH(B41,$B$2:$B$24,0)) -> Ter materiais recicláveis | B41: S | C41: =INDEX('Diagrama de Kano'!$D$2:$D$24,MATCH(B41,'Diagrama de Kano'!$B$2:$B$24,0)) -> Atrativo | D41: =INDEX($C$2:$C$24,MATCH(B41,$B$2:$B$24,0)) -> 0 | E41: =MATCH(B41,$B$2:$B$24,0) -> 23 | F41: Peso zero; meta de fim de vida permanece | G41: RP19
A43: A classe Kano acompanha a interpretação do QFD; a quantificação usa os pontos brutos do Mudge, sem multiplicador de classe. Rever categorias e pares se as novas entrevistas mudarem a interpretação; atualizar Pareto, QFD e seleção na mesma rodada. | B43: A classe Kano acompanha a interpretação do QFD; a quantificação usa os pontos brutos do Mudge, sem multiplicador de classe. Rever categorias e pares se as novas entrevistas mudarem a interpretação; atualizar Pareto, QFD e seleção na mesma rodada. | C43: A classe Kano acompanha a interpretação do QFD; a quantificação usa os pontos brutos do Mudge, sem multiplicador de classe. Rever categorias e pares se as novas entrevistas mudarem a interpretação; atualizar Pareto, QFD e seleção na mesma rodada. | D43: A classe Kano acompanha a interpretação do QFD; a quantificação usa os pontos brutos do Mudge, sem multiplicador de classe. Rever categorias e pares se as novas entrevistas mudarem a interpretação; atualizar Pareto, QFD e seleção na mesma rodada. | E43: A classe Kano acompanha a interpretação do QFD; a quantificação usa os pontos brutos do Mudge, sem multiplicador de classe. Rever categorias e pares se as novas entrevistas mudarem a interpretação; atualizar Pareto, QFD e seleção na mesma rodada. | F43: A classe Kano acompanha a interpretação do QFD; a quantificação usa os pontos brutos do Mudge, sem multiplicador de classe. Rever categorias e pares se as novas entrevistas mudarem a interpretação; atualizar Pareto, QFD e seleção na mesma rodada. | G43: A classe Kano acompanha a interpretação do QFD; a quantificação usa os pontos brutos do Mudge, sem multiplicador de classe. Rever categorias e pares se as novas entrevistas mudarem a interpretação; atualizar Pareto, QFD e seleção na mesma rodada.

Sheet Benchmarking
B2: Benchmarking
B4: R1 | C4: Embalagem de papelão do fabricante | D4: Caixa de papelão com berço interno, uma viagem. Padrão observado no estoque do distribuidor e no recebimento da obra (Semana 03).
B5: R2 | C5: Engradado de madeira com calços | D5: Caixa de ripas com calços internos, usada em cargas especiais e longas distâncias. Referência de mercado descrita pelo distribuidor.
B6: R3 | C6: Palete com filme stretch e cantoneiras | D6: Unitização da expedição: caixas sobre palete, filme stretch e cantoneiras de papelão. Observado na expedição do distribuidor.
B7: R4 | C7: Sistema de encaixes de papelão — US9221577B2 | D7: Estado da arte documental. Encaixes de papelão que posicionam bacia, caixa acoplada e tampa; a especificação reivindica cerca de 27% menos volume de embalagem. Avaliado por especificação, não por observação.
B9: ID | C9: Requisito do cliente | D9: Kano | E9: Pontuação Mudge | F9: R1 Embalagem de papelão do fabricante | G9: R2 Engradado de madeira com calços | H9: R3 Palete com filme stretch e cantoneiras | I9: R4 Sistema de encaixes de papelão — US9221577B2 | J9: Melhor | K9: Base da avaliação
B10: ='Diagrama de Pareto'!B2 | C10: ='Diagrama de Pareto'!A2 | D10: {=INDEX('Diagrama de Kano'!$D$2:$D$24,MATCH($B10,'Diagrama de Kano'!$B$2:$B$24,0))} | E10: ='Diagrama de Pareto'!C2 | F10: 3 | G10: 4 | H10: 3 | I10: 5 | J10: =MAX(F10:I10) | K10: O filme prende a caixa ao palete, não a peça dentro dela. Os encaixes da patente restringem as três peças e reduzem contato entre elas.
B11: ='Diagrama de Pareto'!B3 | C11: ='Diagrama de Pareto'!A3 | D11: {=INDEX('Diagrama de Kano'!$D$2:$D$24,MATCH($B11,'Diagrama de Kano'!$B$2:$B$24,0))} | E11: ='Diagrama de Pareto'!C3 | F11: 3 | G11: 2 | H11: 3 | I11: 3 | J11: =MAX(F11:I11) | K11: Campo: quando o carrinho não acessa o ponto, a movimentação vira manual. O palete resolve o pátio e não o último trecho.
B12: ='Diagrama de Pareto'!B4 | C12: ='Diagrama de Pareto'!A4 | D12: {=INDEX('Diagrama de Kano'!$D$2:$D$24,MATCH($B12,'Diagrama de Kano'!$B$2:$B$24,0))} | E12: ='Diagrama de Pareto'!C4 | F12: 3 | G12: 4 | H12: 2 | I12: 4 | J12: =MAX(F12:I12) | K12: Campo: avarias associadas ao trecho distribuidor→obra mesmo com berço de papelão. Madeira e encaixes dedicados protegem mais; o palete apenas unitiza.
B13: ='Diagrama de Pareto'!B5 | C13: ='Diagrama de Pareto'!A5 | D13: {=INDEX('Diagrama de Kano'!$D$2:$D$24,MATCH($B13,'Diagrama de Kano'!$B$2:$B$24,0))} | E13: ='Diagrama de Pareto'!C5 | F13: 1 | G13: 2 | H13: 1 | I13: 1 | J13: =MAX(F13:I13) | K13: Nenhuma referência permite conferir a peça fechada. As frestas do engradado dão visão parcial da superfície, não de trinca.
B14: ='Diagrama de Pareto'!B6 | C14: ='Diagrama de Pareto'!A6 | D14: {=INDEX('Diagrama de Kano'!$D$2:$D$24,MATCH($B14,'Diagrama de Kano'!$B$2:$B$24,0))} | E14: ='Diagrama de Pareto'!C6 | F14: 2 | G14: 3 | H14: 1 | I14: 2 | J14: =MAX(F14:I14) | K14: Nenhuma referência define ponto de pega para a peça. As ripas servem de apoio improvisado, com risco de farpa.
B15: ='Diagrama de Pareto'!B7 | C15: ='Diagrama de Pareto'!A7 | D15: {=INDEX('Diagrama de Kano'!$D$2:$D$24,MATCH($B15,'Diagrama de Kano'!$B$2:$B$24,0))} | E15: ='Diagrama de Pareto'!C7 | F15: 2 | G15: 2 | H15: 2 | I15: 3 | J15: =MAX(F15:I15) | K15: Abertura com estilete ou saque de pregos, com o caco oculto ainda dentro. Nos encaixes a remoção é mais ordenada — inferência da especificação.
B16: ='Diagrama de Pareto'!B8 | C16: ='Diagrama de Pareto'!A8 | D16: {=INDEX('Diagrama de Kano'!$D$2:$D$24,MATCH($B16,'Diagrama de Kano'!$B$2:$B$24,0))} | E16: ='Diagrama de Pareto'!C8 | F16: 2 | G16: 3 | H16: 4 | I16: 2 | J16: =MAX(F16:I16) | K16: Papelão e encaixes são dedicados a um modelo. O palete aceita qualquer caixa; o engradado pode ser feito sob medida, mas peça a peça.
B17: ='Diagrama de Pareto'!B9 | C17: ='Diagrama de Pareto'!A9 | D17: {=INDEX('Diagrama de Kano'!$D$2:$D$24,MATCH($B17,'Diagrama de Kano'!$B$2:$B$24,0))} | E17: ='Diagrama de Pareto'!C9 | F17: 4 | G17: 3 | H17: 5 | I17: 5 | J17: =MAX(F17:I17) | K17: Paletização é o padrão do transporte. A patente reivindica redução de volume, o que aumenta a ocupação do baú.
B18: ='Diagrama de Pareto'!B10 | C18: ='Diagrama de Pareto'!A10 | D18: {=INDEX('Diagrama de Kano'!$D$2:$D$24,MATCH($B18,'Diagrama de Kano'!$B$2:$B$24,0))} | E18: ='Diagrama de Pareto'!C10 | F18: 3 | G18: 4 | H18: 4 | I18: 3 | J18: =MAX(F18:I18) | K18: Campo: a caixa apoiada no canteiro tem base estreita em relação à altura. O engradado e o palete unitizado são mais estáveis; a patente não trata de apoio isolado.
B19: ='Diagrama de Pareto'!B11 | C19: ='Diagrama de Pareto'!A11 | D19: {=INDEX('Diagrama de Kano'!$D$2:$D$24,MATCH($B19,'Diagrama de Kano'!$B$2:$B$24,0))} | E19: ='Diagrama de Pareto'!C11 | F19: 4 | G19: 2 | H19: 4 | I19: 4 | J19: =MAX(F19:I19) | K19: O papelão é o mais barato por unidade, mas o custo da avaria não está nele. A madeira é a mais cara.
B20: ='Diagrama de Pareto'!B12 | C20: ='Diagrama de Pareto'!A12 | D20: {=INDEX('Diagrama de Kano'!$D$2:$D$24,MATCH($B20,'Diagrama de Kano'!$B$2:$B$24,0))} | E20: ='Diagrama de Pareto'!C12 | F20: 4 | G20: 3 | H20: 4 | I20: 3 | J20: =MAX(F20:I20) | K20: Abrir caixa é trivial e não exige instrução. Engradado e encaixes exigem ferramenta ou sequência.
B21: ='Diagrama de Pareto'!B13 | C21: ='Diagrama de Pareto'!A13 | D21: {=INDEX('Diagrama de Kano'!$D$2:$D$24,MATCH($B21,'Diagrama de Kano'!$B$2:$B$24,0))} | E21: ='Diagrama de Pareto'!C13 | F21: 3 | G21: 4 | H21: 4 | I21: 4 | J21: =MAX(F21:I21) | K21: Campo: o papelão empilha, mas cede com peso e umidade.
... B25: ='Diagrama de Pareto'!B17 | C25: ='Diagrama de Pareto'!A17 | D25: {=INDEX('Diagrama de Kano'!$D$2:$D$24,MATCH($B25,'Diagrama de Kano'!$B$2:$B$24,0))} | E25: ='Diagrama de Pareto'!C17 | F25: 1 | G25: 3 | H25: 3 | I25: 1 | J25: =MAX(F25:I25) | K25: Campo: papelão exposto à chuva perde rigidez. O filme protege parcialmente; a madeira tolera exposição.
B26: ='Diagrama de Pareto'!B20 | C26: ='Diagrama de Pareto'!A20 | D26: {=INDEX('Diagrama de Kano'!$D$2:$D$24,MATCH($B26,'Diagrama de Kano'!$B$2:$B$24,0))} | E26: ='Diagrama de Pareto'!C20 | F26: 1 | G26: 1 | H26: 1 | I26: 1 | J26: =MAX(F26:I26) | K26: Nenhuma das referências indica que houve impacto, tombamento ou uso indevido. Confirma a lacuna levantada na pesquisa de patentes.
B27: ='Diagrama de Pareto'!B21 | C27: ='Diagrama de Pareto'!A21 | D27: {=INDEX('Diagrama de Kano'!$D$2:$D$24,MATCH($B27,'Diagrama de Kano'!$B$2:$B$24,0))} | E27: ='Diagrama de Pareto'!C21 | F27: 2 | G27: 2 | H27: 3 | I27: 4 | J27: =MAX(F27:I27) | K27: Só a patente separa a proteção por componente (bacia, caixa, tampa).
B28: ='Diagrama de Pareto'!B22 | C28: ='Diagrama de Pareto'!A22 | D28: {=INDEX('Diagrama de Kano'!$D$2:$D$24,MATCH($B28,'Diagrama de Kano'!$B$2:$B$24,0))} | E28: ='Diagrama de Pareto'!C22 | F28: 4 | G28: 2 | H28: 3 | I28: 3 | J28: =MAX(F28:I28) | K28: Montagem da caixa é imediata; engradado exige pregar e calçar.
B29: ='Diagrama de Pareto'!B23 | C29: ='Diagrama de Pareto'!A23 | D29: {=INDEX('Diagrama de Kano'!$D$2:$D$24,MATCH($B29,'Diagrama de Kano'!$B$2:$B$24,0))} | E29: ='Diagrama de Pareto'!C23 | F29: 1 | G29: 3 | H29: 2 | I29: 1 | J29: =MAX(F29:I29) | K29: Embalagem descartável não é mantida, é substituída. O engradado admite reparo pontual.
B30: ='Diagrama de Pareto'!B24 | C30: ='Diagrama de Pareto'!A24 | D30: {=INDEX('Diagrama de Kano'!$D$2:$D$24,MATCH($B30,'Diagrama de Kano'!$B$2:$B$24,0))} | E30: ='Diagrama de Pareto'!C24 | F30: 4 | G30: 2 | H30: 3 | I30: 4 | J30: =MAX(F30:I30) | K30: Caixa impressa traz modelo, lado correto e símbolo de frágil; o engradado depende de marcação manual.
B31: ='Diagrama de Pareto'!B18 | C31: ='Diagrama de Pareto'!A18 | D31: {=INDEX('Diagrama de Kano'!$D$2:$D$24,MATCH($B31,'Diagrama de Kano'!$B$2:$B$24,0))} | E31: ='Diagrama de Pareto'!C18 | F31: 4 | G31: 2 | H31: 3 | I31: 4 | J31: =MAX(F31:I31) | K31: Papelão e encaixes desmontam por dobra; o engradado exige saque de pregos.
B32: ='Diagrama de Pareto'!B19 | C32: ='Diagrama de Pareto'!A19 | D32: {=INDEX('Diagrama de Kano'!$D$2:$D$24,MATCH($B32,'Diagrama de Kano'!$B$2:$B$24,0))} | E32: ='Diagrama de Pareto'!C19 | F32: 5 | G32: 3 | H32: 2 | I32: 5 | J32: =MAX(F32:I32) | K32: Papelão é reciclável na cadeia existente; o filme stretch vira resíduo de difícil destinação.
C33: Índice ponderado pelo Mudge (Σ peso × nota ÷ Σ peso) | F33: =SUMPRODUCT($E$10:$E$32,F10:F32)/SUM($E$10:$E$32) | G33: =SUMPRODUCT($E$10:$E$32,G10:G32)/SUM($E$10:$E$32) | H33: =SUMPRODUCT($E$10:$E$32,H10:H32)/SUM($E$10:$E$32) | I33: =SUMPRODUCT($E$10:$E$32,I10:I32)/SUM($E$10:$E$32)
B34: Escala: 1 péssimo · 2 ruim · 3 regular · 4 bom · 5 ótimo (Aula 12). Avaliação da equipe a partir das evidências de campo e da especificação das patentes; a revalidar com o distribuidor. Destacadas em rosa: linhas em que nenhuma referência passa de 2.

Sheet Requisito de Projeto
B2: Requisito de projeto | C2: ID | D2: Unidade | E2: Direção | F2: Letra | G2: Como mensurar (parâmetro técnico) | H2: Método de ensaio | I2: Referência normativa
B3: =INDEX('Diagrama de Pareto'!$A$2:$A$24,MATCH($F3,'Diagrama de Pareto'!$B$2:$B$24,0)) | C3: RP1 | D3: g (1 g = 9,81 m/s²) | E3: (−) | F3: A | G3: Pico de aceleração medido na peça durante ensaio de queda livre | H3: Acelerômetro fixado na louça; queda livre sobre as faces, arestas e cantos mais críticos, na altura da classe de massa. Registrar o maior pico. | I3: ASTM D5276 (queda livre) · ASTM D4169 Schedule A, nível de garantia II
B4: =INDEX('Diagrama de Pareto'!$A$2:$A$24,MATCH($F4,'Diagrama de Pareto'!$B$2:$B$24,0)) | C4: RP2 | D4: mm | E4: (−) | F4: B | G4: Deslocamento residual da peça após o ciclo de ensaio de distribuição | H4: Marcar a posição inicial da peça, aplicar o ciclo de vibração e queda e medir o deslocamento remanescente em relação à marcação. | I4: ASTM D4169 Schedules A e E · ASTM D999 (vibração)
B5: =INDEX('Diagrama de Pareto'!$A$2:$A$24,MATCH($F5,'Diagrama de Pareto'!$B$2:$B$24,0)) | C5: RP3 | D5: N | E5: (−) | F5: F | G5: Força de partida (initial force) para iniciar o movimento do conjunto carregado | H5: Dinamômetro na altura de pega, entre articulação dos dedos e ombro; medir a força de pico ao iniciar o movimento a 0,1 m/s, em piso de canteiro. | I5: ISO 11228-2 / ABNT NBR ISO 11228-2 · valores-guia do HSE
B6: =INDEX('Diagrama de Pareto'!$A$2:$A$24,MATCH($F6,'Diagrama de Pareto'!$B$2:$B$24,0)) | C6: RP4 | D6: % da área crítica | E6: (+) | F6: C | G6: Fração da superfície sujeita a trinca que pode ser inspecionada sem abrir | H6: Delimitar a área crítica da peça (bordas, base e pontos de apoio); medir a parcela visível ou acessível com o conjunto fechado. | I6: Definição da equipe a partir da evidência de campo E-04
B7: =INDEX('Diagrama de Pareto'!$A$2:$A$24,MATCH($F7,'Diagrama de Pareto'!$B$2:$B$24,0)) | C7: RP5 | D7: un | E7: (+) | F7: G | G7: Número de pegas com vão livre compatível com mão enluvada | H7: Contagem das pegas, com verificação do vão livre mínimo e da largura contra a referência antropométrica adotada. | I7: ABNT NBR ISO 11228-1 (transporte manual) · antropometria da população adulta
B8: =INDEX('Diagrama de Pareto'!$A$2:$A$24,MATCH($F8,'Diagrama de Pareto'!$B$2:$B$24,0)) | C8: RP6 | D8: % da massa | E8: (+) | F8: H | G8: Fração da massa de fragmentos retida no interior após quebra provocada | H8: Quebra controlada de peça refugada dentro do conjunto; pesar os fragmentos retidos e os que escaparam. | I8: Ensaio próprio, derivado da exposição a corte registrada em E-04
B9: =INDEX('Diagrama de Pareto'!$A$2:$A$24,MATCH($F9,'Diagrama de Pareto'!$B$2:$B$24,0)) | C9: RP7 | D9: mm | E9: (+) | F9: D | G9: Amplitude na dimensão governante aceita sem troca de componentes | H9: Levantar o mix por volume de vendas; medir a maior e a menor peça aceitas na mesma configuração. | I9: Mix do distribuidor (pendência P-03) · ABNT NBR 15097 (aparelhos sanitários cerâmicos)
B10: =INDEX('Diagrama de Pareto'!$A$2:$A$24,MATCH($F10,'Diagrama de Pareto'!$B$2:$B$24,0)) | C10: RP8 | D10: % da área do palete | E10: (+) | F10: E | G10: Aproveitamento da área útil do palete PBR 1200 × 1000 mm | H10: Área da base do conjunto multiplicada pelo número de conjuntos por camada, dividida pela área do palete. | I10: ABNT NBR 8252 (palete PBR)
B11: =INDEX('Diagrama de Pareto'!$A$2:$A$24,MATCH($F11,'Diagrama de Pareto'!$B$2:$B$24,0)) | C11: RP9 | D11: graus (°) | E11: (+) | F11: W | G11: Ângulo de inclinação em que o conjunto carregado perde a estabilidade | H11: Plano inclinado; aumentar a inclinação até o tombamento, com o conjunto na configuração mais desfavorável de carga. | I11: ASTM D6179 (manuseio de cargas unitizadas), ensaio de estabilidade
B12: =INDEX('Diagrama de Pareto'!$A$2:$A$24,MATCH($F12,'Diagrama de Pareto'!$B$2:$B$24,0)) | C12: RP10 | D12: etapas | E12: (−) | F12: I | G12: Etapas até o primeiro uso correto por operador sem treinamento | H12: Operador que nunca usou o produto executa o ciclo; contar as ações elementares e registrar erros até a execução correta. | I12: Ensaio de usabilidade próprio, derivado do cenário de uso
B13: =INDEX('Diagrama de Pareto'!$A$2:$A$24,MATCH($F13,'Diagrama de Pareto'!$B$2:$B$24,0)) | C13: RP11 | D13: kN | E13: (+) | F13: K | G13: Carga de compressão suportada sem deformação que comprometa a proteção | H13: Compressão vertical em prensa, a velocidade constante, até a deformação que reduza a proteção; altura de pilha conforme a prática do distribuidor. | I13: ASTM D642 (compressão) · ASTM D4169 Schedule C
B14: =INDEX('Diagrama de Pareto'!$A$2:$A$24,MATCH($F14,'Diagrama de Pareto'!$B$2:$B$24,0)) | C14: RP12 | D14: % (coeficiente de variação) | E14: (−) | F14: L | G14: Coeficiente de variação do pico de aceleração entre unidades e repetições | H14: Repetir o ensaio de queda em amostra de unidades diferentes e calcular desvio-padrão sobre a média dos picos. | I14: ASTM D5276, repetido sobre amostra · tratamento estatístico
... B25: =INDEX('Diagrama de Pareto'!$A$2:$A$24,MATCH($F25,'Diagrama de Pareto'!$B$2:$B$24,0)) | C25: RP23 | D25: R$/ciclo | E25: (−) | F25: V | G25: Custo total do conjunto rateado pelo número de ciclos de vida útil | H25: Custo de aquisição somado a manutenção e frete de retorno, dividido pelos ciclos alcançados no ensaio cíclico. | I25: Custo-meta do projeto · comparação com o custo médio da avaria evitada
B27: Cada requisito do cliente dá origem a um requisito de projeto. A numeração RP1 a RP23 é a do grupo e foi preservada, porque a Matriz de Relacionamento, a Matriz de Correlação e o QFD referenciam esses identificadores. A coluna de referência indica a norma ou o método que define como o parâmetro é medido; onde não há norma aplicável ao caso, o ensaio é próprio e está descrito na coluna de método. As metas numéricas ficam na aba Especificação Meta.
B29: A coluna "Letra" liga cada requisito de projeto ao requisito do cliente por busca, não por posição. Isso permite reordenar o Pareto sem quebrar o vínculo — foi por referência posicional que a pontuação de dez requisitos ficou trocada na versão anterior.

Sheet MUDGE 2

Sheet Matriz de Relacionamento
F2: Requisito de projeto
B4: ID | C4: Requisito Cliente | D4: Pontuação Mudge | E4: Grau de Importância | F4: Matriz de Relacionamento | AC4: Valor de Importância | AD4: 9 | AE4: 3 | AF4: 1 | AG4: Verificação | AH4: Classe Kano | AI4: Peso ajustado
F5: ='Requisito de Projeto'!C3 | G5: ='Requisito de Projeto'!C4 | H5: ='Requisito de Projeto'!C5 | I5: ='Requisito de Projeto'!C6 | J5: ='Requisito de Projeto'!C7 | K5: ='Requisito de Projeto'!C8 | L5: ='Requisito de Projeto'!C9 | M5: ='Requisito de Projeto'!C10 | N5: ='Requisito de Projeto'!C11 | O5: ='Requisito de Projeto'!C12 | P5: ='Requisito de Projeto'!C13 | Q5: ='Requisito de Projeto'!C14 | R5: ='Requisito de Projeto'!C15 | S5: ='Requisito de Projeto'!C16 | T5: ='Requisito de Projeto'!C17 | U5: ='Requisito de Projeto'!C18 | V5: ='Requisito de Projeto'!C19 | W5: ='Requisito de Projeto'!C20 | X5: ='Requisito de Projeto'!C21 | Y5: ='Requisito de Projeto'!C22 | Z5: ='Requisito de Projeto'!C23 | AA5: ='Requisito de Projeto'!C24 | AB5: ='Requisito de Projeto'!C25
C6: Requisito de projeto → unidade (direção) | F6: ='Requisito de Projeto'!B3&" — "&'Requisito de Projeto'!D3&" "&'Requisito de Projeto'!E3 | G6: ='Requisito de Projeto'!B4&" — "&'Requisito de Projeto'!D4&" "&'Requisito de Projeto'!E4 | H6: ='Requisito de Projeto'!B5&" — "&'Requisito de Projeto'!D5&" "&'Requisito de Projeto'!E5 | I6: ='Requisito de Projeto'!B6&" — "&'Requisito de Projeto'!D6&" "&'Requisito de Projeto'!E6 | J6: ='Requisito de Projeto'!B7&" — "&'Requisito de Projeto'!D7&" "&'Requisito de Projeto'!E7 | K6: ='Requisito de Projeto'!B8&" — "&'Requisito de Projeto'!D8&" "&'Requisito de Projeto'!E8 | L6: ='Requisito de Projeto'!B9&" — "&'Requisito de Projeto'!D9&" "&'Requisito de Projeto'!E9 | M6: ='Requisito de Projeto'!B10&" — "&'Requisito de Projeto'!D10&" "&'Requisito de Projeto'!E10 | N6: ='Requisito de Projeto'!B11&" — "&'Requisito de Projeto'!D11&" "&'Requisito de Projeto'!E11 | O6: ='Requisito de Projeto'!B12&" — "&'Requisito de Projeto'!D12&" "&'Requisito de Projeto'!E12 | P6: ='Requisito de Projeto'!B13&" — "&'Requisito de Projeto'!D13&" "&'Requisito de Projeto'!E13 | Q6: ='Requisito de Projeto'!B14&" — "&'Requisito de Projeto'!D14&" "&'Requisito de Projeto'!E14 | R6: ='Requisito de Projeto'!B15&" — "&'Requisito de Projeto'!D15&" "&'Requisito de Projeto'!E15 | S6: ='Requisito de Projeto'!B16&" — "&'Requisito de Projeto'!D16&" "&'Requisito de Projeto'!E16 | T6: ='Requisito de Projeto'!B17&" — "&'Requisito de Projeto'!D17&" "&'Requisito de Projeto'!E17 | U6: ='Requisito de Projeto'!B18&" — "&'Requisito de Projeto'!D18&" "&'Requisito de Projeto'!E18 | V6: ='Requisito de Projeto'!B19&" — "&'Requisito de Projeto'!D19&" "&'Requisito de Projeto'!E19 | W6: ='Requisito de Projeto'!B20&" — "&'Requisito de Projeto'!D20&" "&'Requisito de Projeto'!E20 | X6: ='Requisito de Projeto'!B21&" — "&'Requisito de Projeto'!D21&" "&'Requisito de Projeto'!E21 | Y6: ='Requisito de Projeto'!B22&" — "&'Requisito de Projeto'!D22&" "&'Requisito de Projeto'!E22 | Z6: ='Requisito de Projeto'!B23&" — "&'Requisito de Projeto'!D23&" "&'Requisito de Projeto'!E23 | AA6: ='Requisito de Projeto'!B24&" — "&'Requisito de Projeto'!D24&" "&'Requisito de Projeto'!E24 | AB6: ='Requisito de Projeto'!B25&" — "&'Requisito de Projeto'!D25&" "&'Requisito de Projeto'!E25
B7: ='Diagrama de Pareto'!B2 | C7: ='Diagrama de Pareto'!A2 | D7: ='Diagrama de Pareto'!C2 | E7: ='Diagrama de Pareto'!F2 | F7: 9 | G7: 3 | H7: 3 | I7: 0 | J7: 0 | K7: 1 | L7: 3 | M7: 0 | N7: 0 | O7: 0 | P7: 0 | Q7: 3 | R7: 3 | S7: 0 | T7: 0 | U7: 0 | V7: 0 | W7: 0 | X7: 1 | Y7: 0 | Z7: 0 | AA7: 0 | AB7: 0 | AC7: =D7*SUM(F7:AB7) | AD7: =COUNTIF(F7:AB7,9) | AE7: =COUNTIF(F7:AB7,3) | AF7: =COUNTIF(F7:AB7,1) | AG7: =IF(SUM(F7:AB7)=0,"SEM RELAÇÃO","ok") | AH7: {=INDEX('Diagrama de Kano'!$D$2:$D$24,MATCH($B7,'Diagrama de Kano'!$B$2:$B$24,0))} | AI7: =D7*IF(AH7="Atrativo",$E$34,1)
B8: ='Diagrama de Pareto'!B3 | C8: ='Diagrama de Pareto'!A3 | D8: ='Diagrama de Pareto'!C3 | E8: ='Diagrama de Pareto'!F3 | F8: 0 | G8: 9 | H8: 0 | I8: 0 | J8: 3 | K8: 0 | L8: 0 | M8: 0 | N8: 1 | O8: 0 | P8: 1 | Q8: 0 | R8: 0 | S8: 0 | T8: 3 | U8: 0 | V8: 0 | W8: 1 | X8: 0 | Y8: 0 | Z8: 0 | AA8: 0 | AB8: 0 | AC8: =D8*SUM(F8:AB8) | AD8: =COUNTIF(F8:AB8,9) | AE8: =COUNTIF(F8:AB8,3) | AF8: =COUNTIF(F8:AB8,1) | AG8: =IF(SUM(F8:AB8)=0,"SEM RELAÇÃO","ok") | AH8: {=INDEX('Diagrama de Kano'!$D$2:$D$24,MATCH($B8,'Diagrama de Kano'!$B$2:$B$24,0))} | AI8: =D8*IF(AH8="Atrativo",$E$34,1)
B9: ='Diagrama de Pareto'!B4 | C9: ='Diagrama de Pareto'!A4 | D9: ='Diagrama de Pareto'!C4 | E9: ='Diagrama de Pareto'!F4 | F9: 3 | G9: 0 | H9: 9 | I9: 0 | J9: 3 | K9: 0 | L9: 0 | M9: 0 | N9: 0 | O9: 0 | P9: 0 | Q9: 1 | R9: 3 | S9: 1 | T9: 0 | U9: 3 | V9: 0 | W9: 0 | X9: 0 | Y9: 0 | Z9: 0 | AA9: 0 | AB9: 0 | AC9: =D9*SUM(F9:AB9) | AD9: =COUNTIF(F9:AB9,9) | AE9: =COUNTIF(F9:AB9,3) | AF9: =COUNTIF(F9:AB9,1) | AG9: =IF(SUM(F9:AB9)=0,"SEM RELAÇÃO","ok") | AH9: {=INDEX('Diagrama de Kano'!$D$2:$D$24,MATCH($B9,'Diagrama de Kano'!$B$2:$B$24,0))} | AI9: =D9*IF(AH9="Atrativo",$E$34,1)
B10: ='Diagrama de Pareto'!B5 | C10: ='Diagrama de Pareto'!A5 | D10: ='Diagrama de Pareto'!C5 | E10: ='Diagrama de Pareto'!F5 | F10: 0 | G10: 0 | H10: 0 | I10: 9 | J10: 0 | K10: 1 | L10: 0 | M10: 0 | N10: 0 | O10: 0 | P10: 3 | Q10: 0 | R10: 0 | S10: 0 | T10: 0 | U10: 0 | V10: 3 | W10: 0 | X10: 0 | Y10: 0 | Z10: 1 | AA10: 0 | AB10: 0 | AC10: =D10*SUM(F10:AB10) | AD10: =COUNTIF(F10:AB10,9) | AE10: =COUNTIF(F10:AB10,3) | AF10: =COUNTIF(F10:AB10,1) | AG10: =IF(SUM(F10:AB10)=0,"SEM RELAÇÃO","ok") | AH10: {=INDEX('Diagrama de Kano'!$D$2:$D$24,MATCH($B10,'Diagrama de Kano'!$B$2:$B$24,0))} | AI10: =D10*IF(AH10="Atrativo",$E$34,1)
B11: ='Diagrama de Pareto'!B6 | C11: ='Diagrama de Pareto'!A6 | D11: ='Diagrama de Pareto'!C6 | E11: ='Diagrama de Pareto'!F6 | F11: 0 | G11: 3 | H11: 0 | I11: 0 | J11: 9 | K11: 3 | L11: 0 | M11: 0 | N11: 0 | O11: 0 | P11: 1 | Q11: 0 | R11: 0 | S11: 0 | T11: 0 | U11: 0 | V11: 0 | W11: 0 | X11: 0 | Y11: 0 | Z11: 0 | AA11: 0 | AB11: 0 | AC11: =D11*SUM(F11:AB11) | AD11: =COUNTIF(F11:AB11,9) | AE11: =COUNTIF(F11:AB11,3) | AF11: =COUNTIF(F11:AB11,1) | AG11: =IF(SUM(F11:AB11)=0,"SEM RELAÇÃO","ok") | AH11: {=INDEX('Diagrama de Kano'!$D$2:$D$24,MATCH($B11,'Diagrama de Kano'!$B$2:$B$24,0))} | AI11: =D11*IF(AH11="Atrativo",$E$34,1)
B12: ='Diagrama de Pareto'!B7 | C12: ='Diagrama de Pareto'!A7 | D12: ='Diagrama de Pareto'!C7 | E12: ='Diagrama de Pareto'!F7 | F12: 3 | G12: 0 | H12: 3 | I12: 3 | J12: 3 | K12: 9 | L12: 0 | M12: 0 | N12: 1 | O12: 0 | P12: 3 | Q12: 0 | R12: 0 | S12: 0 | T12: 0 | U12: 0 | V12: 1 | W12: 0 | X12: 0 | Y12: 0 | Z12: 0 | AA12: 1 | AB12: 0 | AC12: =D12*SUM(F12:AB12) | AD12: =COUNTIF(F12:AB12,9) | AE12: =COUNTIF(F12:AB12,3) | AF12: =COUNTIF(F12:AB12,1) | AG12: =IF(SUM(F12:AB12)=0,"SEM RELAÇÃO","ok") | AH12: {=INDEX('Diagrama de Kano'!$D$2:$D$24,MATCH($B12,'Diagrama de Kano'!$B$2:$B$24,0))} | AI12: =D12*IF(AH12="Atrativo",$E$34,1)
B13: ='Diagrama de Pareto'!B8 | C13: ='Diagrama de Pareto'!A8 | D13: ='Diagrama de Pareto'!C8 | E13: ='Diagrama de Pareto'!F8 | F13: 3 | G13: 0 | H13: 0 | I13: 0 | J13: 0 | K13: 0 | L13: 9 | M13: 1 | N13: 0 | O13: 0 | P13: 1 | Q13: 0 | R13: 0 | S13: 0 | T13: 1 | U13: 0 | V13: 0 | W13: 3 | X13: 0 | Y13: 0 | Z13: 0 | AA13: 0 | AB13: 0 | AC13: =D13*SUM(F13:AB13) | AD13: =COUNTIF(F13:AB13,9) | AE13: =COUNTIF(F13:AB13,3) | AF13: =COUNTIF(F13:AB13,1) | AG13: =IF(SUM(F13:AB13)=0,"SEM RELAÇÃO","ok") | AH13: {=INDEX('Diagrama de Kano'!$D$2:$D$24,MATCH($B13,'Diagrama de Kano'!$B$2:$B$24,0))} | AI13: =D13*IF(AH13="Atrativo",$E$34,1)
B14: ='Diagrama de Pareto'!B9 | C14: ='Diagrama de Pareto'!A9 | D14: ='Diagrama de Pareto'!C9 | E14: ='Diagrama de Pareto'!F9 | F14: 0 | G14: 0 | H14: 0 | I14: 0 | J14: 0 | K14: 0 | L14: 1 | M14: 9 | N14: 3 | O14: 0 | P14: 0 | Q14: 3 | R14: 0 | S14: 3 | T14: 3 | U14: 0 | V14: 0 | W14: 1 | X14: 0 | Y14: 0 | Z14: 0 | AA14: 0 | AB14: 0 | AC14: =D14*SUM(F14:AB14) | AD14: =COUNTIF(F14:AB14,9) | AE14: =COUNTIF(F14:AB14,3) | AF14: =COUNTIF(F14:AB14,1) | AG14: =IF(SUM(F14:AB14)=0,"SEM RELAÇÃO","ok") | AH14: {=INDEX('Diagrama de Kano'!$D$2:$D$24,MATCH($B14,'Diagrama de Kano'!$B$2:$B$24,0))} | AI14: =D14*IF(AH14="Atrativo",$E$34,1)
B15: ='Diagrama de Pareto'!B10 | C15: ='Diagrama de Pareto'!A10 | D15: ='Diagrama de Pareto'!C10 | E15: ='Diagrama de Pareto'!F10 | F15: 3 | G15: 0 | H15: 0 | I15: 0 | J15: 0 | K15: 0 | L15: 0 | M15: 0 | N15: 9 | O15: 0 | P15: 0 | Q15: 1 | R15: 0 | S15: 0 | T15: 1 | U15: 0 | V15: 0 | W15: 0 | X15: 0 | Y15: 0 | Z15: 0 | AA15: 0 | AB15: 0 | AC15: =D15*SUM(F15:AB15) | AD15: =COUNTIF(F15:AB15,9) | AE15: =COUNTIF(F15:AB15,3) | AF15: =COUNTIF(F15:AB15,1) | AG15: =IF(SUM(F15:AB15)=0,"SEM RELAÇÃO","ok") | AH15: {=INDEX('Diagrama de Kano'!$D$2:$D$24,MATCH($B15,'Diagrama de Kano'!$B$2:$B$24,0))} | AI15: =D15*IF(AH15="Atrativo",$E$34,1)
B16: ='Diagrama de Pareto'!B11 | C16: ='Diagrama de Pareto'!A11 | D16: ='Diagrama de Pareto'!C11 | E16: ='Diagrama de Pareto'!F11 | F16: 0 | G16: 0 | H16: 0 | I16: 0 | J16: 0 | K16: 0 | L16: 0 | M16: 0 | N16: 0 | O16: 1 | P16: 0 | Q16: 0 | R16: 0 | S16: 3 | T16: 0 | U16: 0 | V16: 0 | W16: 3 | X16: 0 | Y16: 0 | Z16: 0 | AA16: 3 | AB16: 9 | AC16: =D16*SUM(F16:AB16) | AD16: =COUNTIF(F16:AB16,9) | AE16: =COUNTIF(F16:AB16,3) | AF16: =COUNTIF(F16:AB16,1) | AG16: =IF(SUM(F16:AB16)=0,"SEM RELAÇÃO","ok") | AH16: {=INDEX('Diagrama de Kano'!$D$2:$D$24,MATCH($B16,'Diagrama de Kano'!$B$2:$B$24,0))} | AI16: =D16*IF(AH16="Atrativo",$E$34,1)
B17: ='Diagrama de Pareto'!B12 | C17: ='Diagrama de Pareto'!A12 | D17: ='Diagrama de Pareto'!C12 | E17: ='Diagrama de Pareto'!F12 | F17: 0 | G17: 0 | H17: 0 | I17: 0 | J17: 0 | K17: 0 | L17: 0 | M17: 0 | N17: 0 | O17: 9 | P17: 3 | Q17: 0 | R17: 0 | S17: 3 | T17: 1 | U17: 1 | V17: 0 | W17: 3 | X17: 0 | Y17: 1 | Z17: 0 | AA17: 3 | AB17: 1 | AC17: =D17*SUM(F17:AB17) | AD17: =COUNTIF(F17:AB17,9) | AE17: =COUNTIF(F17:AB17,3) | AF17: =COUNTIF(F17:AB17,1) | AG17: =IF(SUM(F17:AB17)=0,"SEM RELAÇÃO","ok") | AH17: {=INDEX('Diagrama de Kano'!$D$2:$D$24,MATCH($B17,'Diagrama de Kano'!$B$2:$B$24,0))} | AI17: =D17*IF(AH17="Atrativo",$E$34,1)
B18: ='Diagrama de Pareto'!B13 | C18: ='Diagrama de Pareto'!A13 | D18: ='Diagrama de Pareto'!C13 | E18: ='Diagrama de Pareto'!F13 | F18: 0 | G18: 0 | H18: 0 | I18: 0 | J18: 1 | K18: 0 | L18: 0 | M18: 3 | N18: 3 | O18: 0 | P18: 9 | Q18: 0 | R18: 0 | S18: 0 | T18: 0 | U18: 0 | V18: 0 | W18: 1 | X18: 3 | Y18: 0 | Z18: 1 | AA18: 1 | AB18: 0 | AC18: =D18*SUM(F18:AB18) | AD18: =COUNTIF(F18:AB18,9) | AE18: =COUNTIF(F18:AB18,3) | AF18: =COUNTIF(F18:AB18,1) | AG18: =IF(SUM(F18:AB18)=0,"SEM RELAÇÃO","ok") | AH18: {=INDEX('Diagrama de Kano'!$D$2:$D$24,MATCH($B18,'Diagrama de Kano'!$B$2:$B$24,0))} | AI18: =D18*IF(AH18="Atrativo",$E$34,1)
... B29: ='Diagrama de Pareto'!B24 | C29: ='Diagrama de Pareto'!A24 | D29: ='Diagrama de Pareto'!C24 | E29: ='Diagrama de Pareto'!F24 | F29: 0 | G29: 0 | H29: 0 | I29: 0 | J29: 0 | K29: 0 | L29: 1 | M29: 0 | N29: 0 | O29: 0 | P29: 3 | Q29: 0 | R29: 0 | S29: 0 | T29: 0 | U29: 0 | V29: 0 | W29: 1 | X29: 9 | Y29: 0 | Z29: 0 | AA29: 0 | AB29: 1 | AC29: =D29*SUM(F29:AB29) | AD29: =COUNTIF(F29:AB29,9) | AE29: =COUNTIF(F29:AB29,3) | AF29: =COUNTIF(F29:AB29,1) | AG29: =IF(SUM(F29:AB29)=0,"SEM RELAÇÃO","ok") | AH29: {=INDEX('Diagrama de Kano'!$D$2:$D$24,MATCH($B29,'Diagrama de Kano'!$B$2:$B$24,0))} | AI29: =D29*IF(AH29="Atrativo",$E$34,1)
C30: Valor de importância (Σ Mudge × relação) | F30: =SUMPRODUCT($D$7:$D$29,F7:F29) | G30: =SUMPRODUCT($D$7:$D$29,G7:G29) | H30: =SUMPRODUCT($D$7:$D$29,H7:H29) | I30: =SUMPRODUCT($D$7:$D$29,I7:I29) | J30: =SUMPRODUCT($D$7:$D$29,J7:J29) | K30: =SUMPRODUCT($D$7:$D$29,K7:K29) | L30: =SUMPRODUCT($D$7:$D$29,L7:L29) | M30: =SUMPRODUCT($D$7:$D$29,M7:M29) | ... AB30: =SUMPRODUCT($D$7:$D$29,AB7:AB29) | AC30: =SUM(AC7:AC29)
C31: Importância relativa | F31: =F30/SUM($F$30:$AB$30) | G31: =G30/SUM($F$30:$AB$30) | H31: =H30/SUM($F$30:$AB$30) | I31: =I30/SUM($F$30:$AB$30) | J31: =J30/SUM($F$30:$AB$30) | K31: =K30/SUM($F$30:$AB$30) | L31: =L30/SUM($F$30:$AB$30) | M31: =M30/SUM($F$30:$AB$30) | ... AB31: =AB30/SUM($F$30:$AB$30)
C32: Classificação | F32: =RANK(F30,$F$30:$AB$30) | G32: =RANK(G30,$F$30:$AB$30) | H32: =RANK(H30,$F$30:$AB$30) | I32: =RANK(I30,$F$30:$AB$30) | J32: =RANK(J30,$F$30:$AB$30) | K32: =RANK(K30,$F$30:$AB$30) | L32: =RANK(L30,$F$30:$AB$30) | M32: =RANK(M30,$F$30:$AB$30) | ... AB32: =RANK(AB30,$F$30:$AB$30)
C34: Fator aplicado aos requisitos atrativos do Kano (editável) | E34: 1.5
C35: Valor com atrativos ajustados (sensibilidade) | F35: =SUMPRODUCT($AI$7:$AI$29,F7:F29) | G35: =SUMPRODUCT($AI$7:$AI$29,G7:G29) | H35: =SUMPRODUCT($AI$7:$AI$29,H7:H29) | I35: =SUMPRODUCT($AI$7:$AI$29,I7:I29) | J35: =SUMPRODUCT($AI$7:$AI$29,J7:J29) | K35: =SUMPRODUCT($AI$7:$AI$29,K7:K29) | L35: =SUMPRODUCT($AI$7:$AI$29,L7:L29) | M35: =SUMPRODUCT($AI$7:$AI$29,M7:M29) | ... AB35: =SUMPRODUCT($AI$7:$AI$29,AB7:AB29)
C36: Classificação ajustada | F36: =RANK(F35,$F$35:$AB$35) | G36: =RANK(G35,$F$35:$AB$35) | H36: =RANK(H35,$F$35:$AB$35) | I36: =RANK(I35,$F$35:$AB$35) | J36: =RANK(J35,$F$35:$AB$35) | K36: =RANK(K35,$F$35:$AB$35) | L36: =RANK(L35,$F$35:$AB$35) | M36: =RANK(M35,$F$35:$AB$35) | ... AB36: =RANK(AB35,$F$35:$AB$35)
C38: Relações maiores que zero por requisito de projeto | F38: =COUNTIF(F7:F29,">0") | G38: =COUNTIF(G7:G29,">0") | H38: =COUNTIF(H7:H29,">0") | I38: =COUNTIF(I7:I29,">0") | J38: =COUNTIF(J7:J29,">0") | K38: =COUNTIF(K7:K29,">0") | L38: =COUNTIF(L7:L29,">0") | M38: =COUNTIF(M7:M29,">0") | ... AB38: =COUNTIF(AB7:AB29,">0")
C39: Verificação | F39: =IF(SUM(F7:F29)=0,"SEM RELAÇÃO","ok") | G39: =IF(SUM(G7:G29)=0,"SEM RELAÇÃO","ok") | H39: =IF(SUM(H7:H29)=0,"SEM RELAÇÃO","ok") | I39: =IF(SUM(I7:I29)=0,"SEM RELAÇÃO","ok") | J39: =IF(SUM(J7:J29)=0,"SEM RELAÇÃO","ok") | K39: =IF(SUM(K7:K29)=0,"SEM RELAÇÃO","ok") | L39: =IF(SUM(L7:L29)=0,"SEM RELAÇÃO","ok") | M39: =IF(SUM(M7:M29)=0,"SEM RELAÇÃO","ok") | ... AB39: =IF(SUM(AB7:AB29)=0,"SEM RELAÇÃO","ok")
B41: Escala: 9 relação forte · 3 média · 1 fraca · 0 sem relação. Todas as células estão preenchidas: o zero é resposta, não lacuna. Como cada requisito de projeto nasce de um requisito do cliente, a diagonal traz o 9 correspondente; fora dela ficam os parâmetros que também verificam outros requisitos.
B44: Relações revisadas nesta rodada
B45: Requisito | C45: RP | D45: Valor | E45: Justificativa
B46: O | C46: RP23 | D46: 9 | E46: O número de ciclos é o denominador do custo por ciclo: é a relação mais forte que faltava
B47: A | C47: RP2 | D47: 3 | E47: Imobilizar reduz o impacto que chega à peça: amortecimento e imobilização são acoplados
B48: F | C48: RP5 | D48: 3 | E48: Ponto de pega definido é o que viabiliza movimentar o conjunto
B49: E | C49: RP14 | D49: 3 | E49: O volume por peça determina quantos conjuntos cabem no veículo
B50: K | C50: RP9 | D50: 3 | E50: Empilhar depende diretamente da estabilidade da pilha
B51: K | C51: RP8 | D51: 3 | E51: O empilhamento acontece sobre o palete
B52: J | C52: RP8 | D52: 3 | E52: Compacidade governa o aproveitamento da área do palete
B53: J | C53: RP23 | D53: 3 | E53: Volume por peça dilui o frete e entra no custo por ciclo
B54: O | C54: RP21 | D54: 3 | E54: Contar ciclos exige identificar a unidade
B55: Q | C55: RP20 | D55: 3 | E55: Modularidade é o que torna a manutenção simples
B56: Q | C56: RP23 | D56: 3 | E56: Tempo de manutenção é custo lançado em cada ciclo
B57: Q | C57: RP17 | D57: 3 | E57: Não se recondiciona o que não se desmonta
... B65: S | C65: RP23 | D65: 1 | E65: A escolha de material com cadeia de reciclagem afeta o custo
B67: O custo por ciclo (RP23) tinha apenas 2 relações e passou a 8: é o requisito de projeto mais afetado pelo modelo retornável, porque ciclos de vida, manutenção, volume e material entram todos no denominador.

Sheet Matriz de Correlação
C2: ='Requisito de Projeto'!C3 | D2: ='Requisito de Projeto'!C4 | E2: ='Requisito de Projeto'!C5 | F2: ='Requisito de Projeto'!C6 | G2: ='Requisito de Projeto'!C7 | H2: ='Requisito de Projeto'!C8 | I2: ='Requisito de Projeto'!C9 | J2: ='Requisito de Projeto'!C10 | K2: ='Requisito de Projeto'!C11 | L2: ='Requisito de Projeto'!C12 | M2: ='Requisito de Projeto'!C13 | N2: ='Requisito de Projeto'!C14 | O2: ='Requisito de Projeto'!C15 | P2: ='Requisito de Projeto'!C16 | Q2: ='Requisito de Projeto'!C17 | R2: ='Requisito de Projeto'!C18 | S2: ='Requisito de Projeto'!C19 | T2: ='Requisito de Projeto'!C20 | U2: ='Requisito de Projeto'!C21 | V2: ='Requisito de Projeto'!C22 | W2: ='Requisito de Projeto'!C23 | X2: ='Requisito de Projeto'!C24 | Y2: ='Requisito de Projeto'!C25
B3: ='Requisito de Projeto'!C3&" · "&'Requisito de Projeto'!B3&" — "&'Requisito de Projeto'!D3&" "&'Requisito de Projeto'!E3 | D3: − | E3: − | F3: − | G3: + | H3: + | I3: −− | J3: 0 | K3: + | L3: − | M3: − | N3: + | O3: + | P3: + | Q3: + | R3: + | S3: + | T3: + | U3: − | V3: − | W3: 0 | X3: − | Y3: −
B4: ='Requisito de Projeto'!C4&" · "&'Requisito de Projeto'!B4&" — "&'Requisito de Projeto'!D4&" "&'Requisito de Projeto'!E4 | E4: − | F4: 0 | G4: + | H4: − | I4: − | J4: + | K4: − | L4: + | M4: + | N4: − | O4: + | P4: − | Q4: ++ | R4: 0 | S4: − | T4: − | U4: + | V4: + | W4: 0 | X4: + | Y4: +
B5: ='Requisito de Projeto'!C5&" · "&'Requisito de Projeto'!B5&" — "&'Requisito de Projeto'!D5&" "&'Requisito de Projeto'!E5 | F5: − | G5: + | H5: + | I5: ++ | J5: − | K5: + | L5: − | M5: 0 | N5: − | O5: ++ | P5: + | Q5: −− | R5: + | S5: 0 | T5: 0 | U5: 0 | V5: 0 | W5: 0 | X5: 0 | Y5: −
B6: ='Requisito de Projeto'!C6&" · "&'Requisito de Projeto'!B6&" — "&'Requisito de Projeto'!D6&" "&'Requisito de Projeto'!E6 | G6: + | H6: −− | I6: 0 | J6: 0 | K6: − | L6: + | M6: 0 | N6: − | O6: − | P6: − | Q6: 0 | R6: − | S6: + | T6: 0 | U6: 0 | V6: 0 | W6: 0 | X6: 0 | Y6: +
B7: ='Requisito de Projeto'!C7&" · "&'Requisito de Projeto'!B7&" — "&'Requisito de Projeto'!D7&" "&'Requisito de Projeto'!E7 | H7: − | I7: + | J7: − | K7: + | L7: − | M7: − | N7: − | O7: − | P7: 0 | Q7: − | R7: 0 | S7: + | T7: + | U7: − | V7: − | W7: − | X7: − | Y7: −
B8: ='Requisito de Projeto'!C8&" · "&'Requisito de Projeto'!B8&" — "&'Requisito de Projeto'!D8&" "&'Requisito de Projeto'!E8 | I8: 0 | J8: 0 | K8: 0 | L8: − | M8: − | N8: + | O8: + | P8: + | Q8: − | R8: + | S8: + | T8: + | U8: 0 | V8: − | W8: + | X8: 0 | Y8: −
B9: ='Requisito de Projeto'!C9&" · "&'Requisito de Projeto'!B9&" — "&'Requisito de Projeto'!D9&" "&'Requisito de Projeto'!E9 | J9: − | K9: + | L9: − | M9: − | N9: 0 | O9: − | P9: 0 | Q9: −− | R9: 0 | S9: + | T9: ++ | U9: − | V9: − | W9: 0 | X9: − | Y9: −
B10: ='Requisito de Projeto'!C10&" · "&'Requisito de Projeto'!B10&" — "&'Requisito de Projeto'!D10&" "&'Requisito de Projeto'!E10 | K10: − | L10: 0 | M10: 0 | N10: + | O10: 0 | P10: 0 | Q10: ++ | R10: 0 | S10: 0 | T10: 0 | U10: 0 | V10: 0 | W10: 0 | X10: 0 | Y10: +
B11: ='Requisito de Projeto'!C11&" · "&'Requisito de Projeto'!B11&" — "&'Requisito de Projeto'!D11&" "&'Requisito de Projeto'!E11 | L11: − | M11: 0 | N11: 0 | O11: + | P11: 0 | Q11: − | R11: + | S11: − | T11: 0 | U11: 0 | V11: − | W11: 0 | X11: 0 | Y11: −
B12: ='Requisito de Projeto'!C12&" · "&'Requisito de Projeto'!B12&" — "&'Requisito de Projeto'!D12&" "&'Requisito de Projeto'!E12 | M12: + | N12: − | O12: 0 | P12: ++ | Q12: + | R12: − | S12: − | T12: − | U12: + | V12: + | W12: 0 | X12: + | Y12: 0
B13: ='Requisito de Projeto'!C13&" · "&'Requisito de Projeto'!B13&" — "&'Requisito de Projeto'!D13&" "&'Requisito de Projeto'!E13 | N13: 0 | O13: + | P13: 0 | Q13: 0 | R13: 0 | S13: − | T13: − | U13: ++ | V13: + | W13: 0 | X13: ++ | Y13: +
B14: ='Requisito de Projeto'!C14&" · "&'Requisito de Projeto'!B14&" — "&'Requisito de Projeto'!D14&" "&'Requisito de Projeto'!E14 | O14: + | P14: ++ | Q14: − | R14: ++ | S14: + | T14: + | U14: 0 | V14: − | W14: + | X14: 0 | Y14: −
B15: ='Requisito de Projeto'!C15&" · "&'Requisito de Projeto'!B15&" — "&'Requisito de Projeto'!D15&" "&'Requisito de Projeto'!E15 | P15: + | Q15: + | R15: + | S15: − | T15: − | U15: + | V15: + | W15: + | X15: + | Y15: +
B16: ='Requisito de Projeto'!C16&" · "&'Requisito de Projeto'!B16&" — "&'Requisito de Projeto'!D16&" "&'Requisito de Projeto'!E16 | Q16: − | R16: ++ | S16: + | T16: + | U16: 0 | V16: ++ | W16: 0 | X16: 0 | Y16: −
B17: ='Requisito de Projeto'!C17&" · "&'Requisito de Projeto'!B17&" — "&'Requisito de Projeto'!D17&" "&'Requisito de Projeto'!E17 | R17: 0 | S17: ++ | T17: + | U17: 0 | V17: ++ | W17: 0 | X17: + | Y17: +
B18: ='Requisito de Projeto'!C18&" · "&'Requisito de Projeto'!B18&" — "&'Requisito de Projeto'!D18&" "&'Requisito de Projeto'!E18 | S18: + | T18: + | U18: 0 | V18: 0 | W18: 0 | X18: 0 | Y18: −
B19: ='Requisito de Projeto'!C19&" · "&'Requisito de Projeto'!B19&" — "&'Requisito de Projeto'!D19&" "&'Requisito de Projeto'!E19 | T19: + | U19: − | V19: − | W19: + | X19: − | Y19: −
B20: ='Requisito de Projeto'!C20&" · "&'Requisito de Projeto'!B20&" — "&'Requisito de Projeto'!D20&" "&'Requisito de Projeto'!E20 | U20: − | V20: ++ | W20: ++ | X20: ++ | Y20: −
B21: ='Requisito de Projeto'!C21&" · "&'Requisito de Projeto'!B21&" — "&'Requisito de Projeto'!D21&" "&'Requisito de Projeto'!E21 | V21: + | W21: 0 | X21: ++ | Y21: +
B22: ='Requisito de Projeto'!C22&" · "&'Requisito de Projeto'!B22&" — "&'Requisito de Projeto'!D22&" "&'Requisito de Projeto'!E22 | W22: − | X22: + | Y22: +
B23: ='Requisito de Projeto'!C23&" · "&'Requisito de Projeto'!B23&" — "&'Requisito de Projeto'!D23&" "&'Requisito de Projeto'!E23 | X23: 0 | Y23: +
B24: ='Requisito de Projeto'!C24&" · "&'Requisito de Projeto'!B24&" — "&'Requisito de Projeto'!D24&" "&'Requisito de Projeto'!E24 | Y24: +
B25: ='Requisito de Projeto'!C25&" · "&'Requisito de Projeto'!B25&" — "&'Requisito de Projeto'!D25&" "&'Requisito de Projeto'!E25
B28: ++ forte sinergia: melhorar um puxa o outro
B29: + sinergia
B30: − conflito: melhorar um piora o outro
B31: −− forte conflito: exige decisão de compromisso
B33: Todas as células do triângulo superior estão preenchidas; 0 significa ausência de interação relevante. Cada conflito traz comentário com a razão física: o eixo em que os dois requisitos de projeto se opõem (folga, área vazada, material, volume, massa, custo, número de peças ou rigidez).
B34: Interações revisadas nesta rodada
B35: Par | C35: Corr. | D35: Justificativa
B36: RP15 × RP6 | C36: − | D36: Reter fragmentos cria superfície interna recortada, mais difícil de limpar
B37: RP17 × RP9 | C37: − | D37: Desmontagem rápida pede fixação leve, que reduz o ângulo de tombamento
B38: RP20 × RP12 | C38: − | D38: Mais módulos e interfaces significam mais fontes de variação entre unidades
B39: RP20 × RP6 | C39: − | D39: Frestas entre módulos são caminho de fuga para fragmento
B40: RP20 × RP9 | C40: − | D40: Junta modular reduz rigidez do conjunto e piora a estabilidade
B41: RP21 × RP20 | C41: − | D41: Trocar um módulo quebra a identidade da unidade rastreada
B42: RP15 × RP17 | C42: ++ | D42: Recondicionar exige desmontar: os dois tempos são o mesmo laço de operação
B43: RP15 × RP20 | C43: ++ | D43: Módulo trocável é justamente o que torna o recondicionamento rápido
B44: RP15 × RP18 | C44: + | D44: Manutenção regular entre ciclos estende a vida útil do conjunto
B45: RP15 × RP23 | C45: + | D45: O tempo de recondicionamento entra direto no custo por ciclo
B46: RP15 × RP22 | C46: + | D46: Mesmo princípio de projeto: poucas ações e sem ferramenta dedicada
... B53: RP23 × RP8 | C53: + | D53: Melhor aproveitamento do palete dilui o frete no custo por ciclo
B55: A matriz mantém 72 pares em zero: são requisitos que de fato não interagem tecnicamente. Os pares acima estavam em zero e foram revisados porque o produto é retornável — recondicionamento, contagem de ciclos e troca de módulos criam acoplamentos que a primeira versão não capturava.

Sheet QFD
B2: Casa da Qualidade
B4: ID | C4: Requisito do cliente | D4: Pontuação Mudge | E4: Kano | F4: ='Requisito de Projeto'!C3 | G4: ='Requisito de Projeto'!C4 | H4: ='Requisito de Projeto'!C5 | I4: ='Requisito de Projeto'!C6 | J4: ='Requisito de Projeto'!C7 | K4: ='Requisito de Projeto'!C8 | L4: ='Requisito de Projeto'!C9 | M4: ='Requisito de Projeto'!C10 | N4: ='Requisito de Projeto'!C11 | O4: ='Requisito de Projeto'!C12 | P4: ='Requisito de Projeto'!C13 | Q4: ='Requisito de Projeto'!C14 | R4: ='Requisito de Projeto'!C15 | S4: ='Requisito de Projeto'!C16 | T4: ='Requisito de Projeto'!C17 | U4: ='Requisito de Projeto'!C18 | V4: ='Requisito de Projeto'!C19 | W4: ='Requisito de Projeto'!C20 | X4: ='Requisito de Projeto'!C21 | Y4: ='Requisito de Projeto'!C22 | Z4: ='Requisito de Projeto'!C23 | AA4: ='Requisito de Projeto'!C24 | AB4: ='Requisito de Projeto'!C25 | AC4: =Benchmarking!F9 | AD4: =Benchmarking!G9 | AE4: =Benchmarking!H9 | AF4: =Benchmarking!I9 | AG4: Melhor atual
C5: Requisito de projeto → unidade (direção) | F5: ='Requisito de Projeto'!B3&" — "&'Requisito de Projeto'!D3&" "&'Requisito de Projeto'!E3 | G5: ='Requisito de Projeto'!B4&" — "&'Requisito de Projeto'!D4&" "&'Requisito de Projeto'!E4 | H5: ='Requisito de Projeto'!B5&" — "&'Requisito de Projeto'!D5&" "&'Requisito de Projeto'!E5 | I5: ='Requisito de Projeto'!B6&" — "&'Requisito de Projeto'!D6&" "&'Requisito de Projeto'!E6 | J5: ='Requisito de Projeto'!B7&" — "&'Requisito de Projeto'!D7&" "&'Requisito de Projeto'!E7 | K5: ='Requisito de Projeto'!B8&" — "&'Requisito de Projeto'!D8&" "&'Requisito de Projeto'!E8 | L5: ='Requisito de Projeto'!B9&" — "&'Requisito de Projeto'!D9&" "&'Requisito de Projeto'!E9 | M5: ='Requisito de Projeto'!B10&" — "&'Requisito de Projeto'!D10&" "&'Requisito de Projeto'!E10 | N5: ='Requisito de Projeto'!B11&" — "&'Requisito de Projeto'!D11&" "&'Requisito de Projeto'!E11 | O5: ='Requisito de Projeto'!B12&" — "&'Requisito de Projeto'!D12&" "&'Requisito de Projeto'!E12 | P5: ='Requisito de Projeto'!B13&" — "&'Requisito de Projeto'!D13&" "&'Requisito de Projeto'!E13 | Q5: ='Requisito de Projeto'!B14&" — "&'Requisito de Projeto'!D14&" "&'Requisito de Projeto'!E14 | R5: ='Requisito de Projeto'!B15&" — "&'Requisito de Projeto'!D15&" "&'Requisito de Projeto'!E15 | S5: ='Requisito de Projeto'!B16&" — "&'Requisito de Projeto'!D16&" "&'Requisito de Projeto'!E16 | T5: ='Requisito de Projeto'!B17&" — "&'Requisito de Projeto'!D17&" "&'Requisito de Projeto'!E17 | U5: ='Requisito de Projeto'!B18&" — "&'Requisito de Projeto'!D18&" "&'Requisito de Projeto'!E18 | V5: ='Requisito de Projeto'!B19&" — "&'Requisito de Projeto'!D19&" "&'Requisito de Projeto'!E19 | W5: ='Requisito de Projeto'!B20&" — "&'Requisito de Projeto'!D20&" "&'Requisito de Projeto'!E20 | X5: ='Requisito de Projeto'!B21&" — "&'Requisito de Projeto'!D21&" "&'Requisito de Projeto'!E21 | Y5: ='Requisito de Projeto'!B22&" — "&'Requisito de Projeto'!D22&" "&'Requisito de Projeto'!E22 | Z5: ='Requisito de Projeto'!B23&" — "&'Requisito de Projeto'!D23&" "&'Requisito de Projeto'!E23 | AA5: ='Requisito de Projeto'!B24&" — "&'Requisito de Projeto'!D24&" "&'Requisito de Projeto'!E24 | AB5: ='Requisito de Projeto'!B25&" — "&'Requisito de Projeto'!D25&" "&'Requisito de Projeto'!E25 | AC5: =Benchmarking!C4 | AD5: =Benchmarking!C5 | AE5: =Benchmarking!C6 | AF5: =Benchmarking!C7
B6: ='Matriz de Relacionamento'!B7 | C6: ='Matriz de Relacionamento'!C7 | D6: ='Matriz de Relacionamento'!D7 | E6: ='Matriz de Relacionamento'!AH7 | F6: =IF('Matriz de Relacionamento'!F7="","",'Matriz de Relacionamento'!F7) | G6: =IF('Matriz de Relacionamento'!G7="","",'Matriz de Relacionamento'!G7) | H6: =IF('Matriz de Relacionamento'!H7="","",'Matriz de Relacionamento'!H7) | I6: =IF('Matriz de Relacionamento'!I7="","",'Matriz de Relacionamento'!I7) | J6: =IF('Matriz de Relacionamento'!J7="","",'Matriz de Relacionamento'!J7) | K6: =IF('Matriz de Relacionamento'!K7="","",'Matriz de Relacionamento'!K7) | L6: =IF('Matriz de Relacionamento'!L7="","",'Matriz de Relacionamento'!L7) | M6: =IF('Matriz de Relacionamento'!M7="","",'Matriz de Relacionamento'!M7) | ... AB6: =IF('Matriz de Relacionamento'!AB7="","",'Matriz de Relacionamento'!AB7) | AC6: =Benchmarking!F10 | AD6: =Benchmarking!G10 | AE6: =Benchmarking!H10 | AF6: =Benchmarking!I10 | AG6: =MAX(AC6:AF6)
B7: ='Matriz de Relacionamento'!B8 | C7: ='Matriz de Relacionamento'!C8 | D7: ='Matriz de Relacionamento'!D8 | E7: ='Matriz de Relacionamento'!AH8 | F7: =IF('Matriz de Relacionamento'!F8="","",'Matriz de Relacionamento'!F8) | G7: =IF('Matriz de Relacionamento'!G8="","",'Matriz de Relacionamento'!G8) | H7: =IF('Matriz de Relacionamento'!H8="","",'Matriz de Relacionamento'!H8) | I7: =IF('Matriz de Relacionamento'!I8="","",'Matriz de Relacionamento'!I8) | J7: =IF('Matriz de Relacionamento'!J8="","",'Matriz de Relacionamento'!J8) | K7: =IF('Matriz de Relacionamento'!K8="","",'Matriz de Relacionamento'!K8) | L7: =IF('Matriz de Relacionamento'!L8="","",'Matriz de Relacionamento'!L8) | M7: =IF('Matriz de Relacionamento'!M8="","",'Matriz de Relacionamento'!M8) | ... AB7: =IF('Matriz de Relacionamento'!AB8="","",'Matriz de Relacionamento'!AB8) | AC7: =Benchmarking!F11 | AD7: =Benchmarking!G11 | AE7: =Benchmarking!H11 | AF7: =Benchmarking!I11 | AG7: =MAX(AC7:AF7)
B8: ='Matriz de Relacionamento'!B9 | C8: ='Matriz de Relacionamento'!C9 | D8: ='Matriz de Relacionamento'!D9 | E8: ='Matriz de Relacionamento'!AH9 | F8: =IF('Matriz de Relacionamento'!F9="","",'Matriz de Relacionamento'!F9) | G8: =IF('Matriz de Relacionamento'!G9="","",'Matriz de Relacionamento'!G9) | H8: =IF('Matriz de Relacionamento'!H9="","",'Matriz de Relacionamento'!H9) | I8: =IF('Matriz de Relacionamento'!I9="","",'Matriz de Relacionamento'!I9) | J8: =IF('Matriz de Relacionamento'!J9="","",'Matriz de Relacionamento'!J9) | K8: =IF('Matriz de Relacionamento'!K9="","",'Matriz de Relacionamento'!K9) | L8: =IF('Matriz de Relacionamento'!L9="","",'Matriz de Relacionamento'!L9) | M8: =IF('Matriz de Relacionamento'!M9="","",'Matriz de Relacionamento'!M9) | ... AB8: =IF('Matriz de Relacionamento'!AB9="","",'Matriz de Relacionamento'!AB9) | AC8: =Benchmarking!F12 | AD8: =Benchmarking!G12 | AE8: =Benchmarking!H12 | AF8: =Benchmarking!I12 | AG8: =MAX(AC8:AF8)
B9: ='Matriz de Relacionamento'!B10 | C9: ='Matriz de Relacionamento'!C10 | D9: ='Matriz de Relacionamento'!D10 | E9: ='Matriz de Relacionamento'!AH10 | F9: =IF('Matriz de Relacionamento'!F10="","",'Matriz de Relacionamento'!F10) | G9: =IF('Matriz de Relacionamento'!G10="","",'Matriz de Relacionamento'!G10) | H9: =IF('Matriz de Relacionamento'!H10="","",'Matriz de Relacionamento'!H10) | I9: =IF('Matriz de Relacionamento'!I10="","",'Matriz de Relacionamento'!I10) | J9: =IF('Matriz de Relacionamento'!J10="","",'Matriz de Relacionamento'!J10) | K9: =IF('Matriz de Relacionamento'!K10="","",'Matriz de Relacionamento'!K10) | L9: =IF('Matriz de Relacionamento'!L10="","",'Matriz de Relacionamento'!L10) | M9: =IF('Matriz de Relacionamento'!M10="","",'Matriz de Relacionamento'!M10) | ... AB9: =IF('Matriz de Relacionamento'!AB10="","",'Matriz de Relacionamento'!AB10) | AC9: =Benchmarking!F13 | AD9: =Benchmarking!G13 | AE9: =Benchmarking!H13 | AF9: =Benchmarking!I13 | AG9: =MAX(AC9:AF9)
B10: ='Matriz de Relacionamento'!B11 | C10: ='Matriz de Relacionamento'!C11 | D10: ='Matriz de Relacionamento'!D11 | E10: ='Matriz de Relacionamento'!AH11 | F10: =IF('Matriz de Relacionamento'!F11="","",'Matriz de Relacionamento'!F11) | G10: =IF('Matriz de Relacionamento'!G11="","",'Matriz de Relacionamento'!G11) | H10: =IF('Matriz de Relacionamento'!H11="","",'Matriz de Relacionamento'!H11) | I10: =IF('Matriz de Relacionamento'!I11="","",'Matriz de Relacionamento'!I11) | J10: =IF('Matriz de Relacionamento'!J11="","",'Matriz de Relacionamento'!J11) | K10: =IF('Matriz de Relacionamento'!K11="","",'Matriz de Relacionamento'!K11) | L10: =IF('Matriz de Relacionamento'!L11="","",'Matriz de Relacionamento'!L11) | M10: =IF('Matriz de Relacionamento'!M11="","",'Matriz de Relacionamento'!M11) | ... AB10: =IF('Matriz de Relacionamento'!AB11="","",'Matriz de Relacionamento'!AB11) | AC10: =Benchmarking!F14 | AD10: =Benchmarking!G14 | AE10: =Benchmarking!H14 | AF10: =Benchmarking!I14 | AG10: =MAX(AC10:AF10)
B11: ='Matriz de Relacionamento'!B12 | C11: ='Matriz de Relacionamento'!C12 | D11: ='Matriz de Relacionamento'!D12 | E11: ='Matriz de Relacionamento'!AH12 | F11: =IF('Matriz de Relacionamento'!F12="","",'Matriz de Relacionamento'!F12) | G11: =IF('Matriz de Relacionamento'!G12="","",'Matriz de Relacionamento'!G12) | H11: =IF('Matriz de Relacionamento'!H12="","",'Matriz de Relacionamento'!H12) | I11: =IF('Matriz de Relacionamento'!I12="","",'Matriz de Relacionamento'!I12) | J11: =IF('Matriz de Relacionamento'!J12="","",'Matriz de Relacionamento'!J12) | K11: =IF('Matriz de Relacionamento'!K12="","",'Matriz de Relacionamento'!K12) | L11: =IF('Matriz de Relacionamento'!L12="","",'Matriz de Relacionamento'!L12) | M11: =IF('Matriz de Relacionamento'!M12="","",'Matriz de Relacionamento'!M12) | ... AB11: =IF('Matriz de Relacionamento'!AB12="","",'Matriz de Relacionamento'!AB12) | AC11: =Benchmarking!F15 | AD11: =Benchmarking!G15 | AE11: =Benchmarking!H15 | AF11: =Benchmarking!I15 | AG11: =MAX(AC11:AF11)
B12: ='Matriz de Relacionamento'!B13 | C12: ='Matriz de Relacionamento'!C13 | D12: ='Matriz de Relacionamento'!D13 | E12: ='Matriz de Relacionamento'!AH13 | F12: =IF('Matriz de Relacionamento'!F13="","",'Matriz de Relacionamento'!F13) | G12: =IF('Matriz de Relacionamento'!G13="","",'Matriz de Relacionamento'!G13) | H12: =IF('Matriz de Relacionamento'!H13="","",'Matriz de Relacionamento'!H13) | I12: =IF('Matriz de Relacionamento'!I13="","",'Matriz de Relacionamento'!I13) | J12: =IF('Matriz de Relacionamento'!J13="","",'Matriz de Relacionamento'!J13) | K12: =IF('Matriz de Relacionamento'!K13="","",'Matriz de Relacionamento'!K13) | L12: =IF('Matriz de Relacionamento'!L13="","",'Matriz de Relacionamento'!L13) | M12: =IF('Matriz de Relacionamento'!M13="","",'Matriz de Relacionamento'!M13) | ... AB12: =IF('Matriz de Relacionamento'!AB13="","",'Matriz de Relacionamento'!AB13) | AC12: =Benchmarking!F16 | AD12: =Benchmarking!G16 | AE12: =Benchmarking!H16 | AF12: =Benchmarking!I16 | AG12: =MAX(AC12:AF12)
B13: ='Matriz de Relacionamento'!B14 | C13: ='Matriz de Relacionamento'!C14 | D13: ='Matriz de Relacionamento'!D14 | E13: ='Matriz de Relacionamento'!AH14 | F13: =IF('Matriz de Relacionamento'!F14="","",'Matriz de Relacionamento'!F14) | G13: =IF('Matriz de Relacionamento'!G14="","",'Matriz de Relacionamento'!G14) | H13: =IF('Matriz de Relacionamento'!H14="","",'Matriz de Relacionamento'!H14) | I13: =IF('Matriz de Relacionamento'!I14="","",'Matriz de Relacionamento'!I14) | J13: =IF('Matriz de Relacionamento'!J14="","",'Matriz de Relacionamento'!J14) | K13: =IF('Matriz de Relacionamento'!K14="","",'Matriz de Relacionamento'!K14) | L13: =IF('Matriz de Relacionamento'!L14="","",'Matriz de Relacionamento'!L14) | M13: =IF('Matriz de Relacionamento'!M14="","",'Matriz de Relacionamento'!M14) | ... AB13: =IF('Matriz de Relacionamento'!AB14="","",'Matriz de Relacionamento'!AB14) | AC13: =Benchmarking!F17 | AD13: =Benchmarking!G17 | AE13: =Benchmarking!H17 | AF13: =Benchmarking!I17 | AG13: =MAX(AC13:AF13)
B14: ='Matriz de Relacionamento'!B15 | C14: ='Matriz de Relacionamento'!C15 | D14: ='Matriz de Relacionamento'!D15 | E14: ='Matriz de Relacionamento'!AH15 | F14: =IF('Matriz de Relacionamento'!F15="","",'Matriz de Relacionamento'!F15) | G14: =IF('Matriz de Relacionamento'!G15="","",'Matriz de Relacionamento'!G15) | H14: =IF('Matriz de Relacionamento'!H15="","",'Matriz de Relacionamento'!H15) | I14: =IF('Matriz de Relacionamento'!I15="","",'Matriz de Relacionamento'!I15) | J14: =IF('Matriz de Relacionamento'!J15="","",'Matriz de Relacionamento'!J15) | K14: =IF('Matriz de Relacionamento'!K15="","",'Matriz de Relacionamento'!K15) | L14: =IF('Matriz de Relacionamento'!L15="","",'Matriz de Relacionamento'!L15) | M14: =IF('Matriz de Relacionamento'!M15="","",'Matriz de Relacionamento'!M15) | ... AB14: =IF('Matriz de Relacionamento'!AB15="","",'Matriz de Relacionamento'!AB15) | AC14: =Benchmarking!F18 | AD14: =Benchmarking!G18 | AE14: =Benchmarking!H18 | AF14: =Benchmarking!I18 | AG14: =MAX(AC14:AF14)
B15: ='Matriz de Relacionamento'!B16 | C15: ='Matriz de Relacionamento'!C16 | D15: ='Matriz de Relacionamento'!D16 | E15: ='Matriz de Relacionamento'!AH16 | F15: =IF('Matriz de Relacionamento'!F16="","",'Matriz de Relacionamento'!F16) | G15: =IF('Matriz de Relacionamento'!G16="","",'Matriz de Relacionamento'!G16) | H15: =IF('Matriz de Relacionamento'!H16="","",'Matriz de Relacionamento'!H16) | I15: =IF('Matriz de Relacionamento'!I16="","",'Matriz de Relacionamento'!I16) | J15: =IF('Matriz de Relacionamento'!J16="","",'Matriz de Relacionamento'!J16) | K15: =IF('Matriz de Relacionamento'!K16="","",'Matriz de Relacionamento'!K16) | L15: =IF('Matriz de Relacionamento'!L16="","",'Matriz de Relacionamento'!L16) | M15: =IF('Matriz de Relacionamento'!M16="","",'Matriz de Relacionamento'!M16) | ... AB15: =IF('Matriz de Relacionamento'!AB16="","",'Matriz de Relacionamento'!AB16) | AC15: =Benchmarking!F19 | AD15: =Benchmarking!G19 | AE15: =Benchmarking!H19 | AF15: =Benchmarking!I19 | AG15: =MAX(AC15:AF15)
B16: ='Matriz de Relacionamento'!B17 | C16: ='Matriz de Relacionamento'!C17 | D16: ='Matriz de Relacionamento'!D17 | E16: ='Matriz de Relacionamento'!AH17 | F16: =IF('Matriz de Relacionamento'!F17="","",'Matriz de Relacionamento'!F17) | G16: =IF('Matriz de Relacionamento'!G17="","",'Matriz de Relacionamento'!G17) | H16: =IF('Matriz de Relacionamento'!H17="","",'Matriz de Relacionamento'!H17) | I16: =IF('Matriz de Relacionamento'!I17="","",'Matriz de Relacionamento'!I17) | J16: =IF('Matriz de Relacionamento'!J17="","",'Matriz de Relacionamento'!J17) | K16: =IF('Matriz de Relacionamento'!K17="","",'Matriz de Relacionamento'!K17) | L16: =IF('Matriz de Relacionamento'!L17="","",'Matriz de Relacionamento'!L17) | M16: =IF('Matriz de Relacionamento'!M17="","",'Matriz de Relacionamento'!M17) | ... AB16: =IF('Matriz de Relacionamento'!AB17="","",'Matriz de Relacionamento'!AB17) | AC16: =Benchmarking!F20 | AD16: =Benchmarking!G20 | AE16: =Benchmarking!H20 | AF16: =Benchmarking!I20 | AG16: =MAX(AC16:AF16)
B17: ='Matriz de Relacionamento'!B18 | C17: ='Matriz de Relacionamento'!C18 | D17: ='Matriz de Relacionamento'!D18 | E17: ='Matriz de Relacionamento'!AH18 | F17: =IF('Matriz de Relacionamento'!F18="","",'Matriz de Relacionamento'!F18) | G17: =IF('Matriz de Relacionamento'!G18="","",'Matriz de Relacionamento'!G18) | H17: =IF('Matriz de Relacionamento'!H18="","",'Matriz de Relacionamento'!H18) | I17: =IF('Matriz de Relacionamento'!I18="","",'Matriz de Relacionamento'!I18) | J17: =IF('Matriz de Relacionamento'!J18="","",'Matriz de Relacionamento'!J18) | K17: =IF('Matriz de Relacionamento'!K18="","",'Matriz de Relacionamento'!K18) | L17: =IF('Matriz de Relacionamento'!L18="","",'Matriz de Relacionamento'!L18) | M17: =IF('Matriz de Relacionamento'!M18="","",'Matriz de Relacionamento'!M18) | ... AB17: =IF('Matriz de Relacionamento'!AB18="","",'Matriz de Relacionamento'!AB18) | AC17: =Benchmarking!F21 | AD17: =Benchmarking!G21 | AE17: =Benchmarking!H21 | AF17: =Benchmarking!I21 | AG17: =MAX(AC17:AF17)
... B28: ='Matriz de Relacionamento'!B29 | C28: ='Matriz de Relacionamento'!C29 | D28: ='Matriz de Relacionamento'!D29 | E28: ='Matriz de Relacionamento'!AH29 | F28: =IF('Matriz de Relacionamento'!F29="","",'Matriz de Relacionamento'!F29) | G28: =IF('Matriz de Relacionamento'!G29="","",'Matriz de Relacionamento'!G29) | H28: =IF('Matriz de Relacionamento'!H29="","",'Matriz de Relacionamento'!H29) | I28: =IF('Matriz de Relacionamento'!I29="","",'Matriz de Relacionamento'!I29) | J28: =IF('Matriz de Relacionamento'!J29="","",'Matriz de Relacionamento'!J29) | K28: =IF('Matriz de Relacionamento'!K29="","",'Matriz de Relacionamento'!K29) | L28: =IF('Matriz de Relacionamento'!L29="","",'Matriz de Relacionamento'!L29) | M28: =IF('Matriz de Relacionamento'!M29="","",'Matriz de Relacionamento'!M29) | ... AB28: =IF('Matriz de Relacionamento'!AB29="","",'Matriz de Relacionamento'!AB29) | AC28: =Benchmarking!F32 | AD28: =Benchmarking!G32 | AE28: =Benchmarking!H32 | AF28: =Benchmarking!I32 | AG28: =MAX(AC28:AF28)
C29: Valor de importância (Σ Mudge × relação) | F29: ='Matriz de Relacionamento'!F30 | G29: ='Matriz de Relacionamento'!G30 | H29: ='Matriz de Relacionamento'!H30 | I29: ='Matriz de Relacionamento'!I30 | J29: ='Matriz de Relacionamento'!J30 | K29: ='Matriz de Relacionamento'!K30 | L29: ='Matriz de Relacionamento'!L30 | M29: ='Matriz de Relacionamento'!M30 | ... AB29: ='Matriz de Relacionamento'!AB30
C30: Importância relativa | F30: ='Matriz de Relacionamento'!F31 | G30: ='Matriz de Relacionamento'!G31 | H30: ='Matriz de Relacionamento'!H31 | I30: ='Matriz de Relacionamento'!I31 | J30: ='Matriz de Relacionamento'!J31 | K30: ='Matriz de Relacionamento'!K31 | L30: ='Matriz de Relacionamento'!L31 | M30: ='Matriz de Relacionamento'!M31 | ... AB30: ='Matriz de Relacionamento'!AB31
C31: Classificação | F31: ='Matriz de Relacionamento'!F32 | G31: ='Matriz de Relacionamento'!G32 | H31: ='Matriz de Relacionamento'!H32 | I31: ='Matriz de Relacionamento'!I32 | J31: ='Matriz de Relacionamento'!J32 | K31: ='Matriz de Relacionamento'!K32 | L31: ='Matriz de Relacionamento'!L32 | M31: ='Matriz de Relacionamento'!M32 | ... AB31: ='Matriz de Relacionamento'!AB32
B34: Cada requisito de projeto é o requisito do cliente da mesma linha, medido pelo parâmetro técnico da aba Requisito de Projeto — daí o 9 na diagonal. O 0 indica ausência de relação. Todas as células vêm por fórmula das abas de origem; o telhado está na aba Matriz de Correlação, com a razão de cada conflito em comentário.

Sheet Especificação Meta
B2: Especificações-meta
B3: As 23 metas são valores de trabalho a confirmar ou revisar. A origem da linha de base não confirma a meta. Medir a operação atual, justificar o limite e verificar a concepção são etapas distintas.
B5: ID | C5: Requisito de projeto | D5: Unidade | E5: Meta | F5: Medição | G5: Justificativa | H5: Direção | I5: Linha de base (valor de partida) | J5: Origem da linha de base | K5: Como o valor foi obtido
B6: ='Requisito de Projeto'!C3 | C6: ='Requisito de Projeto'!B3 | D6: ='Requisito de Projeto'!D3 | E6: ≤ 35 g de pico transmitido à louça, e sempre abaixo do resultado da embalagem atual no mesmo ensaio | F6: Queda instrumentada das duas soluções na mesma altura e nas mesmas faces, com acelerômetro na peça | G6: Meta exploratória. A fragilidade da louça específica não foi medida; confirmar em ensaio tipo ASTM D3332 e comparar as embalagens na mesma condição. O valor não é limiar automático de um indicador externo. | H6: ='Requisito de Projeto'!E3 | I6: 60 a 90 g estimados na embalagem atual; fragilidade da louça entre 40 e 60 g | J6: Fonte + estimativa | K6: Faixa genérica de fragilidade, a confirmar para os modelos estudados. O relato de trinca não mede aceleração nem comprova causa; definir fragilidade e comparar conjuntos em ensaio.
B7: ='Requisito de Projeto'!C4 | C7: ='Requisito de Projeto'!B4 | D7: ='Requisito de Projeto'!D4 | E7: ≤ 6 mm de deslocamento residual após o ciclo de distribuição | F7: Marcação da posição inicial e medição do deslocamento após vibração e queda | G7: Prioridade elevada no Mudge. A relação entre deslocamento, atrito e dano precisa ser verificada no ciclo instrumentado. | H7: ='Requisito de Projeto'!E4 | I7: ≈ 25 mm | J7: Estimativa | K7: Dimensões indicativas de caixa 650 × 400 × 410 mm e peça 610 × 360 × 370 mm sugerem 20 mm de folga por face. Não medem o deslocamento residual: a partida de 25 mm continua estimada.
B8: ='Requisito de Projeto'!C5 | C8: ='Requisito de Projeto'!B5 | D8: ='Requisito de Projeto'!D5 | E8: ≤ 150 N de força de partida com o conjunto carregado, em piso de canteiro | F8: Dinamômetro na altura de pega, a 0,1 m/s, conforme o método da ISO 11228-2 | G8: 150 N é referência de trabalho para força de partida ao empurrar/puxar. Não aprova levantamento nem demonstra adequação a todos os operadores, pisos e percursos; confirmar no contexto real. | H8: ='Requisito de Projeto'!E5 | I8: 334 N (34 kgf) no levantamento manual integral; 17 a 33 N de resistência ao rolamento com carrinho | J8: Fonte + cálculo + estimativa | K8: 34 kg × 9,81 ≈ 334 N descrevem peso no levantamento. Os 17–33 N de rolamento supõem 5–10% do peso; medir partida em piso real. As grandezas não são intercambiáveis.
B9: ='Requisito de Projeto'!C6 | C9: ='Requisito de Projeto'!B6 | D9: ='Requisito de Projeto'!D6 | E9: ≥ 60% da área crítica verificável com o conjunto fechado | F9: Razão entre a área inspecionável e a área sujeita a trinca, delimitada em desenho | G9: Nenhuma referência do benchmarking permite conferir sem abrir. É o requisito que ataca a avaria oculta relatada em campo. | H9: ='Requisito de Projeto'!E6 | I9: 0% (embalagem opaca e fechada) | J9: Fonte | K9: Observação de campo e benchmarking: nota 1 para a embalagem atual neste requisito
B10: ='Requisito de Projeto'!C7 | C10: ='Requisito de Projeto'!B7 | D10: ='Requisito de Projeto'!D7 | E10: ≥ 2 pontos de pega com vão livre compatível com mão enluvada | F10: Contagem e verificação dimensional do vão livre contra a referência antropométrica | G10: A embalagem atual não define onde pegar, o que empurra o trabalhador para a pega improvisada registrada em E-04. | H10: ='Requisito de Projeto'!E7 | I10: 0 (nenhuma pega definida) | J10: Fonte | K10: Observação de campo: a caixa atual não define ponto de pega
B11: ='Requisito de Projeto'!C8 | C11: ='Requisito de Projeto'!B8 | D11: ='Requisito de Projeto'!D8 | E11: ≥ 90% da massa de fragmentos retida no interior | F11: Quebra controlada de peça refugada dentro do conjunto e pesagem dos fragmentos | G11: Conter fragmentos e permitir retirada segura. Retenção de 90% da massa não comprova ausência de risco por fragmentos pequenos; avaliar transporte, abertura e retirada. | H11: ='Requisito de Projeto'!E8 | I11: ≈ 0% (cacos soltos no interior) | J11: Estimativa | K11: Observação de campo, a confirmar por ensaio de quebra controlada
B12: ='Requisito de Projeto'!C9 | C12: ='Requisito de Projeto'!B9 | D12: ='Requisito de Projeto'!D9 | E12: ≥ 300 mm no eixo A e ≥ 150 mm no eixo B, sem troca de componentes no ajuste | F12: Verificar extremos da faixa de Dados, cursos, contatos e imobilização por SKU, com reserva dimensional | G12: Revisão preliminar para cubas e bacias: A de 340 a 640 mm exige 300 mm; B de 290 a 430 mm exige 140 mm, com curso adotado de 150 mm. Confirmar no estoque e no protótipo. | H12: ='Requisito de Projeto'!E9 | I12: 0 mm (uma embalagem por modelo) | J12: Estimativa | K12: Linha de base histórica: uma caixa por modelo. A antiga faixa genérica de bacias 600–750 mm não define o mix atual. Referências e premissas da revisão em Dados, linhas 27–110.
B13: ='Requisito de Projeto'!C10 | C13: ='Requisito de Projeto'!B10 | D13: ='Requisito de Projeto'!D10 | E13: ≥ 80% de ocupação da área do PBR 1200 × 1000 mm; alvo de otimização ≥ 90% | F13: Verificar arranjo sem sobreposição ou balanço; calcular área ocupada e conferir portas, massa e restrição de movimento no veículo real | G13: Mínimo preliminar para reservar proteção no mix. Três bases ocupam 81,6%; alvo 90%. Continuam 3 peças/camada, como na base histórica: área ocupada maior não prova ganho de frete. Validar custo e densidade por família. | H13: ='Requisito de Projeto'!E10 | I13: 65% da área do palete, 3 peças por camada | J13: Cálculo | K13: Base histórica indicativa: 3 caixas de 650 × 400 mm =65%. O exemplo 600 × 500 mm é cálculo de área, não cobertura de bacias de até 630 mm. Ver Dados para arranjo e veículo de referência.
B14: ='Requisito de Projeto'!C11 | C14: ='Requisito de Projeto'!B11 | D14: ='Requisito de Projeto'!D11 | E14: ≥ 40° de ângulo de tombamento com o conjunto carregado | F14: Plano inclinado até a perda de estabilidade, na configuração mais desfavorável | G14: Tombamento no canteiro quebra a peça e atinge quem está ao lado. O canteiro tem piso irregular e rampas. | H14: ='Requisito de Projeto'!E11 | I14: ≈ 47° calculados para a caixa atual | J14: Cálculo | K14: Geometria da caixa de 650 × 400 × 410 mm com centro de massa a 45% da altura
B15: ='Requisito de Projeto'!C12 | C15: ='Requisito de Projeto'!B12 | D15: ='Requisito de Projeto'!D12 | E15: ≤ 7 etapas até o primeiro uso correto, sem consultar instrução | F15: Ensaio com operador que nunca usou o produto, contando ações e erros | G15: A adoção depende de o operador acertar na primeira tentativa: o distribuidor não para a operação para treinar. | H15: ='Requisito de Projeto'!E12 | I15: ≈ 6 etapas | J15: Estimativa | K15: Posicionar, cortar fita, abrir abas, remover berço, extrair a peça e descartar a embalagem
B16: ='Requisito de Projeto'!C13 | C16: ='Requisito de Projeto'!B13 | D16: ='Requisito de Projeto'!D13 | E16: ≥ 7,5 kN de carga de compressão sem perda de proteção | F16: Compressão vertical e permanência carregada; estudar dois níveis por 24 h, carga fora da cerâmica, estados seco/úmido e deformação | G16: 7,5 kN continua provisório. Dois conjuntos de até 48 kg dão reação estática de 0,942 kN/coluna e peso superior de 0,471 kN. Isso não justifica margem, duração de ensaio ou dinâmica; não reduzir a meta só pelo peso estático. | H16: ='Requisito de Projeto'!E13 | I16: ≈ 5 kN estimados para caixa de onda dupla desse porte | J16: Estimativa | K16: Ordem de grandeza de caixa de papelão ondulado de parede dupla; a medir por ensaio tipo ISO 12048
B17: ='Requisito de Projeto'!C14 | C17: ='Requisito de Projeto'!B14 | D17: ='Requisito de Projeto'!D14 | E17: ≤ 10% de coeficiente de variação do pico de aceleração | F17: Repetir ensaio entre unidades com mesma peça, massa, regulagem e condições; repetir o protocolo nos extremos de cada família | G17: O papelão atual varia com umidade, reuso e montagem. Proteção que oscila entre unidades não sustenta promessa comercial. | H17: ='Requisito de Projeto'!E14 | I17: ≈ 20% estimados | J17: Estimativa | K17: Dispersão típica de ensaio de embalagem de papelão, agravada por umidade e reuso; a medir
... B28: ='Requisito de Projeto'!C25 | C28: ='Requisito de Projeto'!B25 | D28: ='Requisito de Projeto'!D25 | E28: ≤ R$ 15 por ciclo de uso, com teto econômico no custo médio da avaria evitada | F28: Aquisição rateada pela vida real mais custos de manutenção, retorno e consumíveis por ciclo. Na comparação da operação, somar a embalagem original mantida e avarias residuais. | G28: Teto provisório do dispositivo, sujeito à confirmação com o distribuidor. A operação nova só é viável se seu custo completo for inferior ao cenário atual comparável. | H28: ='Requisito de Projeto'!E25 | I28: R$ 27,40 por peça: R$ 15,00 de embalagem + R$ 10,00 de perda + R$ 2,40 de rateio de reentrega | J28: Cálculo sobre hipóteses | K28: Cenário provisório: R$ 15 de caixa, avaria de 2%, louça a R$ 500 e reentrega a R$ 120. Sem taxa medida ou cotação das concepções. Confirmar registros, custos, vida real e operação comparável.
B30: Observação sobre requisito de peso zero no Mudge
B31: S | C31: Ter materiais recicláveis | D31: S recebeu zero nos julgamentos de Mudge desta rodada. Kano não determina esse resultado. RP19 permanece como meta de fim de vida; a condição deverá ser verificada mesmo sem contribuição direta do RC na quantificação.
B33: Plano de coleta e validação — medir a base, justificar a meta e verificar a concepção | C33: Plano de coleta e validação — medir a base, justificar a meta e verificar a concepção | D33: Plano de coleta e validação — medir a base, justificar a meta e verificar a concepção | E33: Plano de coleta e validação — medir a base, justificar a meta e verificar a concepção | F33: Plano de coleta e validação — medir a base, justificar a meta e verificar a concepção | G33: Plano de coleta e validação — medir a base, justificar a meta e verificar a concepção | H33: Plano de coleta e validação — medir a base, justificar a meta e verificar a concepção | I33: Plano de coleta e validação — medir a base, justificar a meta e verificar a concepção | J33: Plano de coleta e validação — medir a base, justificar a meta e verificar a concepção | K33: Plano de coleta e validação — medir a base, justificar a meta e verificar a concepção
B34: # | C34: Dado a levantar | D34: Protocolo proposto | E34: Onde / com quem | F34: RP relacionados | G34: Prioridade | H34: Frente proposta | I34: Marco de revisão | J34: Situação | K34: Condição para fechar
B35: 1 | C35: Ampliar campo e confrontar Kano/Mudge | D35: Mais 2 distribuidores e 2 obras; ouvir expedição, transporte e recebimento | E35: Operações com acessos distintos | F35: RC A–W; todos os RP | G35: Alta | H35: Campo | I35: Antes de fechar escopo | J35: Não iniciado | K35: Mínimo intencional proposto; registrar casos contrários e revisar julgamentos. Não é amostra estatística.
B36: 2 | C36: Avarias e custo da operação atual | D36: Registros contínuos; se ausentes, propor 4 semanas e ampliar se insuficiente | E36: Distribuidor e recebimento | F36: RP23, RP18 | G36: Alta | H36: Campo | I36: Antes da seleção | J36: Não iniciado | K36: Informar período, peças avariadas/entregues, mix e custos sem dupla contagem; não inferir causa pela detecção.
B37: 3 | C37: Massa, dimensões e mix | D37: Referências em Dados; confirmar dimensões, massa, apoios e mix vendido com balança/trena no distribuidor | E37: Estoque e expedição | F37: RP3, RP5, RP7, RP8, RP9, RP14 | G37: Alta | H37: Campo | I37: Antes de dimensionar | J37: Referências de catálogo reunidas; campo pendente | K37: Confirmar ou rever faixas de Dados por SKU e participação nas vendas; não presumir cobertura do mercado.
B38: 4 | C38: Fragilidade e solicitações | D38: Definir ensaio da peça; medir altura, faces, vibração e empilhamento | E38: Campo e laboratório a confirmar | F38: RP1 | G38: Alta | H38: Ensaios | I38: Antes de ensaiar proteção | J38: Não iniciado | K38: Confirmar fragilidade específica e justificar 35 g; não usar limiar do sensor como aceleração da louça.
B39: 5 | C39: Aceleração e deslocamento | D39: Comparar R1/propostas com mesma peça, sequência e condições; registrar repetições | E39: Laboratório a confirmar | F39: RP1, RP2 | G39: Alta | H39: Ensaios | I39: Antes da seleção | J39: Não iniciado | K39: Confrontar metas de 35 g e 6 mm com contatos e danos; justificar confirmação ou revisão dos limites.
B40: 6 | C40: Uniformidade entre unidades | D40: Repetir com a mesma peça/configuração entre unidades; separar as séries por modelo e condição | E40: Laboratório a confirmar | F40: RP12 | G40: Alta | H40: Ensaios | I40: Antes da seleção | J40: Não iniciado | K40: Definir amostra no protocolo e confrontar CV ≤10%; um ensaio isolado não demonstra uniformidade.
B41: 7 | C41: Movimentação e pega | D41: Medir partida no piso real; observar pega enluvada e levantamento em avaliação própria | E41: Obras e operadores | F41: RP3, RP5 | G41: Alta | H41: Campo | I41: Antes da seleção | J41: Não iniciado | K41: Confrontar 150 N e pega no meio escolhido; definir limites de uso e desníveis cobertos.
B42: 8 | C42: Inspeção da área crítica | D42: Delimitar área, verificar acesso fechado e testar leitura de defeitos conhecidos | E42: Recebimento e protótipo | F42: RP4 | G42: Alta | H42: Ensaios | I42: Antes da seleção | J42: Não iniciado | K42: Registrar área e defeitos detectáveis; ≥60% de acesso não prova detecção de toda trinca. Indicador não substitui inspeção.
B43: 9 | C43: Retenção e retirada segura | D43: Quebra controlada em peça refugada; pesar fragmentos e avaliar abertura/retirada | E43: Laboratório a confirmar | F43: RP6 | G43: Alta | H43: Ensaios | I43: Antes da seleção | J43: Não iniciado | K43: Confrontar ≥90% da massa; registrar escape de pequenos fragmentos e risco durante retirada.
B44: 10 | C44: Aproveitamento e volume | D44: Medir envoltório carregado/vazio e arranjo no palete e veículo | E44: Expedição e retorno | F44: RP8, RP14 | G44: Alta | H44: Campo | I44: Antes da seleção | J44: Não iniciado | K44: Confrontar mínimo 80%/alvo 90% do PBR e volumes ≤ 0,090 m³/cuba e ≤ 0,160 m³/bacia; medir envoltório completo e frete no mesmo SKU.
B45: 11 | C45: Estabilidade carregada | D45: Medir tombamento na configuração desfavorável, apoios e piso de uso | E45: Protótipo e canteiro | F45: RP9 | G45: Alta | H45: Ensaios | I45: Antes da seleção | J45: Não iniciado | K45: Confrontar ≥40° e justificar condição de uso; cálculo geométrico não substitui ensaio do conjunto.
B46: 12 | C46: Primeiro uso, montagem e desmontagem | D46: Contar ações e erros; cronometrar repetições com operadores novos | E46: Distribuidor e obra | F46: RP10, RP17, RP22 | G46: Média | H46: Campo | I46: Antes da seleção | J46: Não iniciado | K46: Confrontar 7 ações, 120 s e 6 ações; definir ação, início/fim e condição de sucesso antes de medir.
... B54: 20 | C54: Custo completo e viabilidade | D54: Cotar aquisição; medir retorno/manutenção/consumo, vida e avaria residual | E54: Distribuidor e fornecedores | F54: RP23, RP18 | G54: Alta | H54: Campo | I54: Antes da seleção | J54: Não iniciado | K54: Confrontar teto de R$15/ciclo do dispositivo e operação completa abaixo da atual comparável; dados ausentes não são zero.
B57: Concluir uma validação exige protocolo, dados individuais, resultado, limitação e justificativa de confirmar/rever a meta. MF-B foi escolhida como modelagem funcional para desenvolvimento; a aprovação técnica e a seleção final da concepção dependem das validações críticas.
B59: As frentes são propostas; nomes, acesso a campo/laboratório e datas ainda serão confirmados. Marcos são dependências do projeto, não compromissos de calendário. Todas as atividades estão não iniciadas neste controle. | C59: As frentes são propostas; nomes, acesso a campo/laboratório e datas ainda serão confirmados. Marcos são dependências do projeto, não compromissos de calendário. Todas as atividades estão não iniciadas neste controle. | D59: As frentes são propostas; nomes, acesso a campo/laboratório e datas ainda serão confirmados. Marcos são dependências do projeto, não compromissos de calendário. Todas as atividades estão não iniciadas neste controle. | E59: As frentes são propostas; nomes, acesso a campo/laboratório e datas ainda serão confirmados. Marcos são dependências do projeto, não compromissos de calendário. Todas as atividades estão não iniciadas neste controle. | F59: As frentes são propostas; nomes, acesso a campo/laboratório e datas ainda serão confirmados. Marcos são dependências do projeto, não compromissos de calendário. Todas as atividades estão não iniciadas neste controle. | G59: As frentes são propostas; nomes, acesso a campo/laboratório e datas ainda serão confirmados. Marcos são dependências do projeto, não compromissos de calendário. Todas as atividades estão não iniciadas neste controle. | H59: As frentes são propostas; nomes, acesso a campo/laboratório e datas ainda serão confirmados. Marcos são dependências do projeto, não compromissos de calendário. Todas as atividades estão não iniciadas neste controle. | I59: As frentes são propostas; nomes, acesso a campo/laboratório e datas ainda serão confirmados. Marcos são dependências do projeto, não compromissos de calendário. Todas as atividades estão não iniciadas neste controle. | J59: As frentes são propostas; nomes, acesso a campo/laboratório e datas ainda serão confirmados. Marcos são dependências do projeto, não compromissos de calendário. Todas as atividades estão não iniciadas neste controle. | K59: As frentes são propostas; nomes, acesso a campo/laboratório e datas ainda serão confirmados. Marcos são dependências do projeto, não compromissos de calendário. Todas as atividades estão não iniciadas neste controle.
B61: A origem da linha de base não confirma a meta. Os 23 valores são de trabalho; registrar confirmação ou revisão por RP antes da aprovação técnica da concepção. A primeira Pugh escolhe a estrutura funcional para desenvolver sob essas condições.
B63: OP-01: indicador de impacto adiado no informacional; opção experimental da M3. Depende de benefício, calibração, posição e custo. RP4 continua exigindo inspeção da louça. As correções do Feedback 2 não alteraram a seleção pendente. | C63: OP-01: indicador de impacto adiado no informacional; opção experimental da M3. Depende de benefício, calibração, posição e custo. RP4 continua exigindo inspeção da louça. As correções do Feedback 2 não alteraram a seleção pendente. | D63: OP-01: indicador de impacto adiado no informacional; opção experimental da M3. Depende de benefício, calibração, posição e custo. RP4 continua exigindo inspeção da louça. As correções do Feedback 2 não alteraram a seleção pendente. | E63: OP-01: indicador de impacto adiado no informacional; opção experimental da M3. Depende de benefício, calibração, posição e custo. RP4 continua exigindo inspeção da louça. As correções do Feedback 2 não alteraram a seleção pendente. | F63: OP-01: indicador de impacto adiado no informacional; opção experimental da M3. Depende de benefício, calibração, posição e custo. RP4 continua exigindo inspeção da louça. As correções do Feedback 2 não alteraram a seleção pendente. | G63: OP-01: indicador de impacto adiado no informacional; opção experimental da M3. Depende de benefício, calibração, posição e custo. RP4 continua exigindo inspeção da louça. As correções do Feedback 2 não alteraram a seleção pendente. | H63: OP-01: indicador de impacto adiado no informacional; opção experimental da M3. Depende de benefício, calibração, posição e custo. RP4 continua exigindo inspeção da louça. As correções do Feedback 2 não alteraram a seleção pendente. | I63: OP-01: indicador de impacto adiado no informacional; opção experimental da M3. Depende de benefício, calibração, posição e custo. RP4 continua exigindo inspeção da louça. As correções do Feedback 2 não alteraram a seleção pendente. | J63: OP-01: indicador de impacto adiado no informacional; opção experimental da M3. Depende de benefício, calibração, posição e custo. RP4 continua exigindo inspeção da louça. As correções do Feedback 2 não alteraram a seleção pendente. | K63: OP-01: indicador de impacto adiado no informacional; opção experimental da M3. Depende de benefício, calibração, posição e custo. RP4 continua exigindo inspeção da louça. As correções do Feedback 2 não alteraram a seleção pendente.
B65: Feedback 2 da Profa. Andréa Santos: amostra pequena e metas estimadas exigem validação. A revisão detalhou o plano, especialmente compressão (7,5 kN), deslocamento (6 mm) e recondicionamento (5 min), sem preencher resultados de campo ou ensaio. | C65: Feedback 2 da Profa. Andréa Santos: amostra pequena e metas estimadas exigem validação. A revisão detalhou o plano, especialmente compressão (7,5 kN), deslocamento (6 mm) e recondicionamento (5 min), sem preencher resultados de campo ou ensaio. | D65: Feedback 2 da Profa. Andréa Santos: amostra pequena e metas estimadas exigem validação. A revisão detalhou o plano, especialmente compressão (7,5 kN), deslocamento (6 mm) e recondicionamento (5 min), sem preencher resultados de campo ou ensaio. | E65: Feedback 2 da Profa. Andréa Santos: amostra pequena e metas estimadas exigem validação. A revisão detalhou o plano, especialmente compressão (7,5 kN), deslocamento (6 mm) e recondicionamento (5 min), sem preencher resultados de campo ou ensaio. | F65: Feedback 2 da Profa. Andréa Santos: amostra pequena e metas estimadas exigem validação. A revisão detalhou o plano, especialmente compressão (7,5 kN), deslocamento (6 mm) e recondicionamento (5 min), sem preencher resultados de campo ou ensaio. | G65: Feedback 2 da Profa. Andréa Santos: amostra pequena e metas estimadas exigem validação. A revisão detalhou o plano, especialmente compressão (7,5 kN), deslocamento (6 mm) e recondicionamento (5 min), sem preencher resultados de campo ou ensaio. | H65: Feedback 2 da Profa. Andréa Santos: amostra pequena e metas estimadas exigem validação. A revisão detalhou o plano, especialmente compressão (7,5 kN), deslocamento (6 mm) e recondicionamento (5 min), sem preencher resultados de campo ou ensaio. | I65: Feedback 2 da Profa. Andréa Santos: amostra pequena e metas estimadas exigem validação. A revisão detalhou o plano, especialmente compressão (7,5 kN), deslocamento (6 mm) e recondicionamento (5 min), sem preencher resultados de campo ou ensaio. | J65: Feedback 2 da Profa. Andréa Santos: amostra pequena e metas estimadas exigem validação. A revisão detalhou o plano, especialmente compressão (7,5 kN), deslocamento (6 mm) e recondicionamento (5 min), sem preencher resultados de campo ou ensaio. | K65: Feedback 2 da Profa. Andréa Santos: amostra pequena e metas estimadas exigem validação. A revisão detalhou o plano, especialmente compressão (7,5 kN), deslocamento (6 mm) e recondicionamento (5 min), sem preencher resultados de campo ou ensaio.

Sheet Função Global
B2: Requisitos e funções — 23 vínculos rastreáveis e catálogo de 17 funções | C2: Requisitos e funções — 23 vínculos rastreáveis e catálogo de 17 funções | D2: Requisitos e funções — 23 vínculos rastreáveis e catálogo de 17 funções | E2: Requisitos e funções — 23 vínculos rastreáveis e catálogo de 17 funções | F2: Requisitos e funções — 23 vínculos rastreáveis e catálogo de 17 funções | G2: Requisitos e funções — 23 vínculos rastreáveis e catálogo de 17 funções | H2: Requisitos e funções — 23 vínculos rastreáveis e catálogo de 17 funções | I2: Requisitos e funções — 23 vínculos rastreáveis e catálogo de 17 funções | J2: Requisitos e funções — 23 vínculos rastreáveis e catálogo de 17 funções | K2: Requisitos e funções — 23 vínculos rastreáveis e catálogo de 17 funções
B3: ID requisito | C3: Requisito de projeto | E3: ID vínculo | F3: Entendimento e justificativa | G3: Funções associadas | H3: Natureza do requisito | I3: IDs funcionais | J3: Tratamento | K3: Especificação-meta preservada
B4: — | C4: Função global do sistema | E4: FG | F4: Material: louça descoberta após preparo no distribuidor. Energia: transporte e manuseio. Sinal: comandos do operador; condição visível, orientação e identidade. Saídas pretendidas, sem desempenho ensaiado. | G4: Resguardar louça | H4: Finalidade global | I4: FG | J4: Desdobrar em funções | K4: Confrontar todas as especificações; o catálogo abaixo distingue função, atributo e restrição.
B5: ='Requisito de Projeto'!C3 -> RP1 | C5: ='Requisito de Projeto'!B3 -> Amortecer impactos do transporte | E5: V01 | F5: Atenuar energia na cerâmica; o pico é critério de desempenho. | G5: ='Função Global'!$C$39 -> Amortecer impacto | H5: Desempenho funcional | I5: ='Função Global'!$B$39 -> F01 | J5: Requer função | K5: ='Especificação Meta'!E6 -> ≤ 35 g de pico transmitido à louça, e sempre abaixo do resultado da embalagem atual no mesmo ensaio
B6: ='Requisito de Projeto'!C4 -> RP2 | C6: ='Requisito de Projeto'!B4 -> Imobilizar a louça | E6: V02 | F6: Conservar posição relativa e verificar o deslocamento após o ciclo. | G6: ='Função Global'!$C$40 -> Imobilizar louça | H6: Desempenho funcional | I6: ='Função Global'!$B$40 -> F02 | J6: Requer função | K6: ='Especificação Meta'!E7 -> ≤ 6 mm de deslocamento residual após o ciclo de distribuição
B7: ='Requisito de Projeto'!C5 -> RP3 | C7: ='Requisito de Projeto'!B5 -> Ser de fácil movimentação | E7: V03 | F7: Portar com pega e apoio; 150 N é força de partida ao empurrar/puxar, não limite de levantamento. | G7: ='Função Global'!$C$41&"; "&'Função Global'!$C$43 -> Portar louça; Prover pega | H7: Ergonomia / desempenho | I7: ='Função Global'!$B$41&", "&'Função Global'!$B$43 -> F03, F05 | J7: Qualifica funções | K7: ='Especificação Meta'!E8 -> ≤ 150 N de força de partida com o conjunto carregado, em piso de canteiro
B8: ='Requisito de Projeto'!C6 -> RP4 | C8: ='Requisito de Projeto'!B6 -> Permitir conferência sem abrir | E8: V04 | F8: Expor a área crítica real da cerâmica; indicador de evento não substitui inspeção. | G8: ='Função Global'!$C$42 -> Expor condição | H8: Inspeção / desempenho | I8: ='Função Global'!$B$42 -> F04 | J8: Requer função | K8: ='Especificação Meta'!E9 -> ≥ 60% da área crítica verificável com o conjunto fechado
B9: ='Requisito de Projeto'!C7 -> RP5 | C9: ='Requisito de Projeto'!B7 -> Ter pontos de pega definidos | E9: V05 | F9: Prover pontos para mão enluvada; confirmar vão, acesso e aplicação de força. | G9: ='Função Global'!$C$43 -> Prover pega | H9: Interface ergonômica | I9: ='Função Global'!$B$43 -> F05 | J9: Qualifica interface | K9: ='Especificação Meta'!E10 -> ≥ 2 pontos de pega com vão livre compatível com mão enluvada
B10: ='Requisito de Projeto'!C8 -> RP6 | C10: ='Requisito de Projeto'!B8 -> Ter retirada segura da louça | E10: V06 | F10: Conter fragmentos em transporte, abertura e retirada segura. | G10: ='Função Global'!$C$44 -> Reter fragmentos | H10: Segurança / desempenho | I10: ='Função Global'!$B$44 -> F06 | J10: Requer função | K10: ='Especificação Meta'!E11 -> ≥ 90% da massa de fragmentos retida no interior
B11: ='Requisito de Projeto'!C9 -> RP7 | C11: ='Requisito de Projeto'!B9 -> Ser ajustável a diferentes louças | E11: V07 | F11: Acomodar a amplitude na mesma configuração; não trocar insertos durante ajuste. | G11: ='Função Global'!$C$45 -> Acomodar variação | H11: Adaptabilidade | I11: ='Função Global'!$B$45 -> F07 | J11: Requer capacidade | K11: ='Especificação Meta'!E12 -> ≥ 300 mm no eixo A e ≥ 150 mm no eixo B, sem troca de componentes no ajuste
B12: ='Requisito de Projeto'!C10 -> RP8 | C12: ='Requisito de Projeto'!B10 -> Ser compatível com o veículo | E12: V08 | F12: Ocupar o palete e compatibilizar o conjunto com transporte e amarração. | G12: ='Função Global'!$C$46&"; "&'Função Global'!$C$41 -> Compatibilizar carga; Portar louça | H12: Interface / geometria | I12: ='Função Global'!$B$46&", "&'Função Global'!$B$41 -> F08, F03 | J12: Restringe interface | K12: ='Especificação Meta'!E13 -> ≥ 80% de ocupação da área do PBR 1200 × 1000 mm; alvo de otimização ≥ 90%
B13: ='Requisito de Projeto'!C11 -> RP9 | C13: ='Requisito de Projeto'!B11 -> Ser estável quando apoiado | E13: V09 | F13: Estabilizar o conjunto carregado e verificar o limite de tombamento. | G13: ='Função Global'!$C$47 -> Estabilizar conjunto | H13: Estabilidade / segurança | I13: ='Função Global'!$B$47 -> F09 | J13: Qualifica função | K13: ='Especificação Meta'!E14 -> ≥ 40° de ângulo de tombamento com o conjunto carregado
B14: ='Requisito de Projeto'!C12 -> RP10 | C14: ='Requisito de Projeto'!B12 -> Ser de uso intuitivo | E14: V10 | F14: Orientação e indicação de ação integram Comunicar uso; não criar função duplicada. | G14: ='Função Global'!$C$51 -> Comunicar uso | H14: Usabilidade | I14: ='Função Global'!$B$51 -> F16 | J14: Atributo de uso | K14: ='Especificação Meta'!E15 -> ≤ 7 etapas até o primeiro uso correto, sem consultar instrução
B15: ='Requisito de Projeto'!C13 -> RP11 | C15: ='Requisito de Projeto'!B13 -> Ser empilhável | E15: V11 | F15: Suportar compressão pelo caminho de carga, preservando a louça. | G15: ='Função Global'!$C$48 -> Suportar carga | H15: Desempenho estrutural | I15: ='Função Global'!$B$48 -> F11 | J15: Qualifica função | K15: ='Especificação Meta'!E16 -> ≥ 7,5 kN de carga de compressão sem perda de proteção
B16: ='Requisito de Projeto'!C14 -> RP12 | C16: ='Requisito de Projeto'!B14 -> Ter desempenho uniforme | E16: V12 | F16: Uniformidade qualifica Amortecer impacto. Não constitui outra função independente. | G16: ='Função Global'!$C$39 -> Amortecer impacto | H16: Qualidade / uniformidade | I16: ='Função Global'!$B$39 -> F01 | J16: Atributo de função | K16: ='Especificação Meta'!E17 -> ≤ 10% de coeficiente de variação do pico de aceleração
B17: ='Requisito de Projeto'!C15 -> RP13 | C17: ='Requisito de Projeto'!B15 -> Ser resistente a intempéries | E17: V13 | F17: Manter capacidade de compressão após umidade. Derivar bloqueio de água apenas se o princípio escolhido exigir. | G17: ='Função Global'!$C$48 -> Suportar carga | H17: Condição ambiental | I17: ='Função Global'!$B$48 -> F11 | J17: Atributo sob condição | K17: ='Especificação Meta'!E18 -> ≤ 12,5% de perda da carga de compressão após 48 h em câmara úmida
B18: ='Requisito de Projeto'!C16 -> RP14 | C18: ='Requisito de Projeto'!B16 -> Ser compacto | E18: V14 | F18: Limitar o envelope carregado pela geometria; recolher partes é ação auxiliar de retorno, não prova da meta carregada. | G18: ='Função Global'!$C$41&"; "&'Função Global'!$C$46&"; "&'Função Global'!$C$49 -> Portar louça; Compatibilizar carga; Recolher partes | H18: Restrição geométrica | I18: ='Função Global'!$B$41&", "&'Função Global'!$B$46&", "&'Função Global'!$B$49 -> F03, F08, F14 | J18: Restrição e suporte | K18: ='Especificação Meta'!E19 -> ≤ 0,090 m³/cuba e ≤ 0,160 m³/bacia individual, incluindo o dispositivo carregado
B19: ='Requisito de Projeto'!C17 -> RP15 | C19: ='Requisito de Projeto'!B17 -> Ter manutenção simples | E19: V15 | F19: Prover acesso, liberar e reunir partes para limpeza, inspeção e reposição. O tempo do ciclo continua obrigatório. | G19: ='Função Global'!$C$50&"; "&'Função Global'!$C$52&"; "&'Função Global'!$C$55 -> Prover acesso; Liberar partes; Unir partes | H19: Manutenibilidade | I19: ='Função Global'!$B$50&", "&'Função Global'!$B$52&", "&'Função Global'!$B$55 -> F15, F17, F22 | J19: Desdobra suporte | K19: ='Especificação Meta'!E20 -> ≤ 5 min por ciclo de limpeza, inspeção e reposição
B20: ='Requisito de Projeto'!C18 -> RP16 | C20: ='Requisito de Projeto'!B18 -> Ter indicação visual de uso | E20: V16 | F20: Comunicar uso com orientação e fechamento legíveis; não confundir com registro de impacto. | G20: ='Função Global'!$C$51 -> Comunicar uso | H20: Interface informacional | I20: ='Função Global'!$B$51 -> F16 | J20: Qualifica função | K20: ='Especificação Meta'!E21 -> ≥ 5 m de distância de leitura do modelo, do lado correto e da advertência
B21: ='Requisito de Projeto'!C19 -> RP17 | C21: ='Requisito de Projeto'!B19 -> Ser de fácil desmontagem | E21: V17 | F21: Liberar partes com o tempo e as condições de ferramenta previstos. | G21: ='Função Global'!$C$52 -> Liberar partes | H21: Desmontabilidade | I21: ='Função Global'!$B$52 -> F17 | J21: Qualifica função | K21: ='Especificação Meta'!E22 -> ≤ 120 s de desmontagem completa, sem ferramenta dedicada
B22: ='Requisito de Projeto'!C20 -> RP18 | C22: ='Requisito de Projeto'!B20 -> Ser reutilizável | E22: V18 | F22: Preservar proteção ao longo dos ciclos e viabilizar manutenção. Vida útil não é outra transformação nem carry-over. | G22: ='Função Global'!$C$39&"; "&'Função Global'!$C$40&"; "&'Função Global'!$C$48&"; "&'Função Global'!$C$50&"; "&'Função Global'!$C$52&"; "&'Função Global'!$C$55 -> Amortecer impacto; Imobilizar louça; Suportar carga; Prover acesso; Liberar partes; Unir partes | H22: Durabilidade | I22: ='Função Global'!$B$39&", "&'Função Global'!$B$40&", "&'Função Global'!$B$48&", "&'Função Global'!$B$50&", "&'Função Global'!$B$52&", "&'Função Global'!$B$55 -> F01, F02, F11, F15, F17, F22 | J22: Atributo e suporte | K22: ='Especificação Meta'!E23 -> ≥ 20 ciclos de reuso até a falha funcional
B23: ='Requisito de Projeto'!C21 -> RP19 | C23: ='Requisito de Projeto'!B21 -> Ter materiais recicláveis | E23: V19 | F23: Liberar partes e viabilizar separação material; composição e cadeia regional continuam critérios de RP19. | G23: ='Função Global'!$C$52&"; "&'Função Global'!$C$53 -> Liberar partes; Separar materiais | H23: Sustentabilidade | I23: ='Função Global'!$B$52&", "&'Função Global'!$B$53 -> F17, F19 | J23: Atributo e suporte | K23: ='Especificação Meta'!E24 -> ≥ 95% da massa em materiais com cadeia de reciclagem estabelecida
B24: ='Requisito de Projeto'!C22 -> RP20 | C24: ='Requisito de Projeto'!B22 -> Ter peças modulares | E24: V20 | F24: Acesso e uniões devem viabilizar troca independente. Contar três módulos requer demonstração física, não três funções. | G24: ='Função Global'!$C$50&"; "&'Função Global'!$C$52&"; "&'Função Global'!$C$55 -> Prover acesso; Liberar partes; Unir partes | H24: Restrição arquitetural | I24: ='Função Global'!$B$50&", "&'Função Global'!$B$52&", "&'Função Global'!$B$55 -> F15, F17, F22 | J24: Restringe arquitetura | K24: ='Especificação Meta'!E25 -> ≥ 3 módulos substituíveis de forma independente
B25: ='Requisito de Projeto'!C23 -> RP21 | C25: ='Requisito de Projeto'!B23 -> Ter identificação visível | E25: V21 | F25: Exibir identidade única da unidade, preservada na estrutura de referência após manutenção. | G25: ='Função Global'!$C$54 -> Exibir identidade | H25: Rastreabilidade | I25: ='Função Global'!$B$54 -> F21 | J25: Requer função | K25: ='Especificação Meta'!E26 -> 1 identificador único por unidade, legível após o ensaio cíclico e o condicionamento úmido
B26: ='Requisito de Projeto'!C24 -> RP22 | C26: ='Requisito de Projeto'!B24 -> Ter montagem em poucas etapas | E26: V22 | F26: Unir as partes no limite de ações e sem perder retenção ou estabilidade. | G26: ='Função Global'!$C$55 -> Unir partes | H26: Montabilidade | I26: ='Função Global'!$B$55 -> F22 | J26: Qualifica função | K26: ='Especificação Meta'!E27 -> ≤ 6 etapas de montagem e fechamento
B27: ='Requisito de Projeto'!C25 -> RP23 | C27: ='Requisito de Projeto'!B25 -> Ter baixo custo por ciclo de uso | E27: V23 | F27: O teto por ciclo restringe soluções, materiais, manutenção e retorno; custo não é função física do produto. | G27: Todas as funções e soluções, como restrição | H27: Restrição econômica | I27: Sem novo ID funcional | J27: Restrição transversal | K27: ='Especificação Meta'!E28 -> ≤ R$ 15 por ciclo de uso, com teto econômico no custo médio da avaria evitada
B30: V01–V23 são vínculos dos RP, não funções. O catálogo F abaixo contém 17 funções e capacidades de suporte. Uma função atende vários RP; um RP pode exigir várias funções. Metas e restrições continuam obrigatórias. | C30: V01–V23 são vínculos dos RP, não funções. O catálogo F abaixo contém 17 funções e capacidades de suporte. Uma função atende vários RP; um RP pode exigir várias funções. Metas e restrições continuam obrigatórias. | D30: V01–V23 são vínculos dos RP, não funções. O catálogo F abaixo contém 17 funções e capacidades de suporte. Uma função atende vários RP; um RP pode exigir várias funções. Metas e restrições continuam obrigatórias. | E30: V01–V23 são vínculos dos RP, não funções. O catálogo F abaixo contém 17 funções e capacidades de suporte. Uma função atende vários RP; um RP pode exigir várias funções. Metas e restrições continuam obrigatórias. | F30: V01–V23 são vínculos dos RP, não funções. O catálogo F abaixo contém 17 funções e capacidades de suporte. Uma função atende vários RP; um RP pode exigir várias funções. Metas e restrições continuam obrigatórias. | G30: V01–V23 são vínculos dos RP, não funções. O catálogo F abaixo contém 17 funções e capacidades de suporte. Uma função atende vários RP; um RP pode exigir várias funções. Metas e restrições continuam obrigatórias. | H30: V01–V23 são vínculos dos RP, não funções. O catálogo F abaixo contém 17 funções e capacidades de suporte. Uma função atende vários RP; um RP pode exigir várias funções. Metas e restrições continuam obrigatórias. | I30: V01–V23 são vínculos dos RP, não funções. O catálogo F abaixo contém 17 funções e capacidades de suporte. Uma função atende vários RP; um RP pode exigir várias funções. Metas e restrições continuam obrigatórias. | J30: V01–V23 são vínculos dos RP, não funções. O catálogo F abaixo contém 17 funções e capacidades de suporte. Uma função atende vários RP; um RP pode exigir várias funções. Metas e restrições continuam obrigatórias. | K30: V01–V23 são vínculos dos RP, não funções. O catálogo F abaixo contém 17 funções e capacidades de suporte. Uma função atende vários RP; um RP pode exigir várias funções. Metas e restrições continuam obrigatórias.
B32: Uniformidade qualifica F01; umidade qualifica F11; vida qualifica o desempenho nos ciclos. RP14 limita a geometria carregada; F14 trata do recolhimento vazio. RP20 limita a arquitetura e requer troca demonstrada. RP23 permanece restrição econômica. | C32: Uniformidade qualifica F01; umidade qualifica F11; vida qualifica o desempenho nos ciclos. RP14 limita a geometria carregada; F14 trata do recolhimento vazio. RP20 limita a arquitetura e requer troca demonstrada. RP23 permanece restrição econômica. | D32: Uniformidade qualifica F01; umidade qualifica F11; vida qualifica o desempenho nos ciclos. RP14 limita a geometria carregada; F14 trata do recolhimento vazio. RP20 limita a arquitetura e requer troca demonstrada. RP23 permanece restrição econômica. | E32: Uniformidade qualifica F01; umidade qualifica F11; vida qualifica o desempenho nos ciclos. RP14 limita a geometria carregada; F14 trata do recolhimento vazio. RP20 limita a arquitetura e requer troca demonstrada. RP23 permanece restrição econômica. | F32: Uniformidade qualifica F01; umidade qualifica F11; vida qualifica o desempenho nos ciclos. RP14 limita a geometria carregada; F14 trata do recolhimento vazio. RP20 limita a arquitetura e requer troca demonstrada. RP23 permanece restrição econômica. | G32: Uniformidade qualifica F01; umidade qualifica F11; vida qualifica o desempenho nos ciclos. RP14 limita a geometria carregada; F14 trata do recolhimento vazio. RP20 limita a arquitetura e requer troca demonstrada. RP23 permanece restrição econômica. | H32: Uniformidade qualifica F01; umidade qualifica F11; vida qualifica o desempenho nos ciclos. RP14 limita a geometria carregada; F14 trata do recolhimento vazio. RP20 limita a arquitetura e requer troca demonstrada. RP23 permanece restrição econômica. | I32: Uniformidade qualifica F01; umidade qualifica F11; vida qualifica o desempenho nos ciclos. RP14 limita a geometria carregada; F14 trata do recolhimento vazio. RP20 limita a arquitetura e requer troca demonstrada. RP23 permanece restrição econômica. | J32: Uniformidade qualifica F01; umidade qualifica F11; vida qualifica o desempenho nos ciclos. RP14 limita a geometria carregada; F14 trata do recolhimento vazio. RP20 limita a arquitetura e requer troca demonstrada. RP23 permanece restrição econômica. | K32: Uniformidade qualifica F01; umidade qualifica F11; vida qualifica o desempenho nos ciclos. RP14 limita a geometria carregada; F14 trata do recolhimento vazio. RP20 limita a arquitetura e requer troca demonstrada. RP23 permanece restrição econômica.
B34: OP-01: registro de evento é complemento exploratório, fora das 17 funções da base. Não substitui F04 nem integra automaticamente os requisitos. Fonte: síntese funcional da disciplina; NASA, Technical Requirements Definition e Logical Decomposition (links no relatório). | C34: OP-01: registro de evento é complemento exploratório, fora das 17 funções da base. Não substitui F04 nem integra automaticamente os requisitos. Fonte: síntese funcional da disciplina; NASA, Technical Requirements Definition e Logical Decomposition (links no relatório). | D34: OP-01: registro de evento é complemento exploratório, fora das 17 funções da base. Não substitui F04 nem integra automaticamente os requisitos. Fonte: síntese funcional da disciplina; NASA, Technical Requirements Definition e Logical Decomposition (links no relatório). | E34: OP-01: registro de evento é complemento exploratório, fora das 17 funções da base. Não substitui F04 nem integra automaticamente os requisitos. Fonte: síntese funcional da disciplina; NASA, Technical Requirements Definition e Logical Decomposition (links no relatório). | F34: OP-01: registro de evento é complemento exploratório, fora das 17 funções da base. Não substitui F04 nem integra automaticamente os requisitos. Fonte: síntese funcional da disciplina; NASA, Technical Requirements Definition e Logical Decomposition (links no relatório). | G34: OP-01: registro de evento é complemento exploratório, fora das 17 funções da base. Não substitui F04 nem integra automaticamente os requisitos. Fonte: síntese funcional da disciplina; NASA, Technical Requirements Definition e Logical Decomposition (links no relatório). | H34: OP-01: registro de evento é complemento exploratório, fora das 17 funções da base. Não substitui F04 nem integra automaticamente os requisitos. Fonte: síntese funcional da disciplina; NASA, Technical Requirements Definition e Logical Decomposition (links no relatório). | I34: OP-01: registro de evento é complemento exploratório, fora das 17 funções da base. Não substitui F04 nem integra automaticamente os requisitos. Fonte: síntese funcional da disciplina; NASA, Technical Requirements Definition e Logical Decomposition (links no relatório). | J34: OP-01: registro de evento é complemento exploratório, fora das 17 funções da base. Não substitui F04 nem integra automaticamente os requisitos. Fonte: síntese funcional da disciplina; NASA, Technical Requirements Definition e Logical Decomposition (links no relatório). | K34: OP-01: registro de evento é complemento exploratório, fora das 17 funções da base. Não substitui F04 nem integra automaticamente os requisitos. Fonte: síntese funcional da disciplina; NASA, Technical Requirements Definition e Logical Decomposition (links no relatório).
B36: Catálogo funcional — IDs mantidos quando compatíveis; suporte e interação também são funções | C36: Catálogo funcional — IDs mantidos quando compatíveis; suporte e interação também são funções | D36: Catálogo funcional — IDs mantidos quando compatíveis; suporte e interação também são funções | E36: Catálogo funcional — IDs mantidos quando compatíveis; suporte e interação também são funções | F36: Catálogo funcional — IDs mantidos quando compatíveis; suporte e interação também são funções | G36: Catálogo funcional — IDs mantidos quando compatíveis; suporte e interação também são funções | H36: Catálogo funcional — IDs mantidos quando compatíveis; suporte e interação também são funções | I36: Catálogo funcional — IDs mantidos quando compatíveis; suporte e interação também são funções | J36: Catálogo funcional — IDs mantidos quando compatíveis; suporte e interação também são funções | K36: Catálogo funcional — IDs mantidos quando compatíveis; suporte e interação também são funções
B38: ID função | C38: Função | D38: Nível | E38: Nível | F38: Efeito e fronteira | G38: RP associados | H38: Classe funcional | I38: Limite e verificação | J38: Limite e verificação | K38: Limite e verificação
B39: F01 | C39: Amortecer impacto | D39: Parcial | E39: Parcial | F39: Atenuar choque e vibração antes da energia chegar à cerâmica. | G39: RP1, RP12, RP18 | H39: Transformação | I39: Uniformidade e vida qualificam esta função; não são funções adicionais. | J39: Uniformidade e vida qualificam esta função; não são funções adicionais. | K39: Uniformidade e vida qualificam esta função; não são funções adicionais.
B40: F02 | C40: Imobilizar louça | D40: Parcial | E40: Parcial | F40: Conservar o posicionamento relativo da carga, na peça ou no volume conforme a fronteira. | G40: RP2, RP18 | H40: Técnica | I40: A função permanece requerida em M1/M2/M3; comparar deslocamento efetivo. | J40: A função permanece requerida em M1/M2/M3; comparar deslocamento efetivo. | K40: A função permanece requerida em M1/M2/M3; comparar deslocamento efetivo.
B41: F03 | C41: Portar louça | D41: Parcial | E41: Parcial | F41: Transferir a carga entre posições com interfaces de movimentação adequadas. | G41: RP3, RP8, RP14 | H41: Ergonômica | I41: Separar empurrar/puxar de levantar/carregar. Geometria e volume limitam a solução. | J41: Separar empurrar/puxar de levantar/carregar. Geometria e volume limitam a solução. | K41: Separar empurrar/puxar de levantar/carregar. Geometria e volume limitam a solução.
B42: F04 | C42: Expor condição | D42: Parcial | E42: Parcial | F42: Tornar a região crítica da cerâmica acessível à inspeção com o conjunto fechado. | G42: RP4 | H42: Interativa | I42: O acondicionamento original não pode bloquear o acesso requerido. | J42: O acondicionamento original não pode bloquear o acesso requerido. | K42: O acondicionamento original não pode bloquear o acesso requerido.
B43: F05 | C43: Prover pega | D43: Suporte | E43: Suporte | F43: Disponibilizar interfaces para aplicação de força pela mão enluvada. | G43: RP3, RP5 | H43: Ergonômica | I43: Quantidade, dimensões e acesso não demonstram ergonomia por si sós. | J43: Quantidade, dimensões e acesso não demonstram ergonomia por si sós. | K43: Quantidade, dimensões e acesso não demonstram ergonomia por si sós.
B44: F06 | C44: Reter fragmentos | D44: Parcial | E44: Parcial | F44: Conter fragmentos na quebra, inclusive durante abertura e retirada. | G44: RP6 | H44: Técnica | I44: Massa retida não elimina a verificação de fragmentos pequenos e risco de corte. | J44: Massa retida não elimina a verificação de fragmentos pequenos e risco de corte. | K44: Massa retida não elimina a verificação de fragmentos pequenos e risco de corte.
B45: F07 | C45: Acomodar variação | D45: Suporte | E45: Suporte | F45: Adaptar o posicionamento à faixa dimensional na mesma configuração. | G45: RP7 | H45: Estrutural | I45: Ajuste sem trocar partes; reposição por desgaste é manutenção. | J45: Ajuste sem trocar partes; reposição por desgaste é manutenção. | K45: Ajuste sem trocar partes; reposição por desgaste é manutenção.
... B58: Migração: F10 foi reunida em F16; F12 em F01; F13 associa RP13 a F11. F18 deixou de ser função autônoma: RP18 qualifica proteção e suporte ao reuso. RP20 usa acesso/liberação/união, sem F20 independente. F23 era restrição econômica. Esses IDs não foram reutilizados. | C58: Migração: F10 foi reunida em F16; F12 em F01; F13 associa RP13 a F11. F18 deixou de ser função autônoma: RP18 qualifica proteção e suporte ao reuso. RP20 usa acesso/liberação/união, sem F20 independente. F23 era restrição econômica. Esses IDs não foram reutilizados. | D58: Migração: F10 foi reunida em F16; F12 em F01; F13 associa RP13 a F11. F18 deixou de ser função autônoma: RP18 qualifica proteção e suporte ao reuso. RP20 usa acesso/liberação/união, sem F20 independente. F23 era restrição econômica. Esses IDs não foram reutilizados. | E58: Migração: F10 foi reunida em F16; F12 em F01; F13 associa RP13 a F11. F18 deixou de ser função autônoma: RP18 qualifica proteção e suporte ao reuso. RP20 usa acesso/liberação/união, sem F20 independente. F23 era restrição econômica. Esses IDs não foram reutilizados. | F58: Migração: F10 foi reunida em F16; F12 em F01; F13 associa RP13 a F11. F18 deixou de ser função autônoma: RP18 qualifica proteção e suporte ao reuso. RP20 usa acesso/liberação/união, sem F20 independente. F23 era restrição econômica. Esses IDs não foram reutilizados. | G58: Migração: F10 foi reunida em F16; F12 em F01; F13 associa RP13 a F11. F18 deixou de ser função autônoma: RP18 qualifica proteção e suporte ao reuso. RP20 usa acesso/liberação/união, sem F20 independente. F23 era restrição econômica. Esses IDs não foram reutilizados. | H58: Migração: F10 foi reunida em F16; F12 em F01; F13 associa RP13 a F11. F18 deixou de ser função autônoma: RP18 qualifica proteção e suporte ao reuso. RP20 usa acesso/liberação/união, sem F20 independente. F23 era restrição econômica. Esses IDs não foram reutilizados. | I58: Migração: F10 foi reunida em F16; F12 em F01; F13 associa RP13 a F11. F18 deixou de ser função autônoma: RP18 qualifica proteção e suporte ao reuso. RP20 usa acesso/liberação/união, sem F20 independente. F23 era restrição econômica. Esses IDs não foram reutilizados. | J58: Migração: F10 foi reunida em F16; F12 em F01; F13 associa RP13 a F11. F18 deixou de ser função autônoma: RP18 qualifica proteção e suporte ao reuso. RP20 usa acesso/liberação/união, sem F20 independente. F23 era restrição econômica. Esses IDs não foram reutilizados. | K58: Migração: F10 foi reunida em F16; F12 em F01; F13 associa RP13 a F11. F18 deixou de ser função autônoma: RP18 qualifica proteção e suporte ao reuso. RP20 usa acesso/liberação/união, sem F20 independente. F23 era restrição econômica. Esses IDs não foram reutilizados.
B60: Diagrama global revisado: peça descoberta, comum a MF-A/MF-B/MF-C. Catálogo de 17 funções e vínculos V01–V23 preservados. Figma: https://www.figma.com/design/hF2hV3uNVjhzfP6jEfPY7F/UNB?node-id=44-2

Sheet  FAST 
A1: 3
B2: FAST — finalidade e meios funcionais da proteção direta da louça
B3: ID | C3: Função | D3: Por quê? | E3: Como? | F3: Fluxo principal | G3: Critério de leitura
B4: FG | C4: Resguardar louça | D4: Finalidade do produto | E4: Imobilizar; amortecer; suportar e portar; expor condição; reter fragmentos. As capacidades de acesso, união, retorno e separação apoiam o ciclo de vida. | F4: Material, energia e sinal | G4: Função global
B5: ='Função Global'!$B$40 -> F02 | C5: ='Função Global'!$C$40 -> Imobilizar louça | D5: Resguardar louça | E5: Estabelecer contatos de apoio; restringir movimento relativo; acomodar a variação dimensional (F07). | F5: Material | G5: RP2 e RP7: ajustar na mesma configuração sem perder o posicionamento. A pressão de contato deve ser verificada.
B6: ='Função Global'!$B$39 -> F01 | C6: ='Função Global'!$C$39 -> Amortecer impacto | D6: Resguardar louça | E6: Receber solicitações; absorver e dissipar energia; limitar sua transmissão à cerâmica. | F6: Energia | G6: MF-A: junto à peça. MF-B: antes do conjunto portador. MF-C: dois estágios F01a/F01b. RP1/RP12/RP18 qualificam o efeito; não são funções novas.
B7: ='Função Global'!$B$41 -> F03 | C7: ='Função Global'!$C$41 -> Portar louça | D7: Resguardar louça | E7: Prover pega (F05); compatibilizar carga (F08); estabilizar conjunto (F09). | F7: Material e energia | G7: RP3/RP5/RP8/RP9/RP14: força, pega, palete, estabilidade e volume carregado. Não confundir força de partida com levantamento.
B8: ='Função Global'!$B$42 -> F04 | C8: ='Função Global'!$C$42 -> Expor condição | D8: Resguardar louça | E8: Disponibilizar caminho de observação até a área crítica; preservar a contenção durante a conferência. | F8: Sinal | G8: RP4 e RP6 devem ser atendidos juntos, com o conjunto fechado. Não basta enxergar uma parte sem relação com a área crítica.
B9: ='Função Global'!$B$44 -> F06 | C9: ='Função Global'!$C$44 -> Reter fragmentos | D9: Resguardar louça e permitir retirada segura | E9: Interceptar fragmentos; restringir sua passagem; preservar a barreira durante abertura e retirada. | F9: Material | G9: Retenção deve continuar durante abertura e retirada
B10: ='Função Global'!$B$50&", "&'Função Global'!$B$52&", "&'Função Global'!$B$53&", "&'Função Global'!$B$55 -> F15, F17, F19, F22 | C10: ='Função Global'!$C$50&"; "&'Função Global'!$C$52&"; "&'Função Global'!$C$53&"; "&'Função Global'!$C$55 -> Prover acesso; Liberar partes; Separar materiais; Unir partes | D10: Viabilizar manutenção, reposição, reuso e fim de vida | E10: Liberar uniões; expor regiões de limpeza e reposição; restabelecer uniões; separar frações materiais no fim de vida. | F10: Material e energia | G10: F15/F17/F22 viabilizam o acesso e a troca; F19 apoia a separação. O operador executa a manutenção. RP15/RP17/RP18/RP19/RP20 permanecem critérios.
B11: ='Função Global'!$B$51&", "&'Função Global'!$B$54 -> F16, F21 | C11: ='Função Global'!$C$51&"; "&'Função Global'!$C$54 -> Comunicar uso; Exibir identidade | D11: Permitir uso correto e controle do retorno | E11: Apresentar orientação e estado de fechamento; exibir identificação permanente e única. | F11: Sinal | G11: Identidade da unidade não é apenas código de modelo ou lote
B12: ='Função Global'!$B$49 -> F14 | C12: ='Função Global'!$C$49 -> Recolher partes | D12: Reduzir o volume do dispositivo vazio para retorno | E12: Reconfigurar as partes vazias após liberar as uniões necessárias, preservando a possibilidade de remontagem. | F12: Material e energia | G12: F14 atua no retorno vazio. Não comprova o volume externo carregado de RP14 nem define sozinho o princípio de recolhimento.
B13: ='Função Global'!$B$48 -> F11 | C13: ='Função Global'!$C$48 -> Suportar carga | D13: Resguardar a louça sob compressão | E13: Receber carga; distribuir esforços pelo caminho resistente; transferir carga aos apoios. | F13: Energia | G13: RP11/RP13: compatibilizar compressão seca e após umidade com o amortecimento. A posição de F01 não demonstra a capacidade resistente.
B14: Restrição | C14: Uniformidade, umidade, vida, volume, força, reciclagem e custo | D14: Atender condições e limites do produto | E14: Confrontar funções e soluções com os 23 RP e suas metas. | F14: Restrições | G14: Registrar atributos e restrições como critérios; custo não é transformação física.
B15: Leitura FAST: COMO? conduz aos meios; POR QUÊ? retorna à finalidade. As relações não representam uma sequência de tarefas. A posição de F01 no fluxo de energia diferencia MF-A/MF-B/MF-C, sem mudar a função global.
B17: OP-01 não integra MF-A/MF-B/MF-C nem as 17 funções base. Registrar impacto não substitui a inspeção da louça. Desdobramentos de F01 e dos demais meios não são novos requisitos nem módulos já definidos.
B19: Requisitos → catálogo funcional → FAST → MF-A/MF-B/MF-C → primeira Pugh. As metas, restrições e conflitos do QFD continuam obrigatórios. A morfológica escolhe princípios para a estrutura encaminhada; a MIM avalia portadores e interfaces depois dessa composição.

Sheet Funções Parciais
B2: Estruturas funcionais — MF-A/MF-B/MF-C sob proteção direta
B3: ID grupo | C3: Entendimento | D3: Funções associadas | E3: Classes funcionais | F3: IDs do catálogo | G3: Requisitos e condições
B4: MF-A — amortecimento na interface da peça. Peça descoberta após preparo no distribuidor; mesma função global e mesmas 23 metas.
B5: A.1 | C5: Suportar e portar. Receber e conduzir esforços pelo conjunto portador; portar e apoiar a carga com interfaces compatíveis. | D5: ='Função Global'!$C$48&"; "&'Função Global'!$C$41&"; "&'Função Global'!$C$43&"; "&'Função Global'!$C$46&"; "&'Função Global'!$C$47 -> Suportar carga; Portar louça; Prover pega; Compatibilizar carga; Estabilizar conjunto | E5: Estrutural; Ergonômica; Interativa | F5: ='Função Global'!$B$48&", "&'Função Global'!$B$41&", "&'Função Global'!$B$43&", "&'Função Global'!$B$46&", "&'Função Global'!$B$47 -> F11, F03, F05, F08, F09 | G5: RP3/RP5/RP8/RP9/RP11/RP13/RP14: caminho resistente, pega, movimentação, estabilidade e envelope carregado.
B6: A.2 | C6: Amortecer na interface. Atenuar choque e vibração junto aos apoios da louça, após o caminho portador. Verificar interação entre ajuste e resposta amortecedora. | D6: ='Função Global'!$C$39 -> Amortecer impacto | E6: Transformação | F6: ='Função Global'!$B$39 -> F01 | G6: RP1/RP12/RP18: atenuação junto à peça, repetibilidade e vida; confirmar em toda a faixa de ajuste.
B7: A.3 | C7: Acomodar e imobilizar. Adaptar contatos à peça e restringir seu movimento na interface protegida. | D7: ='Função Global'!$C$45&"; "&'Função Global'!$C$40 -> Acomodar variação; Imobilizar louça | E7: Técnica; Estrutural | F7: ='Função Global'!$B$45&", "&'Função Global'!$B$40 -> F07, F02 | G7: RP2/RP7: mesma configuração, faixa dimensional, deslocamento residual e pressão de contato.
B8: A.4 | C8: Expor condição e conter. Disponibilizar observação da área crítica mantendo a barreira fechada; conter fragmentos também na abertura e retirada. | D8: ='Função Global'!$C$42&"; "&'Função Global'!$C$44&"; "&'Função Global'!$C$51&"; "&'Função Global'!$C$54 -> Expor condição; Reter fragmentos; Comunicar uso; Exibir identidade | E8: Técnica; Interativa; Semântica | F8: ='Função Global'!$B$42&", "&'Função Global'!$B$44&", "&'Função Global'!$B$51&", "&'Função Global'!$B$54 -> F04, F06, F16, F21 | G8: RP4/RP6/RP10/RP16/RP21: inspeção fechada, contenção na retirada, orientação e identidade.
B9: A.5 | C9: Suportar retorno e manutenção. O produto disponibiliza acesso, uniões liberáveis, recolhimento vazio e separação material. O operador executa limpeza, inspeção e reposição. | D9: ='Função Global'!$C$49&"; "&'Função Global'!$C$50&"; "&'Função Global'!$C$52&"; "&'Função Global'!$C$55&"; "&'Função Global'!$C$53 -> Recolher partes; Prover acesso; Liberar partes; Unir partes; Separar materiais | E9: Interativa; Sintática; Adicional | F9: ='Função Global'!$B$49&", "&'Função Global'!$B$50&", "&'Função Global'!$B$52&", "&'Função Global'!$B$55&", "&'Função Global'!$B$53 -> F14, F15, F17, F22, F19 | G9: RP14/RP15/RP17/RP18/RP19/RP20/RP22: retorno vazio, acesso, liberação/união, vida, separação e troca independente.
B10: A.EMS | C10: Material: peça descoberta e eventuais fragmentos. Energia: transporte/manuseio, transmitida e dissipada. Sinal: comandos e informação visual de condição, orientação e identidade. | D10: Mesmo conjunto de fluxos; organização de F01/F11/F02 diferente. | E10: Material; Energia; Sinal | F10: FG | G10: As setas funcionais não são a sequência de tarefas do operador.
B11: R-A | C11: Uniformidade, umidade, vida, volume, modularidade e reciclabilidade qualificam as funções e restringem princípios e interfaces. | D11: Atributos e restrições preservados | E11: Restrição transversal | F11: — | G11: Todas as 23 metas continuam aplicáveis; F01a/F01b não ampliam o catálogo de 17 funções.
B12: R$-A | C12: O custo completo inclui preparo, transferência e destinação da embalagem retirada, retorno, manutenção, consumíveis e avaria residual. | D12: Restrição econômica transversal | E12: Restrição, sem ID funcional | F12: — | G12: RP23: comparar fronteiras equivalentes; não converter dado ausente em zero.
B14: MF-B — amortecimento antes do conjunto portador. Peça descoberta após preparo no distribuidor; mesma função global e mesmas 23 metas.
B15: B.1 | C15: Amortecer o conjunto. Atenuar choque e vibração antes do conjunto portador; a massa e a carga sustentada condicionam a resposta a verificar. | D15: ='Função Global'!$C$39 -> Amortecer impacto | E15: Transformação | F15: ='Função Global'!$B$39 -> F01 | G15: RP1/RP12/RP18: atenuação antes do conjunto portador, repetibilidade e vida; confirmar em toda a faixa de ajuste.
B16: B.2 | C16: Suportar e portar. Suportar e portar a carga após o estágio de amortecimento, preservando pega, estabilidade e interfaces de transporte. | D16: ='Função Global'!$C$48&"; "&'Função Global'!$C$41&"; "&'Função Global'!$C$43&"; "&'Função Global'!$C$46&"; "&'Função Global'!$C$47 -> Suportar carga; Portar louça; Prover pega; Compatibilizar carga; Estabilizar conjunto | E16: Estrutural; Ergonômica; Interativa | F16: ='Função Global'!$B$48&", "&'Função Global'!$B$41&", "&'Função Global'!$B$43&", "&'Função Global'!$B$46&", "&'Função Global'!$B$47 -> F11, F03, F05, F08, F09 | G16: RP3/RP5/RP8/RP9/RP11/RP13/RP14: caminho resistente, pega, movimentação, estabilidade e envelope carregado.
B17: B.3 | C17: Acomodar e imobilizar. Acomodar e imobilizar a peça no conjunto protegido. O contato ajustável não é o estágio de amortecimento proposto. | D17: ='Função Global'!$C$45&"; "&'Função Global'!$C$40 -> Acomodar variação; Imobilizar louça | E17: Técnica; Estrutural | F17: ='Função Global'!$B$45&", "&'Função Global'!$B$40 -> F07, F02 | G17: RP2/RP7: mesma configuração, faixa dimensional, deslocamento residual e pressão de contato.
B18: B.4 | C18: Expor condição e conter. Disponibilizar observação da área crítica mantendo a barreira fechada; conter fragmentos também na abertura e retirada. | D18: ='Função Global'!$C$42&"; "&'Função Global'!$C$44&"; "&'Função Global'!$C$51&"; "&'Função Global'!$C$54 -> Expor condição; Reter fragmentos; Comunicar uso; Exibir identidade | E18: Técnica; Interativa; Semântica | F18: ='Função Global'!$B$42&", "&'Função Global'!$B$44&", "&'Função Global'!$B$51&", "&'Função Global'!$B$54 -> F04, F06, F16, F21 | G18: RP4/RP6/RP10/RP16/RP21: inspeção fechada, contenção na retirada, orientação e identidade.
B19: B.5 | C19: Suportar retorno e manutenção. O produto disponibiliza acesso, uniões liberáveis, recolhimento vazio e separação material. O operador executa limpeza, inspeção e reposição. | D19: ='Função Global'!$C$49&"; "&'Função Global'!$C$50&"; "&'Função Global'!$C$52&"; "&'Função Global'!$C$55&"; "&'Função Global'!$C$53 -> Recolher partes; Prover acesso; Liberar partes; Unir partes; Separar materiais | E19: Interativa; Sintática; Adicional | F19: ='Função Global'!$B$49&", "&'Função Global'!$B$50&", "&'Função Global'!$B$52&", "&'Função Global'!$B$55&", "&'Função Global'!$B$53 -> F14, F15, F17, F22, F19 | G19: RP14/RP15/RP17/RP18/RP19/RP20/RP22: retorno vazio, acesso, liberação/união, vida, separação e troca independente.
B20: B.EMS | C20: Material: peça descoberta e eventuais fragmentos. Energia: transporte/manuseio, transmitida e dissipada. Sinal: comandos e informação visual de condição, orientação e identidade. | D20: Mesmo conjunto de fluxos; organização de F01/F11/F02 diferente. | E20: Material; Energia; Sinal | F20: FG | G20: As setas funcionais não são a sequência de tarefas do operador.
B21: R-B | C21: Uniformidade, umidade, vida, volume, modularidade e reciclabilidade qualificam as funções e restringem princípios e interfaces. | D21: Atributos e restrições preservados | E21: Restrição transversal | F21: — | G21: Todas as 23 metas continuam aplicáveis; F01a/F01b não ampliam o catálogo de 17 funções.
B22: R$-B | C22: O custo completo inclui preparo, transferência e destinação da embalagem retirada, retorno, manutenção, consumíveis e avaria residual. | D22: Restrição econômica transversal | E22: Restrição, sem ID funcional | F22: — | G22: RP23: comparar fronteiras equivalentes; não converter dado ausente em zero.
B24: MF-C — amortecimento em dois estágios. Peça descoberta após preparo no distribuidor; mesma função global e mesmas 23 metas.
B25: C.1 | C25: Amortecer no exterior. Primeiro estágio de F01: atenuar a solicitação externa antes do conjunto portador. | D25: ='Função Global'!$C$39 -> Amortecer impacto | E25: Transformação | F25: ='Função Global'!$B$39 -> F01 | G25: F01a: desdobramento de F01; RP1/RP12/RP18.
B26: C.2 | C26: Suportar e portar. Conduzir esforços e portar a carga entre os dois estágios de amortecimento. | D26: ='Função Global'!$C$48&"; "&'Função Global'!$C$41&"; "&'Função Global'!$C$43&"; "&'Função Global'!$C$46&"; "&'Função Global'!$C$47 -> Suportar carga; Portar louça; Prover pega; Compatibilizar carga; Estabilizar conjunto | E26: Estrutural; Ergonômica; Interativa | F26: ='Função Global'!$B$48&", "&'Função Global'!$B$41&", "&'Função Global'!$B$43&", "&'Função Global'!$B$46&", "&'Função Global'!$B$47 -> F11, F03, F05, F08, F09 | G26: RP3/RP5/RP8/RP9/RP11/RP13/RP14: caminho resistente, pega, movimentação, estabilidade e envelope carregado.
B27: C.3 | C27: Amortecer na interface. Segundo estágio de F01: atenuar solicitações residuais junto à peça. Compatibilizar a resposta dos dois estágios. | D27: ='Função Global'!$C$39 -> Amortecer impacto | E27: Transformação | F27: ='Função Global'!$B$39 -> F01 | G27: F01b: desdobramento de F01; compatibilizar estágios; RP1/RP2/RP12.
B28: C.4 | C28: Acomodar e imobilizar. Acomodar e imobilizar a louça na interface protegida, verificando movimento residual e contato em toda a faixa. | D28: ='Função Global'!$C$45&"; "&'Função Global'!$C$40 -> Acomodar variação; Imobilizar louça | E28: Técnica; Estrutural | F28: ='Função Global'!$B$45&", "&'Função Global'!$B$40 -> F07, F02 | G28: RP2/RP7: mesma configuração, faixa dimensional, deslocamento residual e pressão de contato.
B29: C.5 | C29: Expor condição e conter. Disponibilizar observação da área crítica mantendo a barreira fechada; conter fragmentos também na abertura e retirada. | D29: ='Função Global'!$C$42&"; "&'Função Global'!$C$44&"; "&'Função Global'!$C$51&"; "&'Função Global'!$C$54 -> Expor condição; Reter fragmentos; Comunicar uso; Exibir identidade | E29: Técnica; Interativa; Semântica | F29: ='Função Global'!$B$42&", "&'Função Global'!$B$44&", "&'Função Global'!$B$51&", "&'Função Global'!$B$54 -> F04, F06, F16, F21 | G29: RP4/RP6/RP10/RP16/RP21: inspeção fechada, contenção na retirada, orientação e identidade.
B30: C.6 | C30: Suportar retorno e manutenção. Disponibilizar acesso, união/liberação, retorno vazio e separação material, considerando os dois níveis de amortecimento. | D30: ='Função Global'!$C$49&"; "&'Função Global'!$C$50&"; "&'Função Global'!$C$52&"; "&'Função Global'!$C$55&"; "&'Função Global'!$C$53 -> Recolher partes; Prover acesso; Liberar partes; Unir partes; Separar materiais | E30: Interativa; Sintática; Adicional | F30: ='Função Global'!$B$49&", "&'Função Global'!$B$50&", "&'Função Global'!$B$52&", "&'Função Global'!$B$55&", "&'Função Global'!$B$53 -> F14, F15, F17, F22, F19 | G30: RP14/RP15/RP17/RP18/RP19/RP20/RP22: retorno vazio, acesso, liberação/união, vida, separação e troca independente.
B31: R-C | C31: Uniformidade, umidade, vida, volume, modularidade e reciclabilidade qualificam as funções e restringem princípios e interfaces. | D31: Atributos e restrições preservados | E31: Restrição transversal | F31: — | G31: Todas as 23 metas continuam aplicáveis; F01a/F01b não ampliam o catálogo de 17 funções.
B32: R$-C | C32: O custo completo inclui preparo, transferência e destinação da embalagem retirada, retorno, manutenção, consumíveis e avaria residual. | D32: Restrição econômica transversal | E32: Restrição, sem ID funcional | F32: — | G32: RP23: comparar fronteiras equivalentes; não converter dado ausente em zero.
B35: MF-A/MF-B/MF-C são organizações funcionais da mesma fronteira de proteção direta. F01a/F01b são dois estágios de F01, sem novos IDs-base. Todos os grupos são capacidades do produto, sem definir componentes, materiais ou módulos exclusivos.

Sheet Modelagem V0
B2: V0 — situação atual e limites da evidência
B3: Fluxo | C3: Entrada de referência | D3: Comportamento a investigar | E3: Saída observada ou pretendida | F3: Origem e limitação
B4: Material | C4: Louça acondicionada na embalagem original do fabricante | D4: A embalagem envolve e posiciona a peça; o comportamento dos fragmentos na abertura ainda precisa ser observado | E4: Relatos de peças recebidas trincadas; resíduos de embalagem após abertura | F4: Campo qualitativo. Sem taxa medida de avaria ou ensaio de retenção
B5: Energia | C5: Choques, vibração, compressão e esforço de movimentação | D5: Atenuação e deformação dependem da geometria, da umidade e do estado da embalagem | E5: 60–90 g e perda por umidade são referências/estimativas, não valores medidos no nosso fluxo | F5: 334 N decorrem de 34 kg × 9,81. Força de rolamento é outra grandeza e depende do meio auxiliar
B6: Sinal | C6: Modelo, orientação e advertência impressos; condição interna não verificada | D6: Papelão opaco limita a observação da cerâmica; ausência de registro de choque não significa integridade | E6: A conferência da peça requer abertura ou uma interface específica de inspeção | F6: Observação qualitativa e descrição da embalagem. Não demonstrada detecção de trinca fechada
B9: Diagnóstico: o campo sustenta o problema e o recorte, mas não comprova aceleração, taxa de avaria, perda de rigidez ou causalidade por etapa. A modelagem V0 organiza o plano de medição; não confirma desempenho de nenhuma alternativa.

Sheet Modelagens Alternativas
B2: Modelagens funcionais — proteção direta da louça e alternativas de amortecimento
B3: Modelo | C3: Fronteira material | D3: Organização da energia | E3: Sinal e contenção | F3: Oportunidade funcional | G3: Condição para prosseguir
B4: MF-A — interface | C4: Peça descoberta após preparo no distribuidor. | D4: F11 → F01 → F02. O amortecimento atua junto à interface da peça. | E4: F04/F06: inspeção com barreira fechada e retenção também na retirada. F16/F21: orientação e identidade. | F4: Conciliar proteção, posicionamento e ajuste diretamente nos apoios da peça. | G4: Verificar pressão, ajuste e amortecimento no mix; MF-A é datum da nova primeira Pugh.
B5: MF-B — conjunto portador | C5: Mesma peça descoberta e mesma operação de preparo. | D5: F01 → F11 → F02. Amortecer antes do conjunto portador. | E5: Mesmas funções obrigatórias de inspeção, contenção, orientação e identidade. | F5: Separar o estágio de amortecimento do contato diretamente ajustável à cerâmica. | G5: Selecionada na primeira Pugh para desenvolvimento: potencial de ajuste e acesso sob H3/H4. Verificar proteção, carga, compressão, estabilidade, volume, vida e custo; nove AV permanecem abertos.
B6: MF-C — dois estágios | C6: Mesma peça descoberta e mesma operação de preparo. | D6: F01a → F11 → F01b → F02. F01a/F01b são desdobramentos de F01. | E6: Mesmas funções obrigatórias; nenhum sensor de impacto na base. | F6: Distribuir a atenuação entre nível externo e interface da peça, hipótese a comparar. | G6: Dois estágios não garantem melhor proteção; verificar interação, movimento residual, volume, manutenção e custo.
B9: Fluxo comum ao trio | C9: Estado recebido | D9: Funções relacionadas | E9: Estado pretendido | F9: RP relacionados | G9: Verificação
B10: Material | C10: Louça descoberta após preparo. | D10: F07/F02: acomodar e imobilizar; F03: portar; F06: reter fragmentos. | E10: Louça protegida; fragmentos contidos se ocorrer quebra. | F10: RP2/RP5/RP6/RP7/RP8/RP9 | G10: Deslocamento, mix, pega, arranjo, estabilidade e contenção também na abertura.
B11: Energia | C11: Energia mecânica do transporte e manuseio. | D11: F01/F11/F03: amortecer, suportar e portar; posições distintas em MF-A/B/C. | E11: Energia transmitida à peça e energia dissipada; limites ainda a demonstrar. | F11: RP1/RP3/RP11/RP12/RP13 | G11: Instrumentar peça; verificar amortecimento e sustentação no mesmo conjunto.
B12: Sinal | C12: Comandos de uso do operador. | D12: F04/F16/F21: expor condição, comunicar uso e exibir identidade. | E12: Informação visual da condição, orientação e identidade. | F12: RP4/RP10/RP16/RP21 | G12: Área crítica visível com conjunto fechado; legibilidade, identidade e ações.
B14: Mix preliminar: cubas e corpos de bacias/vasos individuais conforme faixas, massas e cenários da aba Dados. Proteção direta mantida como fronteira comum. M1/M2/M3 são fronteiras históricas; MF-A/MF-B/MF-C são estruturas funcionais; C1/C2/C3 são combinações físicas a revisar.
B17: Premissa provisória | C17: Valor | D17: Unidade | E17: Origem | F17: Situação | G17: Uso
B18: Aquisição do dispositivo | C18: 300 | D18: R$ | E18: Hipótese já usada no projeto | F18: Estimativa | G18: Não é cotação da M3
B19: Vida útil usada no cenário | C19: 20 | D19: ciclos | E19: Mínimo exploratório do RP18 | F19: A verificar | G19: A vida efetiva precisa de ensaio
B20: Embalagem descartável atual | C20: 15 | D20: R$/entrega | E20: Hipótese de compra industrial | F20: A confirmar | G20: Incluir se permanecer na operação
B21: Taxa de avaria atual | C21: 0.02 | D21: fração | E21: Hipótese do custo atual | F21: A medir | G21: Não foi medida em campo
B22: Custo da louça | C22: 500 | D22: R$/peça | E22: Hipótese de custo de reposição | F22: A confirmar | G22: Mesma população e operação
B23: Reentrega por ocorrência | C23: 120 | D23: R$/ocorrência | E23: Hipótese de logística | F23: A confirmar | G23: Ratear pela frequência de avaria
B24: Retorno do dispositivo | D24: R$/ciclo | E24: Logística reversa | F24: Sem medição | G24: Entrada requerida
B25: Manutenção | D25: R$/ciclo | E25: Limpeza, inspeção e reposição | F25: Sem medição | G25: Entrada requerida
B26: Consumíveis e sinal opcional | D26: R$/ciclo | E26: Cotação e frequência de reposição | F26: Sem medição | G26: Zero apenas se comprovado
B27: Taxa de avaria residual | D27: fração | E27: Ensaio/registro da nova operação | F27: Sem medição | G27: Entrada requerida
B30: Comparação | C30: Resultado | D30: Unidade | E30: Cálculo | F30: Interpretação | G30: Situação
B31: Cenário atual | C31: =IF(AND(COUNT(C20:C23)=4,C21>=0,C21<=1),C20+C21*(C22+C23),"Informe as premissas do cenário atual") -> 27.4 | D31: R$/entrega | E31: Embalagem + probabilidade × (louça + reentrega) | F31: Referência calculada sobre hipóteses | G31: Provisório
